Workbook

Sheet 00_Revision_cover
A1: BAAY PROJECTS LIMITED · RC 1526224
A2: Sales and customers — revised
A3: REVISED · 8 October 2026 · original sheets retained so their formulas still work
A5: The original sheets are unchanged. The revision is the two sheets added at the front: this cover, and IFRS15_recognition.
A6: Turnover remains the Sales_Ledger: 859 lines, ₦2,584,814,000 for 2023 to 2025. Nothing was added from the Exceptions tab, and nothing was scaled.
A7: IFRS15_recognition applies the revenue policy to each subscription and to uncontracted sales-ledger lines. Revenue, the receivable and the deferred income on that sheet are the figures in the revised financial statements.
A8: Land marked bought or closed starts from the contract value. The receivable is capped at the client-register balance, and revenue on the sheet is reduced by the same amount. That reduction is ₦515,131,000 across 2023 to 2025. If the register is incomplete, revenue and receivables are both understated. Housing is recognised only on evidenced handover. Other collections are deferred income.
A9: A receivable is only the unpaid balance of a recognised contract, and not above the register balance. Unpaid balances on contracts still deferred are not receivables. They are a pipeline, disclosed in the financial statements.
A10: Exclusions (co-ownership, service income, credit memos) stay off turnover. Co-ownership is a liability in the revised statements. Credit memos are non-cash and are not posted.
A11: Client-register rows dated 2026 are outside this revision.

Sheet IFRS15_recognition
A1: Sub ref | B1: Customer | C1: Product | D1: Project | E1: Status | F1: Contract value | G1: Policy | H1: Collections 2023 | I1: Collections 2024 | J1: Collections 2025 | K1: Revenue 2023 | L1: Revenue 2024 | M1: Revenue 2025 | N1: Receivable at 31 Dec 2025 | O1: Deferred income at 31 Dec 2025
A2: SB0001 | B2: Mr Meshack Osagie | C2: Housing | D2: Pacific Court | E2: PAID | F2: 10500000 | G2: Housing not yet handed over — receipts held as deferred income (contract liability) | H2: 0 | I2: 0 | J2: 0 | K2: 0 | L2: 0 | M2: 0 | N2: 0 | O2: 0
A3: SB0002 | B3: Temidayo Oniosun | C3: Housing | D3: Pacific Court | E3: PAID | F3: 52200000 | G3: Housing not yet handed over — receipts held as deferred income (contract liability) | H3: 0 | I3: 0 | J3: 0 | K3: 0 | L3: 0 | M3: 0 | N3: 0 | O3: 0
A4: SB0003 | B4: Mrs Agbaje | C4: Housing | D4: Pacific Court | E4: PAID | F4: 63000000 | G4: Housing not yet handed over — receipts held as deferred income (contract liability) | H4: 0 | I4: 0 | J4: 0 | K4: 0 | L4: 0 | M4: 0 | N4: 0 | O4: 0
A5: SB0004 | B5: Mrs Kate | C5: Housing | D5: Pacific Court | E5: REFUND | F5: 40000000 | G5: Housing not yet handed over — receipts held as deferred income (contract liability) | H5: 0 | I5: 0 | J5: 0 | K5: 0 | L5: 0 | M5: 0 | N5: 0 | O5: 0
A6: SB0005 | B6: Mrs Mo | C6: Housing | D6: Pacific Court | E6: PAID | F6: 47000000 | G6: Housing not yet handed over — receipts held as deferred income (contract liability) | H6: 0 | I6: 0 | J6: 0 | K6: 0 | L6: 0 | M6: 0 | N6: 0 | O6: 0
A7: SB0006 | B7: Mrs Ero | C7: Housing | D7: Pacific Court | E7: PAID | F7: 600000000 | G7: Housing not yet handed over — receipts held as deferred income (contract liability) | H7: 0 | I7: 0 | J7: 0 | K7: 0 | L7: 0 | M7: 0 | N7: 0 | O7: 0
A8: SB0007 | B8: Mr Rasaq Roqeeb | C8: Land | D8: Green City Phase 1 (Lantaba, Ketu-Epe) | E8: BOUGHT | F8: 3900000 | G8: Land control transferred (allocated / bought). Revenue at contract value | H8: 500000 | I8: 1150000 | J8: 0 | K8: 500000 | L8: 0 | M8: 0 | N8: 0 | O8: 1150000
A9: SB0008 | B9: OLAIYA SUNDAY TEMITOPE | C9: Land | D9: Green City Phase 1 (Lantaba, Ketu-Epe) | E9: BOUGHT | F9: 1500000 | G9: Land control transferred (allocated / bought). Revenue at contract value | H9: 0 | I9: 475000 | J9: 0 | K9: 0 | L9: 0 | M9: 0 | N9: 0 | O9: 475000
A10: SB0009 | B10: MOSHOOD TIJANI | C10: Land | D10: Green City Phase 1 (Lantaba, Ketu-Epe) | E10: BOUGHT | F10: 1500000 | G10: Land control transferred (allocated / bought). Revenue at contract value | H10: 1000000 | I10: 400000 | J10: 0 | K10: 1100000 | L10: 0 | M10: 0 | N10: 0 | O10: 300000
A11: SB0010 | B11: PROF OLUGBENGA AKINADE/MRS ARAWOMO OMOLOLA | C11: Land | D11: Green City Phase 1 (Lantaba, Ketu-Epe) | E11: BOUGHT | F11: 3600000 | G11: Land control transferred (allocated / bought). Revenue at contract value | H11: 0 | I11: 0 | J11: 0 | K11: 0 | L11: 0 | M11: 0 | N11: 0 | O11: 0
A12: SB0011 | B12: MR Damilare Ositade Owolabi | C12: Land | D12: Green City Phase 1 (Lantaba, Ketu-Epe) | E12: BOUGHT | F12: 1500000 | G12: Land control transferred (allocated / bought). Revenue at contract value | H12: 1500000 | I12: 135000 | J12: 0 | K12: 1500000 | L12: 0 | M12: 0 | N12: 0 | O12: 135000
A13: SB0012 | B13: Mr Tobi Adesina | C13: Land | D13: Green City Phase 1 (Lantaba, Ketu-Epe) | E13: INCENTIVES | F13: 1500000 | G13: Land subscription still paying / refund / no completed status — receipts deferred | H13: 0 | I13: 0 | J13: 0 | K13: 0 | L13: 0 | M13: 0 | N13: 0 | O13: 0
... A215: SB0214 | B215: Mrs and Mr Bidemi | C215: Housing | D215: Pacific Court | E215: ALMOST BOUGHT | F215: 0 | G215: Housing not yet handed over — receipts held as deferred income (contract liability) | H215: 0 | I215: 0 | J215: 0 | K215: 0 | L215: 0 | M215: 0 | N215: 0 | O215: 0
A216: UN-0001 | B216: Mr Olasupo Oladimeji | C216: Land | D216: Land (estate not stated in source) | F216: 0 | G216: Plot receipt with no open subscription — recognised in the year of receipt (turnover-register basis) | H216: 894000 | I216: 0 | J216: 0 | K216: 894000 | L216: 0 | M216: 0 | N216: 0 | O216: 0
A217: UN-0002 | B217: Mr Olasupo Oladimeji Muritala | C217: Land | D217: Land (estate not stated in source) | F217: 0 | G217: Plot receipt with no open subscription — recognised in the year of receipt (turnover-register basis) | H217: 2000000 | I217: 0 | J217: 0 | K217: 2000000 | L217: 0 | M217: 0 | N217: 0 | O217: 0
A218: UN-0003 | B218: Miss Oji Blessing Mary | C218: Land | D218: Land: corner piece premium | F218: 0 | G218: Plot receipt with no open subscription — recognised in the year of receipt (turnover-register basis) | H218: 0 | I218: 135000 | J218: 0 | K218: 0 | L218: 135000 | M218: 0 | N218: 0 | O218: 0
A219: UN-0004 | B219: Mrs Yohanna Paulina | C219: Land | D219: Land (estate not stated in source) | F219: 0 | G219: Plot receipt with no open subscription — recognised in the year of receipt (turnover-register basis) | H219: 300000 | I219: 0 | J219: 0 | K219: 300000 | L219: 0 | M219: 0 | N219: 0 | O219: 0
A220: UN-0005 | B220: Mr Taiwo John Adeleye | C220: Land | D220: Land (estate not stated in source) | F220: 0 | G220: Plot receipt with no open subscription — recognised in the year of receipt (turnover-register basis) | H220: 0 | I220: 0 | J220: 45000 | K220: 0 | L220: 0 | M220: 45000 | N220: 0 | O220: 0
A221: UN-0006 | B221: Mr Ogbu Pius Ejaka | C221: Land | D221: Land (estate not stated in source) | F221: 0 | G221: Plot receipt with no open subscription — recognised in the year of receipt (turnover-register basis) | H221: 1500000 | I221: 0 | J221: 6500000 | K221: 1500000 | L221: 0 | M221: 6500000 | N221: 0 | O221: 0
A222: UN-0007 | B222: Mr Ogbu Pius Ejaka | C222: Land | D222: Land: corner piece premium | F222: 0 | G222: Plot receipt with no open subscription — recognised in the year of receipt (turnover-register basis) | H222: 0 | I222: 135000 | J222: 0 | K222: 0 | L222: 135000 | M222: 0 | N222: 0 | O222: 0
A223: UN-0008 | B223: Mr & Mrs Adebayo Dada | C223: Land | D223: Land (estate not stated in source) | F223: 0 | G223: Plot receipt with no open subscription — recognised in the year of receipt (turnover-register basis) | H223: 3000000 | I223: 0 | J223: 0 | K223: 3000000 | L223: 0 | M223: 0 | N223: 0 | O223: 0
A224: UN-0009 | B224: Mr & Mrs Adebayo Dada | C224: Land | D224: Land: corner piece premium | F224: 0 | G224: Plot receipt with no open subscription — recognised in the year of receipt (turnover-register basis) | H224: 0 | I224: 135000 | J224: 0 | K224: 0 | L224: 135000 | M224: 0 | N224: 0 | O224: 0
A225: UN-0010 | B225: Mr Adebayo Dada | C225: Land | D225: Land (estate not stated in source) | F225: 0 | G225: Plot receipt with no open subscription — recognised in the year of receipt (turnover-register basis) | H225: 1300000 | I225: 0 | J225: 0 | K225: 1300000 | L225: 0 | M225: 0 | N225: 0 | O225: 0
A226: UN-0011 | B226: Mr Edun Ayobami Simeon | C226: Land | D226: Land: corner piece premium | F226: 0 | G226: Plot receipt with no open subscription — recognised in the year of receipt (turnover-register basis) | H226: 0 | I226: 135000 | J226: 0 | K226: 0 | L226: 135000 | M226: 0 | N226: 0 | O226: 0
A227: UN-0012 | B227: Mr Adebanjo Isaac | C227: Land | D227: Land (estate not stated in source) | F227: 0 | G227: Plot receipt with no open subscription — recognised in the year of receipt (turnover-register basis) | H227: 250000 | I227: 0 | J227: 0 | K227: 250000 | L227: 0 | M227: 0 | N227: 0 | O227: 0
... A362: UN-0147 | B362: Mr Opeodu Ayodele & Mr Daisi Omokoya | C362: Housing | D362: Gorge View Court (GVC Gbagada) | F362: 0 | G362: Housing receipt with no handover evidence — deferred income | H362: 0 | I362: 0 | J362: 250000000 | K362: 0 | L362: 0 | M362: 0 | N362: 0 | O362: 250000000
A363: Total | F363: 4016366740 | H363: 125620000 | I363: 594080600 | J363: 1865113400 | K363: 84117680 | L363: 350864060 | M363: 940893400 | N363: 14900000 | O363: 1223838860

Sheet Summary
A1: BAAY Projects Limited: sales and customer summary for the auditor, 2022 to 2025
A2: Prepared 2 October 2026 from the company Google Drive (not Xero). All figures are cash receipts per company records, in Naira. Every number below is a formula on the detail tabs.
A4: 1. Sales receipts by product line and year (Sales_Ledger)
A5: 2022 shows nil: no transaction-level receipts for 2022 exist on the Drive. Construction shows nil: no construction-contract receipts were found for 2022 to 2025.
A6: Product line | B6: 2022 | C6: 2023 | D6: 2024 | E6: 2025 | F6: Total 2022-2025
A7: Land: plot price / instalments | B7: =SUMIFS(Sales_Ledger!$J$5:$J$863,Sales_Ledger!$E$5:$E$863,"Land",Sales_Ledger!$D$5:$D$863,2022,Sales_Ledger!$F$5:$F$863,"Plot / unit price") | C7: =SUMIFS(Sales_Ledger!$J$5:$J$863,Sales_Ledger!$E$5:$E$863,"Land",Sales_Ledger!$D$5:$D$863,2023,Sales_Ledger!$F$5:$F$863,"Plot / unit price") | D7: =SUMIFS(Sales_Ledger!$J$5:$J$863,Sales_Ledger!$E$5:$E$863,"Land",Sales_Ledger!$D$5:$D$863,2024,Sales_Ledger!$F$5:$F$863,"Plot / unit price") | E7: =SUMIFS(Sales_Ledger!$J$5:$J$863,Sales_Ledger!$E$5:$E$863,"Land",Sales_Ledger!$D$5:$D$863,2025,Sales_Ledger!$F$5:$F$863,"Plot / unit price") | F7: =SUM(B7:E7)
A8: Land: ancillary charges (corner piece, documentation, development) | B8: =SUMIFS(Sales_Ledger!$J$5:$J$863,Sales_Ledger!$E$5:$E$863,"Land",Sales_Ledger!$D$5:$D$863,2022,Sales_Ledger!$F$5:$F$863,"Ancillary charge") | C8: =SUMIFS(Sales_Ledger!$J$5:$J$863,Sales_Ledger!$E$5:$E$863,"Land",Sales_Ledger!$D$5:$D$863,2023,Sales_Ledger!$F$5:$F$863,"Ancillary charge") | D8: =SUMIFS(Sales_Ledger!$J$5:$J$863,Sales_Ledger!$E$5:$E$863,"Land",Sales_Ledger!$D$5:$D$863,2024,Sales_Ledger!$F$5:$F$863,"Ancillary charge") | E8: =SUMIFS(Sales_Ledger!$J$5:$J$863,Sales_Ledger!$E$5:$E$863,"Land",Sales_Ledger!$D$5:$D$863,2025,Sales_Ledger!$F$5:$F$863,"Ancillary charge") | F8: =SUM(B8:E8)
A9: Housing: unit price / instalments | B9: =SUMIFS(Sales_Ledger!$J$5:$J$863,Sales_Ledger!$E$5:$E$863,"Housing",Sales_Ledger!$D$5:$D$863,2022,Sales_Ledger!$F$5:$F$863,"Plot / unit price") | C9: =SUMIFS(Sales_Ledger!$J$5:$J$863,Sales_Ledger!$E$5:$E$863,"Housing",Sales_Ledger!$D$5:$D$863,2023,Sales_Ledger!$F$5:$F$863,"Plot / unit price") | D9: =SUMIFS(Sales_Ledger!$J$5:$J$863,Sales_Ledger!$E$5:$E$863,"Housing",Sales_Ledger!$D$5:$D$863,2024,Sales_Ledger!$F$5:$F$863,"Plot / unit price") | E9: =SUMIFS(Sales_Ledger!$J$5:$J$863,Sales_Ledger!$E$5:$E$863,"Housing",Sales_Ledger!$D$5:$D$863,2025,Sales_Ledger!$F$5:$F$863,"Plot / unit price") | F9: =SUM(B9:E9)
A10: Construction | B10: =SUMIFS(Sales_Ledger!$J$5:$J$863,Sales_Ledger!$E$5:$E$863,"Construction",Sales_Ledger!$D$5:$D$863,2022) | C10: =SUMIFS(Sales_Ledger!$J$5:$J$863,Sales_Ledger!$E$5:$E$863,"Construction",Sales_Ledger!$D$5:$D$863,2023) | D10: =SUMIFS(Sales_Ledger!$J$5:$J$863,Sales_Ledger!$E$5:$E$863,"Construction",Sales_Ledger!$D$5:$D$863,2024) | E10: =SUMIFS(Sales_Ledger!$J$5:$J$863,Sales_Ledger!$E$5:$E$863,"Construction",Sales_Ledger!$D$5:$D$863,2025) | F10: =SUM(B10:E10)
A11: Total sales receipts | B11: =SUM(B7:B10) | C11: =SUM(C7:C10) | D11: =SUM(D7:D10) | E11: =SUM(E7:E10) | F11: =SUM(F7:F10)
A12: Check: agrees to Sales_Ledger total (should be 0) | F12: =F11-SUM(Sales_Ledger!$J$5:$J$863)
A14: 2. How each year's receipts were sourced
A15: The basis tells the auditor how much reliance the list can bear before agreeing it to bank statements.
A16: Population basis | B16: 2022 | C16: 2023 | D16: 2024 | E16: 2025 | F16: Total
A17: Monthly turnover register (Dec 2023 to Dec 2024) | B17: =SUMIFS(Sales_Ledger!$J$5:$J$863,Sales_Ledger!$L$5:$L$863,"Primary: monthly turnover register",Sales_Ledger!$D$5:$D$863,2022) | C17: =SUMIFS(Sales_Ledger!$J$5:$J$863,Sales_Ledger!$L$5:$L$863,"Primary: monthly turnover register",Sales_Ledger!$D$5:$D$863,2023) | D17: =SUMIFS(Sales_Ledger!$J$5:$J$863,Sales_Ledger!$L$5:$L$863,"Primary: monthly turnover register",Sales_Ledger!$D$5:$D$863,2024) | E17: =SUMIFS(Sales_Ledger!$J$5:$J$863,Sales_Ledger!$L$5:$L$863,"Primary: monthly turnover register",Sales_Ledger!$D$5:$D$863,2025) | F17: =SUM(B17:E17)
A18: Turnover schedule, Green City Ph1/Ph2 (Jan to Nov 2023) | B18: =SUMIFS(Sales_Ledger!$J$5:$J$863,Sales_Ledger!$L$5:$L$863,"Secondary: turnover schedule (Green City Ph1/Ph2 payment history); no monthly turnover register for this period",Sales_Ledger!$D$5:$D$863,2022) | C18: =SUMIFS(Sales_Ledger!$J$5:$J$863,Sales_Ledger!$L$5:$L$863,"Secondary: turnover schedule (Green City Ph1/Ph2 payment history); no monthly turnover register for this period",Sales_Ledger!$D$5:$D$863,2023) | D18: =SUMIFS(Sales_Ledger!$J$5:$J$863,Sales_Ledger!$L$5:$L$863,"Secondary: turnover schedule (Green City Ph1/Ph2 payment history); no monthly turnover register for this period",Sales_Ledger!$D$5:$D$863,2024) | E18: =SUMIFS(Sales_Ledger!$J$5:$J$863,Sales_Ledger!$L$5:$L$863,"Secondary: turnover schedule (Green City Ph1/Ph2 payment history); no monthly turnover register for this period",Sales_Ledger!$D$5:$D$863,2025) | F18: =SUM(B18:E18)
A19: Sales commission records (Jan to Nov 2023, and all of 2025) | B19: =SUMIFS(Sales_Ledger!$J$5:$J$863,Sales_Ledger!$L$5:$L$863,"Secondary: commission records; no monthly turnover register for this period",Sales_Ledger!$D$5:$D$863,2022) | C19: =SUMIFS(Sales_Ledger!$J$5:$J$863,Sales_Ledger!$L$5:$L$863,"Secondary: commission records; no monthly turnover register for this period",Sales_Ledger!$D$5:$D$863,2023) | D19: =SUMIFS(Sales_Ledger!$J$5:$J$863,Sales_Ledger!$L$5:$L$863,"Secondary: commission records; no monthly turnover register for this period",Sales_Ledger!$D$5:$D$863,2024) | E19: =SUMIFS(Sales_Ledger!$J$5:$J$863,Sales_Ledger!$L$5:$L$863,"Secondary: commission records; no monthly turnover register for this period",Sales_Ledger!$D$5:$D$863,2025) | F19: =SUM(B19:E19)
A20: Total | B20: =SUM(B17:B19) | C20: =SUM(C17:C19) | D20: =SUM(D17:D19) | E20: =SUM(E17:E19) | F20: =SUM(F17:F19)
A22: 3. Sales receipts by project / estate and year
A23: Project / estate | B23: 2022 | C23: 2023 | D23: 2024 | E23: 2025 | F23: Total
A24: Baay Foreshore | B24: =SUMIFS(Sales_Ledger!$J$5:$J$863,Sales_Ledger!$G$5:$G$863,$A24,Sales_Ledger!$D$5:$D$863,2022) | C24: =SUMIFS(Sales_Ledger!$J$5:$J$863,Sales_Ledger!$G$5:$G$863,$A24,Sales_Ledger!$D$5:$D$863,2023) | D24: =SUMIFS(Sales_Ledger!$J$5:$J$863,Sales_Ledger!$G$5:$G$863,$A24,Sales_Ledger!$D$5:$D$863,2024) | E24: =SUMIFS(Sales_Ledger!$J$5:$J$863,Sales_Ledger!$G$5:$G$863,$A24,Sales_Ledger!$D$5:$D$863,2025) | F24: =SUM(B24:E24)
A25: Gorge View Court (GVC Gbagada) | B25: =SUMIFS(Sales_Ledger!$J$5:$J$863,Sales_Ledger!$G$5:$G$863,$A25,Sales_Ledger!$D$5:$D$863,2022) | C25: =SUMIFS(Sales_Ledger!$J$5:$J$863,Sales_Ledger!$G$5:$G$863,$A25,Sales_Ledger!$D$5:$D$863,2023) | D25: =SUMIFS(Sales_Ledger!$J$5:$J$863,Sales_Ledger!$G$5:$G$863,$A25,Sales_Ledger!$D$5:$D$863,2024) | E25: =SUMIFS(Sales_Ledger!$J$5:$J$863,Sales_Ledger!$G$5:$G$863,$A25,Sales_Ledger!$D$5:$D$863,2025) | F25: =SUM(B25:E25)
A26: Green City Ibadan (Akinyele-Moniya) | B26: =SUMIFS(Sales_Ledger!$J$5:$J$863,Sales_Ledger!$G$5:$G$863,$A26,Sales_Ledger!$D$5:$D$863,2022) | C26: =SUMIFS(Sales_Ledger!$J$5:$J$863,Sales_Ledger!$G$5:$G$863,$A26,Sales_Ledger!$D$5:$D$863,2023) | D26: =SUMIFS(Sales_Ledger!$J$5:$J$863,Sales_Ledger!$G$5:$G$863,$A26,Sales_Ledger!$D$5:$D$863,2024) | E26: =SUMIFS(Sales_Ledger!$J$5:$J$863,Sales_Ledger!$G$5:$G$863,$A26,Sales_Ledger!$D$5:$D$863,2025) | F26: =SUM(B26:E26)
A27: Green City Phase 1 (Ketu-Epe) | B27: =SUMIFS(Sales_Ledger!$J$5:$J$863,Sales_Ledger!$G$5:$G$863,$A27,Sales_Ledger!$D$5:$D$863,2022) | C27: =SUMIFS(Sales_Ledger!$J$5:$J$863,Sales_Ledger!$G$5:$G$863,$A27,Sales_Ledger!$D$5:$D$863,2023) | D27: =SUMIFS(Sales_Ledger!$J$5:$J$863,Sales_Ledger!$G$5:$G$863,$A27,Sales_Ledger!$D$5:$D$863,2024) | E27: =SUMIFS(Sales_Ledger!$J$5:$J$863,Sales_Ledger!$G$5:$G$863,$A27,Sales_Ledger!$D$5:$D$863,2025) | F27: =SUM(B27:E27)
A28: Green City Phase 1 (Lantaba, Ketu-Epe) | B28: =SUMIFS(Sales_Ledger!$J$5:$J$863,Sales_Ledger!$G$5:$G$863,$A28,Sales_Ledger!$D$5:$D$863,2022) | C28: =SUMIFS(Sales_Ledger!$J$5:$J$863,Sales_Ledger!$G$5:$G$863,$A28,Sales_Ledger!$D$5:$D$863,2023) | D28: =SUMIFS(Sales_Ledger!$J$5:$J$863,Sales_Ledger!$G$5:$G$863,$A28,Sales_Ledger!$D$5:$D$863,2024) | E28: =SUMIFS(Sales_Ledger!$J$5:$J$863,Sales_Ledger!$G$5:$G$863,$A28,Sales_Ledger!$D$5:$D$863,2025) | F28: =SUM(B28:E28)
A29: Green City Phase 2 (Idobi, Ketu-Epe) | B29: =SUMIFS(Sales_Ledger!$J$5:$J$863,Sales_Ledger!$G$5:$G$863,$A29,Sales_Ledger!$D$5:$D$863,2022) | C29: =SUMIFS(Sales_Ledger!$J$5:$J$863,Sales_Ledger!$G$5:$G$863,$A29,Sales_Ledger!$D$5:$D$863,2023) | D29: =SUMIFS(Sales_Ledger!$J$5:$J$863,Sales_Ledger!$G$5:$G$863,$A29,Sales_Ledger!$D$5:$D$863,2024) | E29: =SUMIFS(Sales_Ledger!$J$5:$J$863,Sales_Ledger!$G$5:$G$863,$A29,Sales_Ledger!$D$5:$D$863,2025) | F29: =SUM(B29:E29)
A30: Green City Phase 2 (Ketu-Epe) | B30: =SUMIFS(Sales_Ledger!$J$5:$J$863,Sales_Ledger!$G$5:$G$863,$A30,Sales_Ledger!$D$5:$D$863,2022) | C30: =SUMIFS(Sales_Ledger!$J$5:$J$863,Sales_Ledger!$G$5:$G$863,$A30,Sales_Ledger!$D$5:$D$863,2023) | D30: =SUMIFS(Sales_Ledger!$J$5:$J$863,Sales_Ledger!$G$5:$G$863,$A30,Sales_Ledger!$D$5:$D$863,2024) | E30: =SUMIFS(Sales_Ledger!$J$5:$J$863,Sales_Ledger!$G$5:$G$863,$A30,Sales_Ledger!$D$5:$D$863,2025) | F30: =SUM(B30:E30)
A31: Green City Phase 3 (Omu-Epe) | B31: =SUMIFS(Sales_Ledger!$J$5:$J$863,Sales_Ledger!$G$5:$G$863,$A31,Sales_Ledger!$D$5:$D$863,2022) | C31: =SUMIFS(Sales_Ledger!$J$5:$J$863,Sales_Ledger!$G$5:$G$863,$A31,Sales_Ledger!$D$5:$D$863,2023) | D31: =SUMIFS(Sales_Ledger!$J$5:$J$863,Sales_Ledger!$G$5:$G$863,$A31,Sales_Ledger!$D$5:$D$863,2024) | E31: =SUMIFS(Sales_Ledger!$J$5:$J$863,Sales_Ledger!$G$5:$G$863,$A31,Sales_Ledger!$D$5:$D$863,2025) | F31: =SUM(B31:E31)
A32: Green City Phase 3 Extension (Omu-Epe) | B32: =SUMIFS(Sales_Ledger!$J$5:$J$863,Sales_Ledger!$G$5:$G$863,$A32,Sales_Ledger!$D$5:$D$863,2022) | C32: =SUMIFS(Sales_Ledger!$J$5:$J$863,Sales_Ledger!$G$5:$G$863,$A32,Sales_Ledger!$D$5:$D$863,2023) | D32: =SUMIFS(Sales_Ledger!$J$5:$J$863,Sales_Ledger!$G$5:$G$863,$A32,Sales_Ledger!$D$5:$D$863,2024) | E32: =SUMIFS(Sales_Ledger!$J$5:$J$863,Sales_Ledger!$G$5:$G$863,$A32,Sales_Ledger!$D$5:$D$863,2025) | F32: =SUM(B32:E32)
A33: Heritage Garden | B33: =SUMIFS(Sales_Ledger!$J$5:$J$863,Sales_Ledger!$G$5:$G$863,$A33,Sales_Ledger!$D$5:$D$863,2022) | C33: =SUMIFS(Sales_Ledger!$J$5:$J$863,Sales_Ledger!$G$5:$G$863,$A33,Sales_Ledger!$D$5:$D$863,2023) | D33: =SUMIFS(Sales_Ledger!$J$5:$J$863,Sales_Ledger!$G$5:$G$863,$A33,Sales_Ledger!$D$5:$D$863,2024) | E33: =SUMIFS(Sales_Ledger!$J$5:$J$863,Sales_Ledger!$G$5:$G$863,$A33,Sales_Ledger!$D$5:$D$863,2025) | F33: =SUM(B33:E33)
A34: Housing unit (project not stated in source) | B34: =SUMIFS(Sales_Ledger!$J$5:$J$863,Sales_Ledger!$G$5:$G$863,$A34,Sales_Ledger!$D$5:$D$863,2022) | C34: =SUMIFS(Sales_Ledger!$J$5:$J$863,Sales_Ledger!$G$5:$G$863,$A34,Sales_Ledger!$D$5:$D$863,2023) | D34: =SUMIFS(Sales_Ledger!$J$5:$J$863,Sales_Ledger!$G$5:$G$863,$A34,Sales_Ledger!$D$5:$D$863,2024) | E34: =SUMIFS(Sales_Ledger!$J$5:$J$863,Sales_Ledger!$G$5:$G$863,$A34,Sales_Ledger!$D$5:$D$863,2025) | F34: =SUM(B34:E34)
A35: Land (estate not stated in source) | B35: =SUMIFS(Sales_Ledger!$J$5:$J$863,Sales_Ledger!$G$5:$G$863,$A35,Sales_Ledger!$D$5:$D$863,2022) | C35: =SUMIFS(Sales_Ledger!$J$5:$J$863,Sales_Ledger!$G$5:$G$863,$A35,Sales_Ledger!$D$5:$D$863,2023) | D35: =SUMIFS(Sales_Ledger!$J$5:$J$863,Sales_Ledger!$G$5:$G$863,$A35,Sales_Ledger!$D$5:$D$863,2024) | E35: =SUMIFS(Sales_Ledger!$J$5:$J$863,Sales_Ledger!$G$5:$G$863,$A35,Sales_Ledger!$D$5:$D$863,2025) | F35: =SUM(B35:E35)
... A41: Pacific Court 2 | B41: =SUMIFS(Sales_Ledger!$J$5:$J$863,Sales_Ledger!$G$5:$G$863,$A41,Sales_Ledger!$D$5:$D$863,2022) | C41: =SUMIFS(Sales_Ledger!$J$5:$J$863,Sales_Ledger!$G$5:$G$863,$A41,Sales_Ledger!$D$5:$D$863,2023) | D41: =SUMIFS(Sales_Ledger!$J$5:$J$863,Sales_Ledger!$G$5:$G$863,$A41,Sales_Ledger!$D$5:$D$863,2024) | E41: =SUMIFS(Sales_Ledger!$J$5:$J$863,Sales_Ledger!$G$5:$G$863,$A41,Sales_Ledger!$D$5:$D$863,2025) | F41: =SUM(B41:E41)
A42: Total | B42: =SUM(B24:B41) | C42: =SUM(C24:C41) | D42: =SUM(D24:D41) | E42: =SUM(E24:E41) | F42: =SUM(F24:F41)
A44: 4. Customers subscribed (Subscriptions and Customer_Master)
A45: Subscriptions are counted in the year of the subscription date in the client register.
A46: Subscriptions per client register | B46: 2022 | C46: 2023 | D46: 2024 | E46: 2025 | F46: Total
A47: Land | B47: =COUNTIFS(Subscriptions!$D$5:$D$218,"Land",Subscriptions!$H$5:$H$218,2022) | C47: =COUNTIFS(Subscriptions!$D$5:$D$218,"Land",Subscriptions!$H$5:$H$218,2023) | D47: =COUNTIFS(Subscriptions!$D$5:$D$218,"Land",Subscriptions!$H$5:$H$218,2024) | E47: =COUNTIFS(Subscriptions!$D$5:$D$218,"Land",Subscriptions!$H$5:$H$218,2025) | F47: =SUM(B47:E47)
A48: Housing | B48: =COUNTIFS(Subscriptions!$D$5:$D$218,"Housing",Subscriptions!$H$5:$H$218,2022) | C48: =COUNTIFS(Subscriptions!$D$5:$D$218,"Housing",Subscriptions!$H$5:$H$218,2023) | D48: =COUNTIFS(Subscriptions!$D$5:$D$218,"Housing",Subscriptions!$H$5:$H$218,2024) | E48: =COUNTIFS(Subscriptions!$D$5:$D$218,"Housing",Subscriptions!$H$5:$H$218,2025) | F48: =SUM(B48:E48)
A49: Construction | B49: =COUNTIFS(Subscriptions!$D$5:$D$218,"Construction",Subscriptions!$H$5:$H$218,2022) | C49: =COUNTIFS(Subscriptions!$D$5:$D$218,"Construction",Subscriptions!$H$5:$H$218,2023) | D49: =COUNTIFS(Subscriptions!$D$5:$D$218,"Construction",Subscriptions!$H$5:$H$218,2024) | E49: =COUNTIFS(Subscriptions!$D$5:$D$218,"Construction",Subscriptions!$H$5:$H$218,2025) | F49: =SUM(B49:E49)
A50: Subscriptions with a dated entry | B50: =SUM(B47:B49) | C50: =SUM(C47:C49) | D50: =SUM(D47:D49) | E50: =SUM(E47:E49) | F50: =SUM(F47:F49)
A51: Subscriptions with no date in the register | F51: =COUNTIFS(Subscriptions!$A$5:$A$218,"SB*",Subscriptions!$G$5:$G$218,"")
A54: Distinct customers in Customer_Master | F54: =COUNTIF(Customer_Master!$A$5:$A$240,"BP-C*")
A55: of which buying land | F55: =COUNTIF(Customer_Master!$E$5:$E$240,"*Land*")
A56: of which buying housing | F56: =COUNTIF(Customer_Master!$E$5:$E$240,"*Housing*")
A57: found in both client register and transaction records | F57: =COUNTIF(Customer_Master!$O$5:$O$240,"Client register + Transaction records")
A58: in client register only (no receipt line found) | F58: =COUNTIF(Customer_Master!$O$5:$O$240,"Client register")
A59: in transaction records only (not in client register) | F59: =COUNTIF(Customer_Master!$O$5:$O$240,"Transaction records")
A60: in commission records only (see exceptions tab) | F60: =COUNTIF(Customer_Master!$O$5:$O$240,"Commission records only*")
A61: Customers flagged for review (Customer_Master column R) | F61: =COUNTIF(Customer_Master!$R$5:$R$240,"?*")
A63: 5. Items removed from the sales population (Exclusions tab)
A64: Reason | B64: 2022 | C64: 2023 | D64: 2024 | E64: 2025 | F64: Total
A65: Co-ownership investment receipts | B65: =SUMIFS(Exclusions!$F$5:$F$108,Exclusions!$H$5:$H$108,"Co-ownership investment receipt: fixed-r*",Exclusions!$D$5:$D$108,2022) | C65: =SUMIFS(Exclusions!$F$5:$F$108,Exclusions!$H$5:$H$108,"Co-ownership investment receipt: fixed-r*",Exclusions!$D$5:$D$108,2023) | D65: =SUMIFS(Exclusions!$F$5:$F$108,Exclusions!$H$5:$H$108,"Co-ownership investment receipt: fixed-r*",Exclusions!$D$5:$D$108,2024) | E65: =SUMIFS(Exclusions!$F$5:$F$108,Exclusions!$H$5:$H$108,"Co-ownership investment receipt: fixed-r*",Exclusions!$D$5:$D$108,2025) | F65: =SUM(B65:E65)
A66: Credit memos (non-cash transfers) | B66: =SUMIFS(Exclusions!$F$5:$F$108,Exclusions!$H$5:$H$108,"Credit memo: non-cash transfer of an ear*",Exclusions!$D$5:$D$108,2022) | C66: =SUMIFS(Exclusions!$F$5:$F$108,Exclusions!$H$5:$H$108,"Credit memo: non-cash transfer of an ear*",Exclusions!$D$5:$D$108,2023) | D66: =SUMIFS(Exclusions!$F$5:$F$108,Exclusions!$H$5:$H$108,"Credit memo: non-cash transfer of an ear*",Exclusions!$D$5:$D$108,2024) | E66: =SUMIFS(Exclusions!$F$5:$F$108,Exclusions!$H$5:$H$108,"Credit memo: non-cash transfer of an ear*",Exclusions!$D$5:$D$108,2025) | F66: =SUM(B66:E66)
A67: Service / engagement income | B67: =SUMIFS(Exclusions!$F$5:$F$108,Exclusions!$H$5:$H$108,"Service/engagement income: not a land, h*",Exclusions!$D$5:$D$108,2022) | C67: =SUMIFS(Exclusions!$F$5:$F$108,Exclusions!$H$5:$H$108,"Service/engagement income: not a land, h*",Exclusions!$D$5:$D$108,2023) | D67: =SUMIFS(Exclusions!$F$5:$F$108,Exclusions!$H$5:$H$108,"Service/engagement income: not a land, h*",Exclusions!$D$5:$D$108,2024) | E67: =SUMIFS(Exclusions!$F$5:$F$108,Exclusions!$H$5:$H$108,"Service/engagement income: not a land, h*",Exclusions!$D$5:$D$108,2025) | F67: =SUM(B67:E67)
A68: Total excluded | B68: =SUM(B65:B67) | C68: =SUM(C65:C67) | D68: =SUM(D65:D67) | E68: =SUM(E65:E67) | F68: =SUM(F65:F67)
A70: 6. Open items for the auditor
A71: Unmatched secondary records, Dec 2023 to Dec 2024 (Exceptions tab) | F71: =SUM(Exceptions_Dec23_Dec24!$F$5:$F$94)
A72: Turnover sheets: total differences vs stated totals (Turnover_Recon) | F72: =SUM(Turnover_Recon!H5:H17)

Sheet Notes
A1: Basis of preparation, sources and limitations
A4: Purpose
A5: Scope | B5: All sales records across land, housing and construction for 1 Jan 2023 to 31 Dec 2025, with 2022 included where records exist, plus every customer who subscribed in that window. Prepared for the external auditor from files on the BAAY Google Drive. Xero was not used.
A6: What the figures are | B6: Cash receipts from customers as recorded by Accounts and Client Relations. They are not revenue: under IFRS 15, housing revenue is recognised at handover and instalment land sales on transfer of control, so receipts will not equal the revenue line in the audited accounts.
A8: Source files (Google Drive)
A9: BAAY PROJECTS FINANCIALS 2024.xlsx | B9: Owner baayrealty@gmail.com. Monthly turnover sheets DECEMBER 2023 TURNOVER to DECEMBER TURNOVER (2024), split by Allen and Magodo branches from July 2024; TURNOVER SCHEDULE (Green City Phase 1 and 2 payment histories, 2023 to 2024). https://drive.google.com/file/d/1xxPmuhTO7yU2Xj4dTlhJLBm4G8uQ0djH/view
A10: BAAY PROJECTS SALES EXPENSES (COMMISSION) RECORDS (1) | B10: Owner finance.baayprojects@gmail.com, live Google Sheet (latest version, edited 2 Oct 2026). One tab per realtor/associate listing each client payment on which commission was computed. Tabs RESERVE, ASSOCIATE LEAD and 2% UPLINE were not used because they restate the same sales. https://docs.google.com/spreadsheets/d/1d6rtbsgtIV7EDgoHHqDDx_pL2jXcNY92DPUl5KqOXg8
A11: BAAY PROJECTS CLIENTS | B11: Owner baayrealty@gmail.com. Client register maintained by Client Relations: one tab per estate/project with subscription date, price, amount paid, payment plan, allocation and contacts. https://docs.google.com/spreadsheets/d/1DRFmvVuOpeHsLXLAUwPu5Y37A_mOiNGEEYaO8-mRS2o
A12: BAAY FORESHORE, IBADAN EXPENSES, SUBSCRIBERS & FINANCIALS | B12: Owner acct.baayprojects@gmail.com. Tab REVENUE/FINACIALS BY SUBSCRIBERS used for Baay Foreshore subscribers in 2025 (cost, payment, plan). https://docs.google.com/spreadsheets/d/10QOMlmpicusYlxha1Q1CMPboSlq193dtaN_DveSicyg
A13: Searched, not used | B13: BAAY PROJECTS Revenue and Expense Register 2026 and BAAY PROJECTS FINANCIALS 2026 (2026 only); BAAY_Management_Accounts_Workshop.xlsx (2026 journals); audited financial statement PDFs (no customer-level detail); payroll files.
A15: How each year was built
A16: 2022 | B16: No transaction-level receipts exist on the Drive for 2022. Customers subscribed in 2022 (Pacific Court) are listed from the client register only.
A17: Jan to Nov 2023 | B17: No monthly turnover register exists for this period. Receipts come from the TURNOVER SCHEDULE (Green City Phase 1 and 2 only) and from the commission records; a commission line that matches a schedule line is not counted twice.
A18: Dec 2023 to Dec 2024 | B18: The monthly turnover register is the population. Turnover-schedule and commission lines that match a register line one-to-one are shown in the "Also recorded in" column. Lines that do not match are listed on Exceptions_Dec23_Dec24 and are NOT added, because most are aggregates or splits of register receipts; adding them would double count.
A19: 2025 | B19: No turnover register for 2025 exists on the Drive. Receipts come from the commission records, de-duplicated across realtor tabs. Commission records only capture sales that carried commission, and a single line can aggregate several transfers, so 2025 should be treated as a list for testing against bank statements, not a complete cash book.
A20: Construction | B20: No construction-contract receipts were found for 2022 to 2025 in any source. The first construction engagement in the records (12 Basket apartment renovation) is dated February 2026, outside this period.
A22: Processing rules
A23: Dates | B23: Several source sheets store dates typed as day/month but read by the spreadsheet as month/day (e.g. 1 December 2023 held as 12 January 2023). Day and month were swapped back for those cells; the sequence of each client's instalments and the month of each turnover sheet confirm the correction. The date exactly as stored is kept in the "Date as recorded" column. Obvious year typos (e.g. 3034, 0204) are noted and the line is reported in the month of the sheet it sits on.
A24: Duplicates | B24: Commission tabs restate earlier payments in each payout block, and the same sale can sit on two realtor tabs. Exact repeats within a tab were dropped; across tabs, lines for the same customer and amount within 45 days were treated as one receipt (cross-reference kept).
A25: Customer matching | B25: Names were matched across sources after removing titles (Mr, Mrs, Dr, Engr, etc.) and comparing the remaining name parts. Each person has one Customer ID. Matching is approximate: a misspelt name can create a second ID, so review the Customer_Master flags.
A26: Exclusions | B26: Co-ownership receipts (a fixed-return investment product, not a sale), credit memos (non-cash transfers between products) and service/engagement income are removed to the Exclusions tab, so the turnover sheet totals still reconcile on Turnover_Recon.
A27: Contact details | B27: Phone and email are included only for customer confirmation work. Dates of birth held in the client register were left out.
A29: Points the auditor should know
A30: 1 | B30: Agree receipts to bank statements, especially 2025 and the Exceptions tab.
A31: 2 | B31: 9 register entries dated in 2026 were left out of Subscriptions (outside the period).
A32: 3 | B32: Customer_Master column R flags customers whose receipts exceed the contract value in the register (possible duplicate entries, a second plot, or ancillary fees) and customers who appear in transaction records but not in the client register.
A33: 4 | B33: Contract values and paid-to-date figures on Subscriptions are as typed by Client Relations and were not recomputed.

Sheet Sales_Ledger
A1: BAAY Projects Limited: Sales receipts ledger, land and housing (Jan 2023 to Dec 2025)
A2: One row per customer receipt. Source, row and recorded date kept for every line so each can be traced back. Amounts in Naira.
A4: Ref | B4: Receipt date | C4: Reporting month | D4: Year | E4: Product line | F4: Receipt type | G4: Project / estate | H4: Customer ID | I4: Customer name (as recorded) | J4: Amount (₦) | K4: Branch | L4: Population basis | M4: Source file | N4: Source sheet | O4: Source row | P4: Date as recorded in source | Q4: Also recorded in | R4: Review note
A5: SL0001 | B5: 44957 | C5: 2023-01 | D5: 2023 | E5: Land | F5: Plot / unit price | G5: Land (estate not stated in source) | H5: BP-C0006 | I5: Mr Olasupo Oladimeji | J5: 894000 | L5: Secondary: commission records; no monthly turnover register for this period | M5: BAAY PROJECTS SALES EXPENSES (COMMISSION) RECORDS (1) | N5: MRS ABIMBOLA | O5: 15 | P5: 31/01/2023 | R5: Commission-record amount: confirm to bank statement (records can aggregate several transfers)
A6: SL0002 | B6: 44987 | C6: 2023-03 | D6: 2023 | E6: Land | F6: Plot / unit price | G6: Green City Phase 2 (Ketu-Epe) | H6: BP-C0009 | I6: Miss Oji Blessing Mary | J6: 740000 | L6: Secondary: turnover schedule (Green City Ph1/Ph2 payment history); no monthly turnover register for this period | M6: BAAY PROJECTS FINANCIALS 2024.xlsx | N6: TURNOVER SCHEDULE | O6: 111 | P6: 2023-02-03
A7: SL0003 | B7: 45059 | C7: 2023-05 | D7: 2023 | E7: Land | F7: Plot / unit price | G7: Land (estate not stated in source) | H7: BP-C0010 | I7: Mrs Yohanna Paulina | J7: 300000 | L7: Secondary: commission records; no monthly turnover register for this period | M7: BAAY PROJECTS SALES EXPENSES (COMMISSION) RECORDS (1) | N7: MR CHARLES | O7: 44 | P7: 13/05/2023 | R7: Commission-record amount: confirm to bank statement (records can aggregate several transfers)
A8: SL0004 | B8: 45063 | C8: 2023-05 | D8: 2023 | E8: Land | F8: Plot / unit price | G8: Green City Phase 2 (Ketu-Epe) | H8: BP-C0012 | I8: Mr Apiafi Imiebam | J8: 1000000 | L8: Secondary: turnover schedule (Green City Ph1/Ph2 payment history); no monthly turnover register for this period | M8: BAAY PROJECTS FINANCIALS 2024.xlsx | N8: TURNOVER SCHEDULE | O8: 310 | P8: 17/05/2023
A9: SL0005 | B9: 45076 | C9: 2023-05 | D9: 2023 | E9: Land | F9: Plot / unit price | G9: Green City Phase 1 (Ketu-Epe) | H9: BP-C0013 | I9: Mr Tijani Moshood Abiola | J9: 1000000 | L9: Secondary: turnover schedule (Green City Ph1/Ph2 payment history); no monthly turnover register for this period | M9: BAAY PROJECTS FINANCIALS 2024.xlsx | N9: TURNOVER SCHEDULE | O9: 282 | P9: 30/05/2023
A10: SL0006 | B10: 45092 | C10: 2023-06 | D10: 2023 | E10: Land | F10: Plot / unit price | G10: Land (estate not stated in source) | H10: BP-C0015 | I10: Mr Damilare Ositade Owolabi | J10: 1500000 | L10: Secondary: commission records; no monthly turnover register for this period | M10: BAAY PROJECTS SALES EXPENSES (COMMISSION) RECORDS (1) | N10: IDARA EKANEMI | O10: 7 | P10: 15/06/2023 | R10: Commission-record amount: confirm to bank statement (records can aggregate several transfers)
A11: SL0007 | B11: 45152 | C11: 2023-08 | D11: 2023 | E11: Land | F11: Plot / unit price | G11: Land (estate not stated in source) | H11: BP-C0019 | I11: Mr Ogbu Pius Ejaka | J11: 1500000 | L11: Secondary: commission records; no monthly turnover register for this period | M11: BAAY PROJECTS SALES EXPENSES (COMMISSION) RECORDS (1) | N11: MS BLESSING | O11: 90 | P11: 14/08/2023 | Q11: MS MAYOWA BRAIMOH r19 | R11: Commission-record amount: confirm to bank statement (records can aggregate several transfers)
A12: SL0008 | B12: 45161 | C12: 2023-08 | D12: 2023 | E12: Land | F12: Plot / unit price | G12: Land (estate not stated in source) | H12: BP-C0021 | I12: Mr Oyewusi sheriff Oyewole | J12: 1000000 | L12: Secondary: commission records; no monthly turnover register for this period | M12: BAAY PROJECTS SALES EXPENSES (COMMISSION) RECORDS (1) | N12: MS BOLANLE | O12: 7 | P12: 23/08/2023 | R12: Commission-record amount: confirm to bank statement (records can aggregate several transfers)
A13: SL0009 | B13: 45173 | C13: 2023-09 | D13: 2023 | E13: Land | F13: Plot / unit price | G13: Land (estate not stated in source) | H13: BP-C0025 | I13: Mrs Obadara Dorcas Adebisi | J13: 1500000 | L13: Secondary: commission records; no monthly turnover register for this period | M13: BAAY PROJECTS SALES EXPENSES (COMMISSION) RECORDS (1) | N13: NELSON | O13: 7 | P13: 2023-04-09 | R13: Commission-record amount: confirm to bank statement (records can aggregate several transfers)
A14: SL0010 | B14: 45184 | C14: 2023-09 | D14: 2023 | E14: Land | F14: Plot / unit price | G14: Green City Phase 1 (Ketu-Epe) | H14: BP-C0026 | I14: Mr Adebayo Dada | J14: 400000 | L14: Secondary: turnover schedule (Green City Ph1/Ph2 payment history); no monthly turnover register for this period | M14: BAAY PROJECTS FINANCIALS 2024.xlsx | N14: TURNOVER SCHEDULE | O14: 6 | P14: 15/09/2023
A15: SL0011 | B15: 45190 | C15: 2023-09 | D15: 2023 | E15: Land | F15: Plot / unit price | G15: Green City Phase 1 (Ketu-Epe) | H15: BP-C0027 | I15: Mr Edun Ayobami Simeon | J15: 1000000 | L15: Secondary: turnover schedule (Green City Ph1/Ph2 payment history); no monthly turnover register for this period | M15: BAAY PROJECTS FINANCIALS 2024.xlsx | N15: TURNOVER SCHEDULE | O15: 125 | P15: 21/09/2023 | Q15: OLAIYA r7
A16: SL0012 | B16: 45190 | C16: 2023-09 | D16: 2023 | E16: Land | F16: Plot / unit price | G16: Land (estate not stated in source) | H16: BP-C0018 | I16: Mr Sunday Gideon | J16: 1500000 | L16: Secondary: commission records; no monthly turnover register for this period | M16: BAAY PROJECTS SALES EXPENSES (COMMISSION) RECORDS (1) | N16: MS BLESSING | O16: 7 | P16: 21/09/2023 | R16: Commission-record amount: confirm to bank statement (records can aggregate several transfers)
A17: SL0013 | B17: 45197 | C17: 2023-09 | D17: 2023 | E17: Land | F17: Plot / unit price | G17: Green City Phase 1 (Ketu-Epe) | H17: BP-C0028 | I17: Mr Adebanjo Isaac | J17: 1000000 | L17: Secondary: turnover schedule (Green City Ph1/Ph2 payment history); no monthly turnover register for this period | M17: BAAY PROJECTS FINANCIALS 2024.xlsx | N17: TURNOVER SCHEDULE | O17: 198 | P17: 28/09/2023
A18: SL0014 | B18: 45197 | C18: 2023-09 | D18: 2023 | E18: Land | F18: Plot / unit price | G18: Green City Phase 1 (Ketu-Epe) | H18: BP-C0026 | I18: Mr Adebayo Dada | J18: 300000 | L18: Secondary: turnover schedule (Green City Ph1/Ph2 payment history); no monthly turnover register for this period | M18: BAAY PROJECTS FINANCIALS 2024.xlsx | N18: TURNOVER SCHEDULE | O18: 7 | P18: 28/09/2023
A19: SL0015 | B19: 45197 | C19: 2023-09 | D19: 2023 | E19: Land | F19: Plot / unit price | G19: Land (estate not stated in source) | H19: BP-C0021 | I19: Mr Oyewusi sheriff Oyewole | J19: 1000000 | L19: Secondary: commission records; no monthly turnover register for this period | M19: BAAY PROJECTS SALES EXPENSES (COMMISSION) RECORDS (1) | N19: MS BOLANLE | O19: 8 | P19: 28/09/2023 | R19: Commission-record amount: confirm to bank statement (records can aggregate several transfers)
A20: SL0016 | B20: 45202 | C20: 2023-10 | D20: 2023 | E20: Land | F20: Plot / unit price | G20: Green City Phase 1 (Ketu-Epe) | H20: BP-C0030 | I20: Mr Akorede Adese | J20: 1000000 | L20: Secondary: turnover schedule (Green City Ph1/Ph2 payment history); no monthly turnover register for this period | M20: BAAY PROJECTS FINANCIALS 2024.xlsx | N20: TURNOVER SCHEDULE | O20: 202 | P20: 2023-03-10
A21: SL0017 | B21: 45202 | C21: 2023-10 | D21: 2023 | E21: Land | F21: Plot / unit price | G21: Green City Phase 1 (Ketu-Epe) | H21: BP-C0030 | I21: Mr Akorede Adese | J21: 100000 | L21: Secondary: turnover schedule (Green City Ph1/Ph2 payment history); no monthly turnover register for this period | M21: BAAY PROJECTS FINANCIALS 2024.xlsx | N21: TURNOVER SCHEDULE | O21: 203 | P21: 2023-03-10
A22: SL0018 | B22: 45202 | C22: 2023-10 | D22: 2023 | E22: Land | F22: Plot / unit price | G22: Land (estate not stated in source) | H22: BP-C0029 | I22: Mr Ohanehi Anthony | J22: 3000000 | L22: Secondary: commission records; no monthly turnover register for this period | M22: BAAY PROJECTS SALES EXPENSES (COMMISSION) RECORDS (1) | N22: MS IMMACULATE | O22: 8 | P22: 2023-03-10 | R22: Commission-record amount: confirm to bank statement (records can aggregate several transfers)
A23: SL0019 | B23: 45202 | C23: 2023-10 | D23: 2023 | E23: Land | F23: Plot / unit price | G23: Green City Phase 1 (Ketu-Epe) | H23: BP-C0008 | I23: Mr Roqeeb Rasaq Adebare | J23: 300000 | L23: Secondary: turnover schedule (Green City Ph1/Ph2 payment history); no monthly turnover register for this period | M23: BAAY PROJECTS FINANCIALS 2024.xlsx | N23: TURNOVER SCHEDULE | O23: 182 | P23: 2023-03-10
A24: SL0020 | B24: 45202 | C24: 2023-10 | D24: 2023 | E24: Land | F24: Plot / unit price | G24: Green City Phase 1 (Ketu-Epe) | H24: BP-C0008 | I24: Mr Roqeeb Rasaq Adebare | J24: 200000 | L24: Secondary: turnover schedule (Green City Ph1/Ph2 payment history); no monthly turnover register for this period | M24: BAAY PROJECTS FINANCIALS 2024.xlsx | N24: TURNOVER SCHEDULE | O24: 183 | P24: 2023-03-10
A25: SL0021 | B25: 45205 | C25: 2023-10 | D25: 2023 | E25: Land | F25: Plot / unit price | G25: Land (estate not stated in source) | H25: BP-C0026 | I25: Mr & Mrs Adebayo Dada | J25: 3000000 | L25: Secondary: commission records; no monthly turnover register for this period | M25: BAAY PROJECTS SALES EXPENSES (COMMISSION) RECORDS (1) | N25: MRS ABIMBOLA | O25: 7 | P25: 2023-06-10 | R25: Commission-record amount: confirm to bank statement (records can aggregate several transfers)
A26: SL0022 | B26: 45205 | C26: 2023-10 | D26: 2023 | E26: Land | F26: Plot / unit price | G26: Green City Phase 1 (Ketu-Epe) | H26: BP-C0026 | I26: Mr Adebayo Dada | J26: 300000 | L26: Secondary: turnover schedule (Green City Ph1/Ph2 payment history); no monthly turnover register for this period | M26: BAAY PROJECTS FINANCIALS 2024.xlsx | N26: TURNOVER SCHEDULE | O26: 8 | P26: 2023-06-10
A27: SL0023 | B27: 45209 | C27: 2023-10 | D27: 2023 | E27: Land | F27: Plot / unit price | G27: Land (estate not stated in source) | H27: BP-C0029 | I27: Mr Ohanehi Anthony | J27: 1500000 | L27: Secondary: commission records; no monthly turnover register for this period | M27: BAAY PROJECTS SALES EXPENSES (COMMISSION) RECORDS (1) | N27: MS IMMACULATE | O27: 7 | P27: 2023-10-10 | R27: Commission-record amount: confirm to bank statement (records can aggregate several transfers)
A28: SL0024 | B28: 45211 | C28: 2023-10 | D28: 2023 | E28: Land | F28: Plot / unit price | G28: Green City Phase 1 (Ketu-Epe) | H28: BP-C0033 | I28: Mr Olumoko Oladapo Oluwaseun | J28: 1000000 | L28: Secondary: turnover schedule (Green City Ph1/Ph2 payment history); no monthly turnover register for this period | M28: BAAY PROJECTS FINANCIALS 2024.xlsx | N28: TURNOVER SCHEDULE | O28: 155 | P28: 2023-12-10 | Q28: MS BOLANLE r12
A29: SL0025 | B29: 45211 | C29: 2023-10 | D29: 2023 | E29: Land | F29: Plot / unit price | G29: Land (estate not stated in source) | H29: BP-C0034 | I29: Mrs Ndubuisi Ujunwa | J29: 1500000 | L29: Secondary: commission records; no monthly turnover register for this period | M29: BAAY PROJECTS SALES EXPENSES (COMMISSION) RECORDS (1) | N29: MS IMMACULATE | O29: 9 | P29: 2023-12-10 | R29: Commission-record amount: confirm to bank statement (records can aggregate several transfers)
A30: SL0026 | B30: 45219 | C30: 2023-10 | D30: 2023 | E30: Land | F30: Plot / unit price | G30: Land (estate not stated in source) | H30: BP-C0021 | I30: Mr Oyewusi sheriff Oyewole | J30: 1000000 | L30: Secondary: commission records; no monthly turnover register for this period | M30: BAAY PROJECTS SALES EXPENSES (COMMISSION) RECORDS (1) | N30: MS BOLANLE | O30: 9 | P30: 20/10/2023 | R30: Commission-record amount: confirm to bank statement (records can aggregate several transfers)
A31: SL0027 | B31: 45222 | C31: 2023-10 | D31: 2023 | E31: Land | F31: Plot / unit price | G31: Green City Phase 1 (Ketu-Epe) | H31: BP-C0027 | I31: Mr Edun Ayobami Simeon | J31: 700000 | L31: Secondary: turnover schedule (Green City Ph1/Ph2 payment history); no monthly turnover register for this period | M31: BAAY PROJECTS FINANCIALS 2024.xlsx | N31: TURNOVER SCHEDULE | O31: 126 | P31: 23/10/2023 | Q31: OLAIYA r8
A32: SL0028 | B32: 45226 | C32: 2023-10 | D32: 2023 | E32: Land | F32: Plot / unit price | G32: Green City Phase 1 (Ketu-Epe) | H32: BP-C0033 | I32: Mr Olumoko Oladapo Oluwaseun | J32: 1000000 | L32: Secondary: turnover schedule (Green City Ph1/Ph2 payment history); no monthly turnover register for this period | M32: BAAY PROJECTS FINANCIALS 2024.xlsx | N32: TURNOVER SCHEDULE | O32: 156 | P32: 27/10/2023 | Q32: MS BOLANLE r13
A33: SL0029 | B33: 45227 | C33: 2023-10 | D33: 2023 | E33: Land | F33: Plot / unit price | G33: Green City Phase 1 (Ketu-Epe) | H33: BP-C0036 | I33: Mr Ohumende Paul Osaze | J33: 3000000 | L33: Secondary: turnover schedule (Green City Ph1/Ph2 payment history); no monthly turnover register for this period | M33: BAAY PROJECTS FINANCIALS 2024.xlsx | N33: TURNOVER SCHEDULE | O33: 117 | P33: 28/10/2023
A34: SL0030 | B34: 45228 | C34: 2023-10 | D34: 2023 | E34: Land | F34: Plot / unit price | G34: Land (estate not stated in source) | H34: BP-C0029 | I34: Mr Ohanehi Anthony | J34: 9000000 | L34: Secondary: commission records; no monthly turnover register for this period | M34: BAAY PROJECTS SALES EXPENSES (COMMISSION) RECORDS (1) | N34: MS IMMACULATE | O34: 10 | P34: 29/10/2023 | R34: Commission-record amount: confirm to bank statement (records can aggregate several transfers)
A35: SL0031 | B35: 45228 | C35: 2023-10 | D35: 2023 | E35: Land | F35: Plot / unit price | G35: Land (estate not stated in source) | H35: BP-C0038 | I35: Okeizie Ifeoma Mandy | J35: 2000000 | L35: Secondary: commission records; no monthly turnover register for this period | M35: BAAY PROJECTS SALES EXPENSES (COMMISSION) RECORDS (1) | N35: MS CELINA | O35: 7 | P35: 29/10/2023 | R35: Commission-record amount: confirm to bank statement (records can aggregate several transfers)
A36: SL0032 | B36: 45229 | C36: 2023-10 | D36: 2023 | E36: Land | F36: Plot / unit price | G36: Land (estate not stated in source) | H36: BP-C0040 | I36: Bassey Christopher | J36: 9000000 | L36: Secondary: commission records; no monthly turnover register for this period | M36: BAAY PROJECTS SALES EXPENSES (COMMISSION) RECORDS (1) | N36: MS IMMACULATE | O36: 11 | P36: 30/10/2023 | R36: Commission-record amount: confirm to bank statement (records can aggregate several transfers)
A37: SL0033 | B37: 45229 | C37: 2023-10 | D37: 2023 | E37: Land | F37: Plot / unit price | G37: Land (estate not stated in source) | H37: BP-C0040 | I37: Bassey Christopher | J37: 3000000 | L37: Secondary: commission records; no monthly turnover register for this period | M37: BAAY PROJECTS SALES EXPENSES (COMMISSION) RECORDS (1) | N37: MS IMMACULATE | O37: 12 | P37: 30/10/2023 | R37: Commission-record amount: confirm to bank statement (records can aggregate several transfers)
A38: SL0034 | B38: 45229 | C38: 2023-10 | D38: 2023 | E38: Land | F38: Plot / unit price | G38: Green City Phase 1 (Ketu-Epe) | H38: BP-C0030 | I38: Mr Akorede Adese | J38: 100000 | L38: Secondary: turnover schedule (Green City Ph1/Ph2 payment history); no monthly turnover register for this period | M38: BAAY PROJECTS FINANCIALS 2024.xlsx | N38: TURNOVER SCHEDULE | O38: 204 | P38: 30/10/2023
A39: SL0035 | B39: 45229 | C39: 2023-10 | D39: 2023 | E39: Land | F39: Plot / unit price | G39: Green City Phase 2 (Ketu-Epe) | H39: BP-C0039 | I39: Mr Alabi Abdulazeez | J39: 1000000 | L39: Secondary: turnover schedule (Green City Ph1/Ph2 payment history); no monthly turnover register for this period | M39: BAAY PROJECTS FINANCIALS 2024.xlsx | N39: TURNOVER SCHEDULE | O39: 195 | P39: 30/10/2023
A40: SL0036 | B40: 45229 | C40: 2023-10 | D40: 2023 | E40: Land | F40: Plot / unit price | G40: Green City Phase 1 (Ketu-Epe) | H40: BP-C0029 | I40: Mr Ohanehi Anthony Chukwunonso | J40: 1000000 | L40: Secondary: turnover schedule (Green City Ph1/Ph2 payment history); no monthly turnover register for this period | M40: BAAY PROJECTS FINANCIALS 2024.xlsx | N40: TURNOVER SCHEDULE | O40: 17 | P40: 30/10/2023
A41: SL0037 | B41: 45229 | C41: 2023-10 | D41: 2023 | E41: Land | F41: Plot / unit price | G41: Green City Phase 1 (Ketu-Epe) | H41: BP-C0029 | I41: Mr Ohanehi Anthony Chukwunonso | J41: 1000000 | L41: Secondary: turnover schedule (Green City Ph1/Ph2 payment history); no monthly turnover register for this period | M41: BAAY PROJECTS FINANCIALS 2024.xlsx | N41: TURNOVER SCHEDULE | O41: 163 | P41: 30/10/2023
A42: SL0038 | B42: 45229 | C42: 2023-10 | D42: 2023 | E42: Land | F42: Plot / unit price | G42: Land (estate not stated in source) | H42: BP-C0021 | I42: Mr Oyewusi sheriff Oyewole | J42: 600000 | L42: Secondary: commission records; no monthly turnover register for this period | M42: BAAY PROJECTS SALES EXPENSES (COMMISSION) RECORDS (1) | N42: MS BOLANLE | O42: 10 | P42: 30/10/2023 | R42: Commission-record amount: confirm to bank statement (records can aggregate several transfers)
A43: SL0039 | B43: 45232 | C43: 2023-11 | D43: 2023 | E43: Land | F43: Plot / unit price | G43: Green City Phase 1 (Ketu-Epe) | H43: BP-C0036 | I43: Mr Ohumende Paul Osaze | J43: 3000000 | L43: Secondary: turnover schedule (Green City Ph1/Ph2 payment history); no monthly turnover register for this period | M43: BAAY PROJECTS FINANCIALS 2024.xlsx | N43: TURNOVER SCHEDULE | O43: 118 | P43: 2023-02-11
A44: SL0040 | B44: 45233 | C44: 2023-11 | D44: 2023 | E44: Land | F44: Plot / unit price | G44: Land (estate not stated in source) | H44: BP-C0042 | I44: Alhaji Gbadamosi Mohammad | J44: 3900000 | L44: Secondary: commission records; no monthly turnover register for this period | M44: BAAY PROJECTS SALES EXPENSES (COMMISSION) RECORDS (1) | N44: OLUWATOBIJUWON | O44: 7 | P44: 2023-03-11 | R44: Commission-record amount: confirm to bank statement (records can aggregate several transfers)
A45: SL0041 | B45: 45239 | C45: 2023-11 | D45: 2023 | E45: Land | F45: Plot / unit price | G45: Green City Phase 1 (Ketu-Epe) | H45: BP-C0026 | I45: Mr Adebayo Dada | J45: 200000 | L45: Secondary: turnover schedule (Green City Ph1/Ph2 payment history); no monthly turnover register for this period | M45: BAAY PROJECTS FINANCIALS 2024.xlsx | N45: TURNOVER SCHEDULE | O45: 9 | P45: 2023-09-11
A46: SL0042 | B46: 45239 | C46: 2023-11 | D46: 2023 | E46: Land | F46: Plot / unit price | G46: Green City Phase 1 (Ketu-Epe) | H46: BP-C0044 | I46: Mr Babajide Oluwase | J46: 1200000 | L46: Secondary: turnover schedule (Green City Ph1/Ph2 payment history); no monthly turnover register for this period | M46: BAAY PROJECTS FINANCIALS 2024.xlsx | N46: TURNOVER SCHEDULE | O46: 189 | P46: 2023-09-11
A47: SL0043 | B47: 45239 | C47: 2023-11 | D47: 2023 | E47: Land | F47: Plot / unit price | G47: Land (estate not stated in source) | H47: BP-C0043 | I47: Mrs Oladiran Omolola | J47: 750000 | L47: Secondary: commission records; no monthly turnover register for this period | M47: BAAY PROJECTS SALES EXPENSES (COMMISSION) RECORDS (1) | N47: MR PELUMI | O47: 7 | P47: 2023-09-11 | R47: Commission-record amount: confirm to bank statement (records can aggregate several transfers)
A48: SL0044 | B48: 45245 | C48: 2023-11 | D48: 2023 | E48: Land | F48: Plot / unit price | G48: Green City Phase 1 (Ketu-Epe) | H48: BP-C0045 | I48: Mr Bolarinwa Iyanuoluwa Simon & Dr Bolarinwa Abisola Christianah | J48: 1000000 | L48: Secondary: turnover schedule (Green City Ph1/Ph2 payment history); no monthly turnover register for this period | M48: BAAY PROJECTS FINANCIALS 2024.xlsx | N48: TURNOVER SCHEDULE | O48: 265 | P48: 15/11/2023
A49: SL0045 | B49: 45246 | C49: 2023-11 | D49: 2023 | E49: Land | F49: Plot / unit price | G49: Green City Phase 1 (Ketu-Epe) | H49: BP-C0027 | I49: Mr Edun Ayobami Simeon | J49: 700000 | L49: Secondary: turnover schedule (Green City Ph1/Ph2 payment history); no monthly turnover register for this period | M49: BAAY PROJECTS FINANCIALS 2024.xlsx | N49: TURNOVER SCHEDULE | O49: 127 | P49: 16/11/2023 | Q49: OLAIYA r9
A50: SL0046 | B50: 45251 | C50: 2023-11 | D50: 2023 | E50: Land | F50: Plot / unit price | G50: Green City Phase 1 (Ketu-Epe) | H50: BP-C0046 | I50: Mr Adesida Raphael Abiodun | J50: 1000000 | L50: Secondary: turnover schedule (Green City Ph1/Ph2 payment history); no monthly turnover register for this period | M50: BAAY PROJECTS FINANCIALS 2024.xlsx | N50: TURNOVER SCHEDULE | O50: 169 | P50: 21/11/2023
A51: SL0047 | B51: 45254 | C51: 2023-11 | D51: 2023 | E51: Housing | F51: Plot / unit price | G51: Pacific Court | H51: BP-C0047 | I51: Ms Paulina Kehinde Akhere George | J51: 16500000 | L51: Secondary: turnover schedule (Green City Ph1/Ph2 payment history); no monthly turnover register for this period | M51: BAAY PROJECTS FINANCIALS 2024.xlsx | N51: TURNOVER SCHEDULE | O51: 211 | P51: 24/11/2023
A52: SL0048 | B52: 45255 | C52: 2023-11 | D52: 2023 | E52: Land | F52: Plot / unit price | G52: Green City Phase 1 (Ketu-Epe) | H52: BP-C0026 | I52: Mr Adebayo Dada | J52: 200000 | L52: Secondary: turnover schedule (Green City Ph1/Ph2 payment history); no monthly turnover register for this period | M52: BAAY PROJECTS FINANCIALS 2024.xlsx | N52: TURNOVER SCHEDULE | O52: 11 | P52: 25/11/2023
A53: SL0049 | B53: 45259 | C53: 2023-11 | D53: 2023 | E53: Land | F53: Plot / unit price | G53: Green City Phase 1 (Ketu-Epe) | H53: BP-C0029 | I53: Mr Ohanehi Anthony Chukwunonso | J53: 1483000 | L53: Secondary: turnover schedule (Green City Ph1/Ph2 payment history); no monthly turnover register for this period | M53: BAAY PROJECTS FINANCIALS 2024.xlsx | N53: TURNOVER SCHEDULE | O53: 18 | P53: 29/11/2023
A54: SL0050 | B54: 45259 | C54: 2023-11 | D54: 2023 | E54: Land | F54: Plot / unit price | G54: Green City Phase 1 (Ketu-Epe) | H54: BP-C0029 | I54: Mr Ohanehi Anthony Chukwunonso | J54: 1483000 | L54: Secondary: turnover schedule (Green City Ph1/Ph2 payment history); no monthly turnover register for this period | M54: BAAY PROJECTS FINANCIALS 2024.xlsx | N54: TURNOVER SCHEDULE | O54: 164 | P54: 29/11/2023
A55: SL0051 | B55: 45261 | C55: 2023-12 | D55: 2023 | E55: Land | F55: Plot / unit price | G55: Land (estate not stated in source) | H55: BP-C0026 | I55: Mr Adebayo Dada | J55: 300000 | K55: Single register | L55: Primary: monthly turnover register | M55: BAAY PROJECTS FINANCIALS 2024.xlsx | N55: DECEMBER 2023 TURNOVER | O55: 6 | P55: 2023-01-12 | Q55: TURNOVER SCHEDULE r10
A56: SL0052 | B56: 45264 | C56: 2023-12 | D56: 2023 | E56: Land | F56: Plot / unit price | G56: Land (estate not stated in source) | H56: BP-C0036 | I56: Mr Ohumende Paul Osaze | J56: 4600000 | K56: Single register | L56: Primary: monthly turnover register | M56: BAAY PROJECTS FINANCIALS 2024.xlsx | N56: DECEMBER 2023 TURNOVER | O56: 7 | P56: 2023-04-12 | Q56: TURNOVER SCHEDULE r119
A57: SL0053 | B57: 45264 | C57: 2023-12 | D57: 2023 | E57: Housing | F57: Plot / unit price | G57: Housing unit (project not stated in source) | H57: BP-C0047 | I57: Ms Paulina Kehinde Akhere George | J57: 2500000 | K57: Single register | L57: Primary: monthly turnover register | M57: BAAY PROJECTS FINANCIALS 2024.xlsx | N57: DECEMBER 2023 TURNOVER | O57: 8 | P57: 2023-04-12 | Q57: TURNOVER SCHEDULE r212
A58: SL0054 | B58: 45266 | C58: 2023-12 | D58: 2023 | E58: Land | F58: Plot / unit price | G58: Land (estate not stated in source) | H58: BP-C0039 | I58: Mr Alabi Abdulazeez | J58: 800000 | K58: Single register | L58: Primary: monthly turnover register | M58: BAAY PROJECTS FINANCIALS 2024.xlsx | N58: DECEMBER 2023 TURNOVER | O58: 9 | P58: 2023-06-12 | Q58: TURNOVER SCHEDULE r196
A59: SL0055 | B59: 45268 | C59: 2023-12 | D59: 2023 | E59: Land | F59: Plot / unit price | G59: Land (estate not stated in source) | H59: BP-C0048 | I59: Mr Araokonmi Sodiq | J59: 2600000 | K59: Single register | L59: Primary: monthly turnover register | M59: BAAY PROJECTS FINANCIALS 2024.xlsx | N59: DECEMBER 2023 TURNOVER | O59: 10 | P59: 2023-08-12 | Q59: TURNOVER SCHEDULE r123, MS YETUNDE ABISOYE r7
A60: SL0056 | B60: 45270 | C60: 2023-12 | D60: 2023 | E60: Land | F60: Plot / unit price | G60: Land (estate not stated in source) | H60: BP-C0028 | I60: Mr Adebanjo Isaac | J60: 250000 | K60: Single register | L60: Primary: monthly turnover register | M60: BAAY PROJECTS FINANCIALS 2024.xlsx | N60: DECEMBER 2023 TURNOVER | O60: 11 | P60: 2023-10-12 | Q60: TURNOVER SCHEDULE r199
A61: SL0057 | B61: 45270 | C61: 2023-12 | D61: 2023 | E61: Housing | F61: Plot / unit price | G61: Housing unit (project not stated in source) | H61: BP-C0047 | I61: Ms Paulina Kehinde Akhere George | J61: 2500000 | K61: Single register | L61: Primary: monthly turnover register | M61: BAAY PROJECTS FINANCIALS 2024.xlsx | N61: DECEMBER 2023 TURNOVER | O61: 12 | P61: 2023-10-12 | Q61: TURNOVER SCHEDULE r213
A62: SL0058 | B62: 45271 | C62: 2023-12 | D62: 2023 | E62: Land | F62: Plot / unit price | G62: Land (estate not stated in source) | H62: BP-C0049 | I62: Mr Ali Ifesinachi Innocent | J62: 5040000 | K62: Single register | L62: Primary: monthly turnover register | M62: BAAY PROJECTS FINANCIALS 2024.xlsx | N62: DECEMBER 2023 TURNOVER | O62: 13 | P62: 2023-11-12 | Q62: TURNOVER SCHEDULE r209
A63: SL0059 | B63: 45278 | C63: 2023-12 | D63: 2023 | E63: Land | F63: Plot / unit price | G63: Land (estate not stated in source) | H63: BP-C0026 | I63: Mr Adebayo Dada | J63: 500000 | K63: Single register | L63: Primary: monthly turnover register | M63: BAAY PROJECTS FINANCIALS 2024.xlsx | N63: DECEMBER 2023 TURNOVER | O63: 14 | P63: 18/12/2023 | Q63: TURNOVER SCHEDULE r13
A64: SL0060 | B64: 45279 | C64: 2023-12 | D64: 2023 | E64: Land | F64: Plot / unit price | G64: Land (estate not stated in source) | H64: BP-C0026 | I64: Mr Adebayo Dada | J64: 500000 | K64: Single register | L64: Primary: monthly turnover register | M64: BAAY PROJECTS FINANCIALS 2024.xlsx | N64: DECEMBER 2023 TURNOVER | O64: 15 | P64: 19/12/2023 | Q64: TURNOVER SCHEDULE r14
A65: SL0061 | B65: 45280 | C65: 2023-12 | D65: 2023 | E65: Land | F65: Plot / unit price | G65: Land (estate not stated in source) | H65: BP-C0033 | I65: Mr Olumoko Oladapo Oluwaseun | J65: 1000000 | K65: Single register | L65: Primary: monthly turnover register | M65: BAAY PROJECTS FINANCIALS 2024.xlsx | N65: DECEMBER 2023 TURNOVER | O65: 16 | P65: 20/12/2023 | Q65: TURNOVER SCHEDULE r157, MS BOLANLE r14
A66: SL0062 | B66: 45281 | C66: 2023-12 | D66: 2023 | E66: Land | F66: Plot / unit price | G66: Land (estate not stated in source) | H66: BP-C0051 | I66: Mr Olumide Ogunleye | J66: 500000 | K66: Single register | L66: Primary: monthly turnover register | M66: BAAY PROJECTS FINANCIALS 2024.xlsx | N66: DECEMBER 2023 TURNOVER | O66: 17 | P66: 21/12/2023 | Q66: TURNOVER SCHEDULE r41
... A134: SL0130 | B134: 45352 | C134: 2024-03 | D134: 2024 | E134: Land | F134: Plot / unit price | G134: Green City Phase 2 (Ketu-Epe) | H134: BP-C0008 | I134: Mr Rasaq Roqeeb Adebare | J134: 150000 | K134: Single register | L134: Primary: monthly turnover register | M134: BAAY PROJECTS FINANCIALS 2024.xlsx | N134: MARCH TURNOVER | O134: 6 | P134: 2024-01-03 | Q134: TURNOVER SCHEDULE r187
A135: SL0131 | B135: 45353 | C135: 2024-03 | D135: 2024 | E135: Land | F135: Plot / unit price | G135: Green City Phase 2 (Ketu-Epe) | H135: BP-C0009 | I135: Miss Oji Blessing | J135: 740000 | K135: Single register | L135: Primary: monthly turnover register | M135: BAAY PROJECTS FINANCIALS 2024.xlsx | N135: MARCH TURNOVER | O135: 9 | P135: 3034-02-03 | R135: Year typed as 3034 in source (3034-02-03); corrected to 2024 from the sheet month
A136: SL0132 | B136: 45354 | C136: 2024-03 | D136: 2024 | E136: Land | F136: Plot / unit price | G136: Green City Phase 2 (Ketu-Epe) | H136: BP-C0060 | I136: Ms Mitchell jennifer | J136: 200000 | K136: Single register | L136: Primary: monthly turnover register | M136: BAAY PROJECTS FINANCIALS 2024.xlsx | N136: MARCH TURNOVER | O136: 10 | P136: 2024-03-03 | Q136: TURNOVER SCHEDULE r57
A137: SL0133 | B137: 45354 | C137: 2024-03 | D137: 2024 | E137: Land | F137: Plot / unit price | G137: Green City Phase 2 (Ketu-Epe) | H137: BP-C0066 | I137: Omosanya Dotun Akeju | J137: 1650000 | K137: Single register | L137: Primary: monthly turnover register | M137: BAAY PROJECTS FINANCIALS 2024.xlsx | N137: MARCH TURNOVER | O137: 11 | P137: 2024-03-03 | Q137: TURNOVER SCHEDULE r217, MS BOLANLE r34, MS BLESSING OJI r3
A138: SL0134 | B138: 45355 | C138: 2024-03 | D138: 2024 | E138: Land | F138: Plot / unit price | G138: Green City Phase 1 (Lantaba, Ketu-Epe) | H138: BP-C0006 | I138: Mr Olasupo Oladimeji | J138: 460500 | K138: Single register | L138: Primary: monthly turnover register | M138: BAAY PROJECTS FINANCIALS 2024.xlsx | N138: MARCH TURNOVER | O138: 13 | P138: 2024-04-03 | Q138: TURNOVER SCHEDULE r30, MRS ABIMBOLA r37
A139: SL0135 | B139: 45356 | C139: 2024-03 | D139: 2024 | E139: Land | F139: Plot / unit price | G139: Green City Phase 2 (Ketu-Epe) | H139: BP-C0030 | I139: Adese Akorede John | J139: 900000 | K139: Single register | L139: Primary: monthly turnover register | M139: BAAY PROJECTS FINANCIALS 2024.xlsx | N139: MARCH TURNOVER | O139: 14 | P139: 2024-05-03 | Q139: TURNOVER SCHEDULE r286
A140: SL0136 | B140: 45357 | C140: 2024-03 | D140: 2024 | E140: Land | F140: Plot / unit price | G140: Green City Phase 1 (Lantaba, Ketu-Epe) | H140: BP-C0069 | I140: Mr Agbaje Christopher Usiala | J140: 135000 | K140: Single register | L140: Primary: monthly turnover register | M140: BAAY PROJECTS FINANCIALS 2024.xlsx | N140: MARCH TURNOVER | O140: 17 | P140: 2024-06-03
A141: SL0137 | B141: 45357 | C141: 2024-03 | D141: 2024 | E141: Land | F141: Plot / unit price | G141: Green City Phase 2 (Ketu-Epe) | H141: BP-C0070 | I141: Mr Ayodeji Adeogun Daniel | J141: 1000000 | K141: Single register | L141: Primary: monthly turnover register | M141: BAAY PROJECTS FINANCIALS 2024.xlsx | N141: MARCH TURNOVER | O141: 16 | P141: 2024-06-03 | Q141: TURNOVER SCHEDULE r223, MS TAIWO r19, MR ADEWALE OMODARA r2
A142: SL0138 | B142: 45357 | C142: 2024-03 | D142: 2024 | E142: Land | F142: Plot / unit price | G142: Green City Phase 2 (Ketu-Epe) | H142: BP-C0063 | I142: Mr Omodara Adewale | J142: 500000 | K142: Single register | L142: Primary: monthly turnover register | M142: BAAY PROJECTS FINANCIALS 2024.xlsx | N142: MARCH TURNOVER | O142: 15 | P142: 2024-06-03 | Q142: TURNOVER SCHEDULE r97, MS TAIWO r20
A143: SL0139 | B143: 45359 | C143: 2024-03 | D143: 2024 | E143: Land | F143: Plot / unit price | G143: Green City Phase 2 (Ketu-Epe) | H143: BP-C0071 | I143: Miss Oyebola Moyosoreoluwa Boluwatife | J143: 1500000 | K143: Single register | L143: Primary: monthly turnover register | M143: BAAY PROJECTS FINANCIALS 2024.xlsx | N143: MARCH TURNOVER | O143: 19 | P143: 2024-08-03 | Q143: TURNOVER SCHEDULE r228, MR AYOMIDE r2
A144: SL0140 | B144: 45359 | C144: 2024-03 | D144: 2024 | E144: Land | F144: Plot / unit price | G144: Green City Phase 2 (Ketu-Epe) | H144: BP-C0072 | I144: Mr Oyebola Ajibola Ayobami | J144: 1500000 | K144: Single register | L144: Primary: monthly turnover register | M144: BAAY PROJECTS FINANCIALS 2024.xlsx | N144: MARCH TURNOVER | O144: 21 | P144: 2024-08-03 | Q144: TURNOVER SCHEDULE r236, MR AYOMIDE r4
A145: SL0141 | B145: 45359 | C145: 2024-03 | D145: 2024 | E145: Land | F145: Plot / unit price | G145: Green City Phase 2 (Ketu-Epe) | H145: BP-C0073 | I145: Mr Oyebola Temiloluwa Olayinka | J145: 1500000 | K145: Single register | L145: Primary: monthly turnover register | M145: BAAY PROJECTS FINANCIALS 2024.xlsx | N145: MARCH TURNOVER | O145: 20 | P145: 2024-08-03 | Q145: TURNOVER SCHEDULE r232, MR AYOMIDE r3
A146: SL0142 | B146: 45359 | C146: 2024-03 | D146: 2024 | E146: Land | F146: Plot / unit price | G146: Green City Phase 2 (Ketu-Epe) | H146: BP-C0013 | I146: Mr Tijani Moshood Abiola | J146: 400000 | K146: Single register | L146: Primary: monthly turnover register | M146: BAAY PROJECTS FINANCIALS 2024.xlsx | N146: MARCH TURNOVER | O146: 22 | P146: 2024-08-03 | Q146: TURNOVER SCHEDULE r283
A147: SL0143 | B147: 45359 | C147: 2024-03 | D147: 2024 | E147: Land | F147: Plot / unit price | G147: Green City Phase 1 (Lantaba, Ketu-Epe) | H147: BP-C0074 | I147: Mrs Oloniluyi Victoria | J147: 7000000 | K147: Single register | L147: Primary: monthly turnover register | M147: BAAY PROJECTS FINANCIALS 2024.xlsx | N147: MARCH TURNOVER | O147: 18 | P147: 2024-08-03 | Q147: TURNOVER SCHEDULE r280, MRS AGBAJE r2, MD r8
A148: SL0144 | B148: 45360 | C148: 2024-03 | D148: 2024 | E148: Land | F148: Plot / unit price | G148: Green City Phase 1 (Lantaba, Ketu-Epe) | H148: BP-C0033 | I148: Mr Olumoko Oladapo | J148: 1000000 | K148: Single register | L148: Primary: monthly turnover register | M148: BAAY PROJECTS FINANCIALS 2024.xlsx | N148: MARCH TURNOVER | O148: 25 | P148: 2024-09-03 | Q148: TURNOVER SCHEDULE r159, MS BOLANLE r16
A149: SL0145 | B149: 45360 | C149: 2024-03 | D149: 2024 | E149: Land | F149: Plot / unit price | G149: Green City Phase 2 (Ketu-Epe) | H149: BP-C0075 | I149: Ogidan Funmilayo | J149: 300000 | K149: Single register | L149: Primary: monthly turnover register | M149: BAAY PROJECTS FINANCIALS 2024.xlsx | N149: MARCH TURNOVER | O149: 24 | P149: 2024-09-03 | Q149: TURNOVER SCHEDULE r269, OGIDAN r2
A150: SL0146 | B150: 45360 | C150: 2024-03 | D150: 2024 | E150: Land | F150: Plot / unit price | G150: Green City Phase 2 (Ketu-Epe) | H150: BP-C0076 | I150: Ojo Ayomide Babatunde | J150: 500000 | K150: Single register | L150: Primary: monthly turnover register | M150: BAAY PROJECTS FINANCIALS 2024.xlsx | N150: MARCH TURNOVER | O150: 23 | P150: 2024-09-03 | Q150: TURNOVER SCHEDULE r255
A151: SL0147 | B151: 45361 | C151: 2024-03 | D151: 2024 | E151: Land | F151: Plot / unit price | G151: Green City Phase 2 (Ketu-Epe) | H151: BP-C0077 | I151: Mr Uebari Sorbari Godwin | J151: 300000 | K151: Single register | L151: Primary: monthly turnover register | M151: BAAY PROJECTS FINANCIALS 2024.xlsx | N151: MARCH TURNOVER | O151: 26 | P151: 2024-10-03 | Q151: TURNOVER SCHEDULE r304, MS ELIZABETH r24
A152: SL0148 | B152: 45362 | C152: 2024-03 | D152: 2024 | E152: Land | F152: Plot / unit price | G152: Green City Phase 1 (Lantaba, Ketu-Epe) | H152: BP-C0078 | I152: Miss Bingham Kendra | J152: 2000000 | K152: Single register | L152: Primary: monthly turnover register | M152: BAAY PROJECTS FINANCIALS 2024.xlsx | N152: MARCH TURNOVER | O152: 28 | P152: 2024-11-03 | Q152: TURNOVER SCHEDULE r240, MRS ABIMBOLA r48
... A162: SL0158 | B162: 45364 | C162: 2024-03 | D162: 2024 | E162: Land | F162: Plot / unit price | G162: Green City Phase 1 (Lantaba, Ketu-Epe) | H162: BP-C0006 | I162: Mr Olasupo Oladimeji | J162: 700000 | K162: Single register | L162: Primary: monthly turnover register | M162: BAAY PROJECTS FINANCIALS 2024.xlsx | N162: MARCH TURNOVER | O162: 37 | P162: 13/03/2024 | Q162: TURNOVER SCHEDULE r32, MRS ABIMBOLA r39
A163: SL0159 | B163: 45365 | C163: 2024-03 | D163: 2024 | E163: Land | F163: Plot / unit price | G163: Green City Phase 1 (Lantaba, Ketu-Epe) | H163: BP-C0083 | I163: Mrs Yohanna Victoria | J163: 3000000 | K163: Single register | L163: Primary: monthly turnover register | M163: BAAY PROJECTS FINANCIALS 2024.xlsx | N163: MARCH TURNOVER | O163: 38 | P163: 14/03/2024
A164: SL0160 | B164: 45366 | C164: 2024-03 | D164: 2024 | E164: Land | F164: Plot / unit price | G164: Green City Phase 1 (Lantaba, Ketu-Epe) | H164: BP-C0036 | I164: Mr Ohumende Paul Osaze | J164: 7000000 | K164: Single register | L164: Primary: monthly turnover register | M164: BAAY PROJECTS FINANCIALS 2024.xlsx | N164: MARCH TURNOVER | O164: 39 | P164: 15/03/2024 | Q164: TURNOVER SCHEDULE r121
A165: SL0161 | B165: 45367 | C165: 2024-03 | D165: 2024 | E165: Land | F165: Plot / unit price | G165: Green City Phase 1 (Lantaba, Ketu-Epe) | H165: BP-C0045 | I165: Mr Bolarinwa Iyanuoluwa Simon & Dr Bolarinwa Abisola Christianah | J165: 3600000 | K165: Single register | L165: Primary: monthly turnover register | M165: BAAY PROJECTS FINANCIALS 2024.xlsx | N165: MARCH TURNOVER | O165: 40 | P165: 16/03/2024 | Q165: MD r20
A166: SL0162 | B166: 45367 | C166: 2024-03 | D166: 2024 | E166: Land | F166: Plot / unit price | G166: Green City Phase 2 (Ketu-Epe) | H166: BP-C0051 | I166: Mr Ogunleye Olumide | J166: 150000 | K166: Single register | L166: Primary: monthly turnover register | M166: BAAY PROJECTS FINANCIALS 2024.xlsx | N166: MARCH TURNOVER | O166: 41 | P166: 16/03/2024 | Q166: TURNOVER SCHEDULE r44
A167: SL0163 | B167: 45367 | C167: 2024-03 | D167: 2024 | E167: Land | F167: Plot / unit price | G167: Green City Phase 1 (Lantaba, Ketu-Epe) | H167: BP-C0051 | I167: Mr Ogunleye Olumide | J167: 500000 | K167: Single register | L167: Primary: monthly turnover register | M167: BAAY PROJECTS FINANCIALS 2024.xlsx | N167: MARCH TURNOVER | O167: 42 | P167: 16/03/2024 | Q167: TURNOVER SCHEDULE r51
A168: SL0164 | B168: 45371 | C168: 2024-03 | D168: 2024 | E168: Land | F168: Plot / unit price | G168: Green City Phase 1 (Lantaba, Ketu-Epe) | H168: BP-C0050 | I168: Mr Atuanya Patrick Jidevo | J168: 550000 | K168: Single register | L168: Primary: monthly turnover register | M168: BAAY PROJECTS FINANCIALS 2024.xlsx | N168: MARCH TURNOVER | O168: 43 | P168: 20/03/2024 | Q168: TURNOVER SCHEDULE r147, MS YETUNDE ABISOYE r31
A169: SL0165 | B169: 45372 | C169: 2024-03 | D169: 2024 | E169: Land | F169: Plot / unit price | G169: Green City Phase 2 (Ketu-Epe) | H169: BP-C0071 | I169: Miss Oyebola Moyosoreoluwa Boluwatife | J169: 1500000 | K169: Single register | L169: Primary: monthly turnover register | M169: BAAY PROJECTS FINANCIALS 2024.xlsx | N169: MARCH TURNOVER | O169: 44 | P169: 21/03/2024 | Q169: TURNOVER SCHEDULE r229, MR AYOMIDE r5
A170: SL0166 | B170: 45372 | C170: 2024-03 | D170: 2024 | E170: Land | F170: Plot / unit price | G170: Green City Phase 1 (Lantaba, Ketu-Epe) | H170: BP-C0006 | I170: Mr Olasupo Oladimeji | J170: 875350 | K170: Single register | L170: Primary: monthly turnover register | M170: BAAY PROJECTS FINANCIALS 2024.xlsx | N170: MARCH TURNOVER | O170: 47 | P170: 21/03/2024 | Q170: TURNOVER SCHEDULE r33, MRS ABIMBOLA r40
A171: SL0167 | B171: 45372 | C171: 2024-03 | D171: 2024 | E171: Land | F171: Plot / unit price | G171: Green City Phase 2 (Ketu-Epe) | H171: BP-C0072 | I171: Mr Oyebola Ajibola Ayobami | J171: 1500000 | K171: Single register | L171: Primary: monthly turnover register | M171: BAAY PROJECTS FINANCIALS 2024.xlsx | N171: MARCH TURNOVER | O171: 46 | P171: 21/03/2024 | Q171: TURNOVER SCHEDULE r237, MR AYOMIDE r7
A172: SL0168 | B172: 45372 | C172: 2024-03 | D172: 2024 | E172: Land | F172: Plot / unit price | G172: Green City Phase 2 (Ketu-Epe) | H172: BP-C0073 | I172: Mr Oyebola Temiloluwa Olayinka | J172: 1500000 | K172: Single register | L172: Primary: monthly turnover register | M172: BAAY PROJECTS FINANCIALS 2024.xlsx | N172: MARCH TURNOVER | O172: 45 | P172: 21/03/2024 | Q172: TURNOVER SCHEDULE r233, MR AYOMIDE r6
A173: SL0169 | B173: 45373 | C173: 2024-03 | D173: 2024 | E173: Land | F173: Plot / unit price | G173: Green City Phase 1 (Lantaba, Ketu-Epe) | H173: BP-C0053 | I173: Mr Adegbembo Stephen | J173: 1000000 | K173: Single register | L173: Primary: monthly turnover register | M173: BAAY PROJECTS FINANCIALS 2024.xlsx | N173: MARCH TURNOVER | O173: 48 | P173: 22/03/2024 | Q173: TURNOVER SCHEDULE r85
A174: SL0170 | B174: 45376 | C174: 2024-03 | D174: 2024 | E174: Land | F174: Plot / unit price | G174: Green City Phase 1 (Lantaba, Ketu-Epe) | H174: BP-C0046 | I174: Mr Adesida Raphael | J174: 100000 | K174: Single register | L174: Primary: monthly turnover register | M174: BAAY PROJECTS FINANCIALS 2024.xlsx | N174: MARCH TURNOVER | O174: 49 | P174: 25/03/2024 | Q174: TURNOVER SCHEDULE r174, MD r31
A175: SL0171 | B175: 45376 | C175: 2024-03 | D175: 2024 | E175: Land | F175: Plot / unit price | G175: Green City Phase 2 (Ketu-Epe) | H175: BP-C0012 | I175: Mr Apiafi Imiebam | J175: 1800000 | K175: Single register | L175: Primary: monthly turnover register | M175: BAAY PROJECTS FINANCIALS 2024.xlsx | N175: MARCH TURNOVER | O175: 50 | P175: 25/03/2024 | Q175: TURNOVER SCHEDULE r308, MS BLESSING r28
A176: SL0172 | B176: 45376 | C176: 2024-03 | D176: 2024 | E176: Land | F176: Plot / unit price | G176: Green City Phase 2 (Ketu-Epe) | H176: BP-C0085 | I176: Mr Ayokunu Adegbayemu | J176: 1430000 | K176: Single register | L176: Primary: monthly turnover register | M176: BAAY PROJECTS FINANCIALS 2024.xlsx | N176: MARCH TURNOVER | O176: 51 | P176: 25/03/2024
A177: SL0173 | B177: 45376 | C177: 2024-03 | D177: 2024 | E177: Land | F177: Plot / unit price | G177: Green City Phase 2 (Ketu-Epe) | H177: BP-C0017 | I177: Mr John Taiwo Adeleye | J177: 1000000 | K177: Single register | L177: Primary: monthly turnover register | M177: BAAY PROJECTS FINANCIALS 2024.xlsx | N177: MARCH TURNOVER | O177: 52 | P177: 25/03/2023 | R177: Year typed as 2023 in source (25/03/2023); corrected to 2024 from the sheet month
...

Sheet Subscriptions
A1: Customer subscriptions per client register (subscribed Jan 2022 to Dec 2025)
A2: One row per customer per project, as recorded by Client Relations. Contract value and paid-to-date are as stated in the register, not recomputed.
A4: Sub ref | B4: Customer ID | C4: Customer name (register) | D4: Product line | E4: Project / estate | F4: Unit / plot | G4: Subscription date | H4: Year | I4: Contract value (₦) | J4: Paid to date per register (₦) | K4: Balance per register (₦) | L4: Payment plan | M4: Status | N4: Allocation | O4: Documents stage | P4: Realtor / contact | Q4: Source sheet | R4: Source row | S4: Date as recorded | T4: Note
A5: SB0001 | B5: BP-C0001 | C5: Mr Meshack Osagie | D5: Housing | E5: Pacific Court | F5: terrace | units: 3.0 | G5: 44593 | H5: =IF(G5="","",YEAR(G5)) | I5: 10500000 | K5: =IF(OR(I5="",J5=""),"",I5-J5) | L5: 15MONTHS | M5: PAID | P5: AKIN PHILIP | Q5: BAAY PROJECTS CLIENTS > PACIFIC COURT INVESTORS LIST | R5: 2 | S5: 2022-02-01
A6: SB0002 | B6: BP-C0002 | C6: Temidayo Oniosun | D6: Housing | E6: Pacific Court | F6: fully detached | units: 1.0 | G6: 44652 | H6: =IF(G6="","",YEAR(G6)) | I6: 52200000 | K6: =IF(OR(I6="",J6=""),"",I6-J6) | L6: 5MONTHS | M6: PAID | P6: MD | Q6: BAAY PROJECTS CLIENTS > PACIFIC COURT INVESTORS LIST | R6: 3 | S6: 2022-04-01
A7: SB0003 | B7: BP-C0003 | C7: Mrs Agbaje | D7: Housing | E7: Pacific Court | F7: fully detached | units: 1.0 | G7: 44713 | H7: =IF(G7="","",YEAR(G7)) | I7: 63000000 | K7: =IF(OR(I7="",J7=""),"",I7-J7) | L7: 10MONTHS | M7: PAID | P7: MR BIOLA AKOSILE | Q7: BAAY PROJECTS CLIENTS > PACIFIC COURT INVESTORS LIST | R7: 4 | S7: 2022-06-01
A8: SB0004 | B8: BP-C0004 | C8: Mrs Kate | D8: Housing | E8: Pacific Court | F8: terrace | units: 1.0 | G8: 44774 | H8: =IF(G8="","",YEAR(G8)) | I8: 40000000 | K8: =IF(OR(I8="",J8=""),"",I8-J8) | L8: 24MONTHS | M8: REFUND | P8: MD | Q8: BAAY PROJECTS CLIENTS > PACIFIC COURT INVESTORS LIST | R8: 5 | S8: 2022-08-01
A9: SB0005 | B9: BP-C0005 | C9: Mrs Mo | D9: Housing | E9: Pacific Court | F9: terrace | units: 1.0 | G9: 44896 | H9: =IF(G9="","",YEAR(G9)) | I9: 47000000 | K9: =IF(OR(I9="",J9=""),"",I9-J9) | L9: 10MONTHS | M9: PAID | P9: MS YETUNDE ABISOYE | Q9: BAAY PROJECTS CLIENTS > PACIFIC COURT INVESTORS LIST | R9: 6 | S9: 2022-12-01
A10: SB0006 | B10: BP-C0007 | C10: Mrs Ero | D10: Housing | E10: Pacific Court | F10: fully detached | units: 1.0 | G10: 44958 | H10: =IF(G10="","",YEAR(G10)) | I10: 600000000 | K10: =IF(OR(I10="",J10=""),"",I10-J10) | L10: 3MONTHS | M10: PAID | P10: PASTOR GABRIEL | Q10: BAAY PROJECTS CLIENTS > PACIFIC COURT INVESTORS LIST | R10: 7 | S10: 2023-02-01
A11: SB0007 | B11: BP-C0008 | C11: Mr Rasaq Roqeeb | D11: Land | E11: Green City Phase 1 (Lantaba, Ketu-Epe) | F11: 250sqm | G11: 44967 | H11: =IF(G11="","",YEAR(G11)) | I11: 3900000 | J11: 3900000 | K11: =IF(OR(I11="",J11=""),"",I11-J11) | L11: 6 months | M11: Bought | N11: BLOCK F1 | O11: Collected by Client | P11: MD | Q11: BAAY PROJECTS CLIENTS > GREEN CITY KETU 1 INVESTORS LIS | R11: 29 | S11: 2023-10-02
A12: SB0008 | B12: BP-C0011 | C12: OLAIYA SUNDAY TEMITOPE | D12: Land | E12: Green City Phase 1 (Lantaba, Ketu-Epe) | F12: 600sqm | G12: 45061 | H12: =IF(G12="","",YEAR(G12)) | I12: 1500000 | J12: 1500000 | K12: =IF(OR(I12="",J12=""),"",I12-J12) | L12: 3months | M12: Bought | N12: BLOCK E2 | O12: Yet to collect Physical Document with MD | P12: Ms Abimbola | Q12: BAAY PROJECTS CLIENTS > GREEN CITY KETU 1 INVESTORS LIS | R12: 4 | S12: 15/05/2023
A13: SB0009 | B13: BP-C0013 | C13: MOSHOOD TIJANI | D13: Land | E13: Green City Phase 1 (Lantaba, Ketu-Epe) | F13: 250sqm | G13: 45073 | H13: =IF(G13="","",YEAR(G13)) | I13: 1500000 | J13: 1400000 | K13: =IF(OR(I13="",J13=""),"",I13-J13) | L13: 3months | M13: Bought | N13: BLOCK B2A | O13: Yet to collect Deeed | P13: MD | Q13: BAAY PROJECTS CLIENTS > GREEN CITY KETU 1 INVESTORS LIS | R13: 3 | S13: 27/05/2023
A14: SB0010 | B14: BP-C0014 | C14: PROF OLUGBENGA AKINADE/MRS ARAWOMO OMOLOLA | D14: Land | E14: Green City Phase 1 (Lantaba, Ketu-Epe) | F14: 500sqm | G14: 45083 | H14: =IF(G14="","",YEAR(G14)) | I14: 3600000 | J14: 3600000 | K14: =IF(OR(I14="",J14=""),"",I14-J14) | L14: 3months | M14: Bought | N14: BLOCK D7 | O14: Physical Document Collected | P14: MD | Q14: BAAY PROJECTS CLIENTS > GREEN CITY KETU 1 INVESTORS LIS | R14: 5 | S14: 2023-06-06
A15: SB0011 | B15: BP-C0015 | C15: MR Damilare Ositade Owolabi | D15: Land | E15: Green City Phase 1 (Lantaba, Ketu-Epe) | F15: 250sqm | G15: 45092 | H15: =IF(G15="","",YEAR(G15)) | I15: 1500000 | J15: 1500000 | K15: =IF(OR(I15="",J15=""),"",I15-J15) | L15: 3months | M15: Bought | N15: BLOCK D4B | O15: Yet to collect Physical Document | P15: IDARA | Q15: BAAY PROJECTS CLIENTS > GREEN CITY KETU 1 INVESTORS LIS | R15: 7 | S15: 15/06/2023
A16: SB0012 | B16: BP-C0016 | C16: Mr Tobi Adesina | D16: Land | E16: Green City Phase 1 (Lantaba, Ketu-Epe) | F16: 250sqm | G16: 45103 | H16: =IF(G16="","",YEAR(G16)) | I16: 1500000 | K16: =IF(OR(I16="",J16=""),"",I16-J16) | M16: incentives | N16: BLOCK D6A | O16: Collected by Client | P16: TOBY AND TYE | Q16: BAAY PROJECTS CLIENTS > GREEN CITY KETU 1 INVESTORS LIS | R16: 8 | S16: 26/06/2023 | T16: Paid-to-date in source: PARTNERSHIP
A17: SB0013 | B17: BP-C0017 | C17: Mr. Taiwo John Adeleye. | D17: Land | E17: Green City Phase 1 (Lantaba, Ketu-Epe) | F17: 250sqm | G17: 45129 | H17: =IF(G17="","",YEAR(G17)) | I17: 1500000 | J17: 1500000 | K17: =IF(OR(I17="",J17=""),"",I17-J17) | L17: 3months | M17: bought | N17: BLOCK D5b | O17: Collected by Client | P17: MD | Q17: BAAY PROJECTS CLIENTS > GREEN CITY KETU 1 INVESTORS LIS | R17: 10 | S17: 22/07/2023
A18: SB0014 | B18: BP-C0018 | C18: Mr Sunday Gideon | D18: Land | E18: Green City Phase 1 (Lantaba, Ketu-Epe) | F18: 250sqm | G18: 45137 | H18: =IF(G18="","",YEAR(G18)) | I18: 1500000 | J18: 1500000 | K18: =IF(OR(I18="",J18=""),"",I18-J18) | L18: Outright | M18: bought | N18: BLOCK D5A | O18: Collected by client | P18: MS BLESSING | Q18: BAAY PROJECTS CLIENTS > GREEN CITY KETU 1 INVESTORS LIS | R18: 9 | S18: 30/07/2023
A19: SB0015 | B19: BP-C0020 | C19: Mr Adebowale Oluwapelumi Joseph | D19: Land | E19: Green City Phase 1 (Lantaba, Ketu-Epe) | F19: 600sqm | G19: 45161 | H19: =IF(G19="","",YEAR(G19)) | I19: 3600000 | J19: 3600000 | K19: =IF(OR(I19="",J19=""),"",I19-J19) | L19: 3 months | M19: Bought | N19: BLOCK C3 | O19: Collected by client sister | P19: MD | Q19: BAAY PROJECTS CLIENTS > GREEN CITY KETU 1 INVESTORS LIS | R19: 13 | S19: 23/08/2023
A20: SB0016 | B20: BP-C0021 | C20: Mr Oyewole Sheriff Oyewusi | D20: Land | E20: Green City Phase 1 (Lantaba, Ketu-Epe) | F20: 600sqm | G20: 45161 | H20: =IF(G20="","",YEAR(G20)) | I20: 3600000 | J20: 3600000 | K20: =IF(OR(I20="",J20=""),"",I20-J20) | L20: 3 months | M20: Bought | N20: BLOCK C6 | O20: Yet to collect Physical Document | P20: Ms Bolanle | Q20: BAAY PROJECTS CLIENTS > GREEN CITY KETU 1 INVESTORS LIS | R20: 12 | S20: 23/08/2023
A21: SB0017 | B21: BP-C0022 | C21: Mr Folaranmi Olatunde | D21: Land | E21: Green City Phase 1 (Lantaba, Ketu-Epe) | F21: 600sqm | G21: 45162 | H21: =IF(G21="","",YEAR(G21)) | I21: 1500000 | J21: 1500000 | K21: =IF(OR(I21="",J21=""),"",I21-J21) | L21: 3 months | M21: Bought | N21: BLOCK E2 | O21: Collected by Client representative | P21: MD | Q21: BAAY PROJECTS CLIENTS > GREEN CITY KETU 1 INVESTORS LIS | R21: 11 | S21: 24/08/2023
A22: SB0018 | B22: BP-C0023 | C22: MR KOREDE ADESE | D22: Land | E22: Green City Phase 1 (Lantaba, Ketu-Epe) | F22: 250sqm | G22: 45166 | H22: =IF(G22="","",YEAR(G22)) | I22: 3000000 | J22: 3000000 | K22: =IF(OR(I22="",J22=""),"",I22-J22) | L22: 3months | M22: Bought | N22: BLOCK D6b | O22: Physical Document Collected | P22: MD | Q22: BAAY PROJECTS CLIENTS > GREEN CITY KETU 1 INVESTORS LIS | R22: 6 | S22: 28/8/2023
A23: SB0019 | B23: BP-C0024 | C23: Ms Peace Ikpotokin | D23: Land | E23: Green City Phase 1 (Lantaba, Ketu-Epe) | F23: 600sqm | G23: 45166 | H23: =IF(G23="","",YEAR(G23)) | I23: 3600000 | J23: 50000 | K23: =IF(OR(I23="",J23=""),"",I23-J23) | L23: 6months | M23: Promise | N23: NIL | O23: Initial deposit | P23: MD | Q23: BAAY PROJECTS CLIENTS > GREEN CITY KETU 1 INVESTORS LIS | R23: 14 | S23: 28/08/2023
A24: SB0020 | B24: BP-C0025 | C24: Mrs Obadara Dorcas Adebisi | D24: Land | E24: Green City Phase 1 (Lantaba, Ketu-Epe) | F24: 250sqm | G24: 45173 | H24: =IF(G24="","",YEAR(G24)) | I24: 4320000 | J24: 4320000 | K24: =IF(OR(I24="",J24=""),"",I24-J24) | L24: 3 months | M24: Bought | N24: BLOCK D4A | O24: Collected by Client | P24: Barister Nelson | Q24: BAAY PROJECTS CLIENTS > GREEN CITY KETU 1 INVESTORS LIS | R24: 15 | S24: 2023-04-09
A25: SB0021 | B25: BP-C0027 | C25: Mr Edun Ayobami Simeon and bro | D25: Land | E25: Green City Phase 1 (Lantaba, Ketu-Epe) | F25: 2 units of 600sqm | G25: 45190 | H25: =IF(G25="","",YEAR(G25)) | I25: 1500000 | J25: 1500000 | K25: =IF(OR(I25="",J25=""),"",I25-J25) | L25: 12 months | M25: Bought | N25: BLOCK F2345 | O25: Collected by client | P25: Mr Olaiya/MD | Q25: BAAY PROJECTS CLIENTS > GREEN CITY KETU 1 INVESTORS LIS | R25: 16 | S25: 21/09/2023
A26: SB0022 | B26: BP-C0026 | C26: Mr & Mrs Adebayo Dada | D26: Land | E26: Green City Phase 1 (Lantaba, Ketu-Epe) | F26: 500sqm | G26: 45205 | H26: =IF(G26="","",YEAR(G26)) | I26: 8400000 | J26: 8400000 | K26: =IF(OR(I26="",J26=""),"",I26-J26) | L26: 3months | M26: Bought | N26: BLOCK D2 | O26: Collected by Client's Brother | P26: Mrs Abimbola | Q26: BAAY PROJECTS CLIENTS > GREEN CITY KETU 1 INVESTORS LIS | R26: 17 | S26: 2023-06-10
A27: SB0023 | B27: BP-C0031 | C27: Mr Eguavoen Harrison | D27: Land | E27: Green City Agbowa | F27: 250sqm | G27: 45209 | H27: =IF(G27="","",YEAR(G27)) | I27: 750000 | J27: 750000 | K27: =IF(OR(I27="",J27=""),"",I27-J27) | L27: 3months | M27: Refund | P27: Ms Blessing | Q27: BAAY PROJECTS CLIENTS > GREENCITY AGBOWA | R27: 2 | S27: 2023-10-10
A28: SB0024 | B28: BP-C0032 | C28: Mr Tomiwa Ibiks ********* | D28: Land | E28: Green City Phase 1 (Lantaba, Ketu-Epe) | F28: 600sqm | G28: 45209 | H28: =IF(G28="","",YEAR(G28)) | I28: 3600000 | J28: 1000000 | K28: =IF(OR(I28="",J28=""),"",I28-J28) | L28: 3months | M28: Paying | N28: Not Allocated Yet | O28: Not yet submitted subscription form | P28: MD | Q28: BAAY PROJECTS CLIENTS > GREEN CITY KETU 1 INVESTORS LIS | R28: 24 | S28: 2023-10-10
A29: SB0025 | B29: BP-C0033 | C29: Mr Olumoko Oladapo Oluwaseun | D29: Land | E29: Green City Phase 1 (Lantaba, Ketu-Epe) | F29: 500sqm | G29: 45211 | H29: =IF(G29="","",YEAR(G29)) | I29: 6000000 | J29: 6000000 | K29: =IF(OR(I29="",J29=""),"",I29-J29) | L29: 3months | M29: Bought | N29: BLOCK C4 | O29: Not yet Collected | P29: Ms Bolanle | Q29: BAAY PROJECTS CLIENTS > GREEN CITY KETU 1 INVESTORS LIS + Foreshore financials sheet | R29: 21 | S29: 2023-12-10
A30: SB0026 | B30: BP-C0034 | C30: Mrs Ndubuisi Ujunwa | D30: Land | E30: Green City Phase 1 (Lantaba, Ketu-Epe) | F30: 250sqm | G30: 45211 | H30: =IF(G30="","",YEAR(G30)) | I30: 3900000 | J30: 3900000 | K30: =IF(OR(I30="",J30=""),"",I30-J30) | L30: 3 Months | M30: Bought | N30: BLOCK D3A | O30: Collected by Client | P30: Ms Immaculate | Q30: BAAY PROJECTS CLIENTS > GREEN CITY KETU 1 INVESTORS LIS | R30: 22 | S30: 2023-12-10
A31: SB0027 | B31: BP-C0035 | C31: Vacant | D31: Land | E31: Green City Phase 1 (Lantaba, Ketu-Epe) | F31: 600sqm | G31: 45211 | H31: =IF(G31="","",YEAR(G31)) | I31: 1500000 | J31: 1500000 | K31: =IF(OR(I31="",J31=""),"",I31-J31) | L31: 3months | M31: bought | N31: BLOCK C2 | O31: Yet to collect Physical Document | P31: MD | Q31: BAAY PROJECTS CLIENTS > GREEN CITY KETU 1 INVESTORS LIS | R31: 23 | S31: 2023-12-10
A32: SB0028 | B32: BP-C0037 | C32: Miss Okezie Mandy Ifeoma | D32: Land | E32: Green City Phase 1 (Lantaba, Ketu-Epe) | F32: 250sqm | G32: 45228 | H32: =IF(G32="","",YEAR(G32)) | I32: 4600000 | J32: 4600000 | K32: =IF(OR(I32="",J32=""),"",I32-J32) | L32: 3 Months | M32: Bought | N32: BLOCK D3B | O32: Collected by Client | P32: Celina | Q32: BAAY PROJECTS CLIENTS > GREEN CITY KETU 1 INVESTORS LIS | R32: 25 | S32: 29/10/2023
A33: SB0029 | B33: BP-C0040 | C33: Bassey Christopher | D33: Land | E33: Green City Phase 1 (Lantaba, Ketu-Epe) | F33: 1000sqm & 600sqm | G33: 45229 | H33: =IF(G33="","",YEAR(G33)) | I33: 2000000 | J33: 2000000 | K33: =IF(OR(I33="",J33=""),"",I33-J33) | L33: 3 Months | M33: Bought | N33: BLOCK A45 | O33: Collected by Client | P33: Ms Immaculate | Q33: BAAY PROJECTS CLIENTS > GREEN CITY KETU 1 INVESTORS LIS | R33: 26 | S33: 30/10/2023
A34: SB0030 | B34: BP-C0029 | C34: Mr Ohanehi Anthony Chukwunonso | D34: Land | E34: Green City Phase 1 (Lantaba, Ketu-Epe) | F34: 600sqm Commercial | G34: 45229 | H34: =IF(G34="","",YEAR(G34)) | I34: 3000000 | J34: 9540000 | K34: =IF(OR(I34="",J34=""),"",I34-J34) | L34: 6 Months | M34: Bought | N34: BLOCK A678 | O34: Collected by Client | P34: Ms Immaculate | Q34: BAAY PROJECTS CLIENTS > GREEN CITY KETU 1 INVESTORS LIS + Foreshore financials sheet | R34: 19 | S34: 2023-10-30
A35: SB0031 | B35: BP-C0036 | C35: Ohumende Paul Osaze | D35: Land | E35: Green City Phase 1 (Lantaba, Ketu-Epe) | F35: 600sqm (6 Units) | G35: 45232 | H35: =IF(G35="","",YEAR(G35)) | I35: 15000000 | J35: 15000000 | K35: =IF(OR(I35="",J35=""),"",I35-J35) | L35: 3 months | M35: Bought | N35: BLOCK H123456 | O35: Collected by Client | P35: MD | Q35: BAAY PROJECTS CLIENTS > GREEN CITY KETU 1 INVESTORS LIS | R35: 27 | S35: 2023-02-11
A36: SB0032 | B36: BP-C0041 | C36: Alhaji Badamasi Mohammadu | D36: Land | E36: Green City Phase 1 (Lantaba, Ketu-Epe) | F36: 500sqm | G36: 45233 | H36: =IF(G36="","",YEAR(G36)) | I36: 27600000 | J36: 27600000 | K36: =IF(OR(I36="",J36=""),"",I36-J36) | L36: 3 months | M36: Bought | N36: BLOCK G1 | O36: Collected by Client | P36: Ms Tobi Associate | Q36: BAAY PROJECTS CLIENTS > GREEN CITY KETU 1 INVESTORS LIS | R36: 28 | S36: 2023-03-11
A37: SB0033 | B37: BP-C0043 | C37: Mrs Oladiran Omolola Agnes | D37: Land | E37: Green City Agbowa | F37: 250sqm | G37: 45239 | H37: =IF(G37="","",YEAR(G37)) | I37: 750000 | J37: 750000 | K37: =IF(OR(I37="",J37=""),"",I37-J37) | L37: 3 Months | M37: Convert to ketu 2 | P37: Mr Pelumi | Q37: BAAY PROJECTS CLIENTS > GREENCITY AGBOWA | R37: 3 | S37: 2023-09-11
A38: SB0034 | B38: BP-C0044 | C38: Oluwase Babajide Victor | D38: Land | E38: Green City Phase 1 (Lantaba, Ketu-Epe) | F38: 600sqm | G38: 45239 | H38: =IF(G38="","",YEAR(G38)) | I38: 5290000 | J38: 5290000 | K38: =IF(OR(I38="",J38=""),"",I38-J38) | L38: 6 Months | M38: Bought | N38: BLOCK F7 | O38: Collected by Client | P38: MD | Q38: BAAY PROJECTS CLIENTS > GREEN CITY KETU 1 INVESTORS LIS | R38: 30 | S38: 2023-09-11
A39: SB0035 | B39: BP-C0043 | C39: Mrs Oladiran Omolola | D39: Land | E39: Green City Phase 2 (Ketu-Epe) | F39: 250sqm | G39: 45239 | H39: =IF(G39="","",YEAR(G39)) | I39: 1300000 | K39: =IF(OR(I39="",J39=""),"",I39-J39) | L39: 6 Months | M39: REFUND | N39: BLOCK E, PLOT 6 | O39: Not yet Processed | P39: Pelumi | Q39: BAAY PROJECTS CLIENTS > GREEN CITY KETU EPE 2 | R39: 9 | S39: 2023-09-11 | T39: Paid-to-date in source: REFUND
A40: SB0036 | B40: BP-C0045 | C40: Bolarinwa Iyanuoluwa Simon | D40: Land | E40: Green City Phase 1 (Lantaba, Ketu-Epe) | F40: 600sqm | G40: 45245 | H40: =IF(G40="","",YEAR(G40)) | I40: 5290000 | J40: 5290000 | K40: =IF(OR(I40="",J40=""),"",I40-J40) | L40: 3 Months | M40: Bought | N40: BLOCK E3 | O40: Collected by Client | P40: MD | Q40: BAAY PROJECTS CLIENTS > GREEN CITY KETU 1 INVESTORS LIS | R40: 31 | S40: 15/11/2023
A41: SB0037 | B41: BP-C0047 | C41: Ms Paulina Kehinde Akhere George | D41: Housing | E41: Pacific Court | F41: Land | units: 1.0 | G41: 45261 | H41: =IF(G41="","",YEAR(G41)) | I41: 21500000 | K41: =IF(OR(I41="",J41=""),"",I41-J41) | L41: 3 MONTHS | M41: PAID | P41: Barr. Amokeodo | Q41: BAAY PROJECTS CLIENTS > PACIFIC COURT INVESTORS LIST | R41: 10 | S41: 2023-12-01
A42: SB0038 | B42: BP-C0048 | C42: Mr Araokonmi Sodiq Ayinla | D42: Land | E42: Green City Phase 1 (Lantaba, Ketu-Epe) | F42: 250sqm | G42: 45268 | H42: =IF(G42="","",YEAR(G42)) | I42: 5040000 | J42: 5040000 | K42: =IF(OR(I42="",J42=""),"",I42-J42) | L42: 3 Months | M42: Bought | N42: BLOCK A12 | O42: Collected by Rep | P42: Yetunde/MD | Q42: BAAY PROJECTS CLIENTS > GREEN CITY KETU 1 INVESTORS LIS | R42: 33 | S42: 2023-08-12
A43: SB0039 | B43: BP-C0049 | C43: Mr Ali Ifesinachi Innocent | D43: Land | E43: Green City Phase 1 (Lantaba, Ketu-Epe) | F43: 500sqm | G43: 45271 | H43: =IF(G43="","",YEAR(G43)) | I43: 2743680 | J43: 2743680 | K43: =IF(OR(I43="",J43=""),"",I43-J43) | L43: 3 Months | M43: Bought | N43: BLOCK G3 | O43: Collected by rep (Miss Ude Ifunaya) | P43: MD | Q43: BAAY PROJECTS CLIENTS > GREEN CITY KETU 1 INVESTORS LIS | R43: 32 | S43: 2023-11-12
A44: SB0040 | B44: BP-C0050 | C44: Mr Atuanya Patrick Jideovo | D44: Land | E44: Green City Phase 1 (Lantaba, Ketu-Epe) | F44: 500sqm | G44: 45274 | H44: =IF(G44="","",YEAR(G44)) | I44: 2600000 | J44: 2600000 | K44: =IF(OR(I44="",J44=""),"",I44-J44) | L44: 6 Months | M44: Bought | N44: BLOCK G4 | O44: Collected by client | P44: Yetunde/MD | Q44: BAAY PROJECTS CLIENTS > GREEN CITY KETU 1 INVESTORS LIS | R44: 34 | S44: 14/12/2023
A45: SB0041 | B45: BP-C0023 | C45: MR KOREDE ADESE | D45: Land | E45: Green City Agbowa | F45: 500sqm | G45: 45278 | H45: =IF(G45="","",YEAR(G45)) | I45: 2200000 | J45: 500000 | K45: =IF(OR(I45="",J45=""),"",I45-J45) | L45: 8 Months | M45: Paying | P45: MD | Q45: BAAY PROJECTS CLIENTS > GREENCITY AGBOWA | R45: 4 | S45: 18/12/2023
A46: SB0042 | B46: BP-C0051 | C46: Mr Ogunleye Olumide Victor | D46: Land | E46: Green City Agbowa | F46: 500sqm | G46: 45280 | H46: =IF(G46="","",YEAR(G46)) | I46: 3000000 | J46: 1000000 | K46: =IF(OR(I46="",J46=""),"",I46-J46) | L46: 3 Months | M46: Paying | P46: MD | Q46: BAAY PROJECTS CLIENTS > GREENCITY AGBOWA | R46: 5 | S46: 20/12/2023
A47: SB0043 | B47: BP-C0052 | C47: Mathias Ojoma Lilian | D47: Land | E47: Green City Phase 1 (Lantaba, Ketu-Epe) | F47: 250sqm | G47: 45283 | H47: =IF(G47="","",YEAR(G47)) | I47: 5796000 | J47: 5796000 | K47: =IF(OR(I47="",J47=""),"",I47-J47) | L47: 3 Months | M47: Bought | N47: BLOCK B7A | O47: Collected by Client | P47: Ms Immaculate | Q47: BAAY PROJECTS CLIENTS > GREEN CITY KETU 1 INVESTORS LIS | R47: 38 | S47: 23/12/2023
A48: SB0044 | B48: BP-C0053 | C48: Mr Adegbembo Stephen Oluwagbemiga | D48: Land | E48: Green City Phase 1 (Lantaba, Ketu-Epe) | F48: 500sqm | G48: 45286 | H48: =IF(G48="","",YEAR(G48)) | I48: 2640000 | J48: 2640000 | K48: =IF(OR(I48="",J48=""),"",I48-J48) | L48: 6 Months | M48: Bought | N48: BLOCK D7 | O48: Collected by client | P48: Ms Elizabeth | Q48: BAAY PROJECTS CLIENTS > GREEN CITY KETU 1 INVESTORS LIS | R48: 37 | S48: 26/12/2023
A49: SB0045 | B49: BP-C0054 | C49: Mr Ademola Adeniyi | D49: Land | E49: Green City Phase 1 (Lantaba, Ketu-Epe) | F49: 1000sqm | G49: 45288 | H49: =IF(G49="","",YEAR(G49)) | I49: 2640000 | J49: 2640000 | K49: =IF(OR(I49="",J49=""),"",I49-J49) | L49: 3 Months | M49: Bought | N49: BLOCK D89 | O49: Collected by Client | P49: Ms Abimbola | Q49: BAAY PROJECTS CLIENTS > GREEN CITY KETU 1 INVESTORS LIS | R49: 39 | S49: 28/12/2023
A50: SB0046 | B50: BP-C0006 | C50: Olasupo Oladimeji | D50: Land | E50: Green City Phase 1 (Lantaba, Ketu-Epe) | F50: 1000sqm | G50: 45288 | H50: =IF(G50="","",YEAR(G50)) | I50: 10000000 | J50: 10000000 | K50: =IF(OR(I50="",J50=""),"",I50-J50) | L50: 3 months | M50: Bought | N50: BLOCK B45 | O50: Collected by Client | P50: Ms Abimbola | Q50: BAAY PROJECTS CLIENTS > GREEN CITY KETU 1 INVESTORS LIS | R50: 40 | S50: 28/12/2023
A51: SB0047 | B51: BP-C0056 | C51: Mr Adeuti Olanrewaju Babatunde | D51: Land | E51: Green City Phase 1 (Lantaba, Ketu-Epe) | F51: 250sqm | G51: 45289 | H51: =IF(G51="","",YEAR(G51)) | I51: 5040000 | J51: 5040000 | K51: =IF(OR(I51="",J51=""),"",I51-J51) | L51: 3 Months | M51: Bought | N51: BLOCK G2A | O51: Collected by rep | P51: Ms Abimbola | Q51: BAAY PROJECTS CLIENTS > GREEN CITY KETU 1 INVESTORS LIS | R51: 36 | S51: 29/12/2023
A52: SB0048 | B52: BP-C0058 | C52: Mr Oniyide Olaoluwa | D52: Land | E52: Green City Phase 1 (Lantaba, Ketu-Epe) | F52: 500sqm | G52: 45289 | H52: =IF(G52="","",YEAR(G52)) | I52: 5500000 | J52: 5500000 | K52: =IF(OR(I52="",J52=""),"",I52-J52) | L52: 3 Months | M52: Bought | N52: BLOCK G5 | O52: Collected By Rep | P52: Mr Charles | Q52: BAAY PROJECTS CLIENTS > GREEN CITY KETU 1 INVESTORS LIS | R52: 35 | S52: 29/12/2023
A53: SB0049 | B53: BP-C0059 | C53: Elochukwu George | D53: Land | E53: Green City Phase 1 (Lantaba, Ketu-Epe) | F53: 500sqm | G53: 45291 | H53: =IF(G53="","",YEAR(G53)) | I53: 10000000 | J53: 10000000 | K53: =IF(OR(I53="",J53=""),"",I53-J53) | L53: 3 months | M53: Bought | N53: BLOCK B3 | O53: Collected by Client | P53: Ms Abimbola | Q53: BAAY PROJECTS CLIENTS > GREEN CITY KETU 1 INVESTORS LIS | R53: 41 | S53: 31/12/2023
A54: SB0050 | B54: BP-C0061 | C54: OGUNKOYA EMMANUEL | D54: Land | E54: Green City Phase 2 (Ketu-Epe) | F54: 250sqm | G54: 45296 | H54: =IF(G54="","",YEAR(G54)) | I54: 1800000 | J54: 1700000 | K54: =IF(OR(I54="",J54=""),"",I54-J54) | L54: 3 months | M54: bought | N54: BLOCK E, PLOT 7 | O54: Not yet Collected | P54: MD | Q54: BAAY PROJECTS CLIENTS > GREEN CITY KETU EPE 2 | R54: 2 | S54: 2024-05-01
A55: SB0051 | B55: BP-C0017 | C55: TAIWO JOHN ADELEYE | D55: Land | E55: Green City Phase 2 (Ketu-Epe) | F55: 500sqm | G55: 45306 | H55: =IF(G55="","",YEAR(G55)) | I55: 3500000 | J55: 3500000 | K55: =IF(OR(I55="",J55=""),"",I55-J55) | L55: 6 Months | M55: bought | N55: BLOCK D, PLOT 1 | O55: Collected by Client | P55: MD | Q55: BAAY PROJECTS CLIENTS > GREEN CITY KETU EPE 2 | R55: 3 | S55: 15/01/2024
A56: SB0052 | B56: BP-C0039 | C56: Alabi Abdulazeez Toyosi | D56: Land | E56: Green City Phase 2 (Ketu-Epe) | F56: 250sqm | G56: 45321 | H56: =IF(G56="","",YEAR(G56)) | I56: 1800000 | J56: 1800000 | K56: =IF(OR(I56="",J56=""),"",I56-J56) | L56: 6 Months | M56: REFUND | N56: BLOCK E, PLOT 6 | O56: Not yet Collected | P56: MD | Q56: BAAY PROJECTS CLIENTS > GREEN CITY KETU EPE 2 | R56: 4 | S56: 30/01/2024
A57: SB0053 | B57: BP-C0062 | C57: Mr Agbaje Christopher Usiola | D57: Land | E57: Green City Phase 1 (Lantaba, Ketu-Epe) | F57: 600sqm | G57: 45323 | H57: =IF(G57="","",YEAR(G57)) | I57: 5040000 | J57: 5040000 | K57: =IF(OR(I57="",J57=""),"",I57-J57) | L57: 3 Months | M57: Bought | N57: BLOCK E6 | O57: Deed Collected by Client | P57: MD | Q57: BAAY PROJECTS CLIENTS > GREEN CITY KETU 1 INVESTORS LIS | R57: 42 | S57: 2024-01-02
A58: SB0054 | B58: BP-C0063 | C58: Omodara Adewale David | D58: Land | E58: Green City Phase 2 (Ketu-Epe) | F58: 500sqm | G58: 45326 | H58: =IF(G58="","",YEAR(G58)) | I58: 3500000 | J58: 3500000 | K58: =IF(OR(I58="",J58=""),"",I58-J58) | L58: 3 months | M58: Bought | N58: BLOCK D, PLOT 2 | O58: Collected by Client | P58: Ms Taiwo Ajibola | Q58: BAAY PROJECTS CLIENTS > GREEN CITY KETU EPE 2 | R58: 5 | S58: 2024-04-02
... A104: SB0100 | B104: BP-C0109 | C104: Dr Okeyedun Taiwo Akinbami | D104: Land | E104: Green City Phase 3 (Omu-Epe) | F104: 250Sqm | G104: 45492 | H104: =IF(G104="","",YEAR(G104)) | I104: 2400000 | J104: 300000 | K104: =IF(OR(I104="",J104=""),"",I104-J104) | L104: 6 Months | M104: Paying | N104: BLOCK H, PLOT 3 | O104: Not Yet Processed | P104: MD | Q104: BAAY PROJECTS CLIENTS > GREEN CITY PHASE 3, OMU EPE | R104: 2 | S104: 19/07/2024
A105: SB0101 | B105: BP-C0110 | C105: Mr Adeyemi Kayode | D105: Land | E105: Green City Phase 3 (Omu-Epe) | F105: 500Sqm | G105: 45496 | H105: =IF(G105="","",YEAR(G105)) | I105: 3800000 | J105: 3800000 | K105: =IF(OR(I105="",J105=""),"",I105-J105) | L105: 3 months | M105: Bought | N105: BLOCK F, PLOT 7 | O105: Deed Picked up by client | P105: Ms Bola | Q105: BAAY PROJECTS CLIENTS > GREEN CITY PHASE 3, OMU EPE + Foreshore financials sheet | R105: 8 | S105: 23/07/2024 | T105: Subscription date in source looks mistyped (05/08/0204); left blank
A106: SB0102 | B106: BP-C0026 | C106: Mr & Mrs Adebayo Dada | D106: Land | E106: Green City Phase 3 (Omu-Epe) | F106: 250SQM | G106: 45506 | H106: =IF(G106="","",YEAR(G106)) | I106: 2000000 | J106: 2000000 | K106: =IF(OR(I106="",J106=""),"",I106-J106) | L106: 3 months | M106: Bought | N106: BLOCK D, PLOT 1 | O106: Deed collected by client | P106: Mrs Abimbola | Q106: BAAY PROJECTS CLIENTS > GREEN CITY PHASE 3, OMU EPE | R106: 7 | S106: 2024-02-08
A107: SB0103 | B107: BP-C0111 | C107: Mr Adenuga Lukman Ebenezer | D107: Land | E107: Green City Phase 3 (Omu-Epe) | F107: 250SQM | G107: 45506 | H107: =IF(G107="","",YEAR(G107)) | I107: 1860000 | J107: 1860000 | K107: =IF(OR(I107="",J107=""),"",I107-J107) | L107: 3 months | M107: Bought | N107: BLOCK D, PLOT 5 | O107: Deed collected by client | P107: Ms Adenike | Q107: BAAY PROJECTS CLIENTS > GREEN CITY PHASE 3, OMU EPE | R107: 6 | S107: 2024-02-08
A108: SB0104 | B108: BP-C0037 | C108: Miss Okezie Mandy Ifeoma | D108: Land | E108: Green City Phase 3 (Omu-Epe) | F108: 250Sqm | G108: 45508 | H108: =IF(G108="","",YEAR(G108)) | I108: 1860000 | J108: 1860000 | K108: =IF(OR(I108="",J108=""),"",I108-J108) | L108: 3 months | M108: Bought | N108: BLOCK D, PLOT 2 | O108: Deed collected by client | P108: Ms Celina | Q108: BAAY PROJECTS CLIENTS > GREEN CITY PHASE 3, OMU EPE | R108: 5 | S108: 2024-04-08
A109: SB0105 | B109: BP-C0066 | C109: Miss Omosanya Dotun Akeju | D109: Land | E109: Green City Phase 3 (Omu-Epe) | F109: 500SQM | G109: 45509 | H109: =IF(G109="","",YEAR(G109)) | I109: 3800000 | J109: 3800000 | K109: =IF(OR(I109="",J109=""),"",I109-J109) | L109: 3 months | M109: Bought | N109: BLOCK G, PLOT 11 | O109: Contract of Sales signed. | P109: Ms Bola | Q109: BAAY PROJECTS CLIENTS > GREEN CITY PHASE 3, OMU EPE + Foreshore financials sheet | R109: 29 | S109: 2024-05-08
A110: SB0106 | B110: BP-C0112 | C110: Mr Lawson Albert Olumide | D110: Housing | E110: Pacific Court | F110: Semi Detached 3 Bedroom with BQ Carcass | units: 1.0 | G110: 45512 | H110: =IF(G110="","",YEAR(G110)) | I110: 55000000 | K110: =IF(OR(I110="",J110=""),"",I110-J110) | L110: 12 days | M110: PAID | P110: Mr Ayo | Q110: BAAY PROJECTS CLIENTS > PACIFIC COURT INVESTORS LIST | R110: 11 | S110: 2024-08-08
A111: SB0107 | B111: BP-C0019 | C111: Mr Ogbu Pius Ejaka | D111: Land | E111: Green City Phase 3 (Omu-Epe) | F111: 500SQM | G111: 45516 | H111: =IF(G111="","",YEAR(G111)) | I111: 3510000 | J111: 3510000 | K111: =IF(OR(I111="",J111=""),"",I111-J111) | L111: 3 months | M111: Bought | N111: BLOCK B, PLOT 3 | O111: Deed collected by client | P111: Ms Anointing | Q111: BAAY PROJECTS CLIENTS > GREEN CITY PHASE 3, OMU EPE + Foreshore financials sheet | R111: 34 | S111: 2024-12-08
A112: SB0108 | B112: BP-C0113 | C112: Mr Udoezi Paul | D112: Land | E112: Green City Phase 3 (Omu-Epe) | F112: 500SQM | G112: 45516 | H112: =IF(G112="","",YEAR(G112)) | I112: 3800000 | J112: 500000 | K112: =IF(OR(I112="",J112=""),"",I112-J112) | L112: 3 months | M112: Paying | N112: BLOCK G, PLOT 4 | O112: Not Yet Processed | P112: Ms Blessing | Q112: BAAY PROJECTS CLIENTS > GREEN CITY PHASE 3, OMU EPE | R112: 15 | S112: 2024-12-08
A113: SB0109 | B113: BP-C0114 | C113: Miss Ohaego Ijeoma Goodness | D113: Land | E113: Green City Phase 3 (Omu-Epe) | F113: 500SQM | G113: 45520 | H113: =IF(G113="","",YEAR(G113)) | I113: 3800000 | J113: 3800000 | K113: =IF(OR(I113="",J113=""),"",I113-J113) | L113: 3 months | M113: Bought | N113: BLOCK G, PLOT 5 | O113: Deed Collected by client's rep | P113: Ms Oji Blessing | Q113: BAAY PROJECTS CLIENTS > GREEN CITY PHASE 3, OMU EPE | R113: 13 | S113: 16/08/2024
A114: SB0110 | B114: BP-C0115 | C114: Mrs King Lavonda (LAVONDA RENA KING FAMILY & TOCHUWKU CHRISTIAN EJIOFOR | D114: Land | E114: Green City Phase 3 (Omu-Epe) | F114: 500SQM | G114: 45521 | H114: =IF(G114="","",YEAR(G114)) | I114: 3800000 | J114: 3800000 | K114: =IF(OR(I114="",J114=""),"",I114-J114) | L114: 3 months | M114: Bought | N114: BLOCK F, PLOT 3 | O114: Deed Collected by client's rep | P114: Mrs Abimbola | Q114: BAAY PROJECTS CLIENTS > GREEN CITY PHASE 3, OMU EPE | R114: 12 | S114: 17/08/2024
A115: SB0111 | B115: BP-C0116 | C115: Miss Okorie Rachael Mmesomachi | D115: Land | E115: Green City Phase 3 (Omu-Epe) | F115: 500SQM | G115: 45522 | H115: =IF(G115="","",YEAR(G115)) | I115: 3800000 | J115: 3800000 | K115: =IF(OR(I115="",J115=""),"",I115-J115) | L115: 3 months | M115: Bought | N115: BLOCK F, PLOT 5 | O115: Deed collected by client's rep | P115: Ms Oji Blessing | Q115: BAAY PROJECTS CLIENTS > GREEN CITY PHASE 3, OMU EPE | R115: 14 | S115: 18/08/2024
A116: SB0112 | B116: BP-C0060 | C116: Ms Mitchell Jennifer | D116: Land | E116: Heritage Garden | F116: 250sqm | G116: 45526 | H116: =IF(G116="","",YEAR(G116)) | I116: 608060 | J116: 608060 | K116: =IF(OR(I116="",J116=""),"",I116-J116) | L116: 3 months | M116: Bought | N116: BLOCK C, PLOT 9 | O116: Contract of Sales Signed | P116: Ms Celina | Q116: BAAY PROJECTS CLIENTS > HERITAGE GARDEN | R116: 3 | S116: 22/08/2024
A117: SB0113 | B117: BP-C0118 | C117: Pastor Ikechukwu Kingsley & Deaconess Ikechukwu Rose Uju | D117: Land | E117: Green City Phase 3 (Omu-Epe) | F117: 500SQM | G117: 45527 | H117: =IF(G117="","",YEAR(G117)) | I117: 3800000 | J117: 3800000 | K117: =IF(OR(I117="",J117=""),"",I117-J117) | L117: 3 months | M117: Bought | N117: BLOCK E, PLOT 2 | O117: Deed collected by client | P117: Ms Adenike | Q117: BAAY PROJECTS CLIENTS > GREEN CITY PHASE 3, OMU EPE | R117: 16 | S117: 23/08/2024
A118: SB0114 | B118: BP-C0119 | C118: Mr Adedapo Adekunle Solomon | D118: Land | E118: Green City Phase 3 (Omu-Epe) | F118: 500SQM | G118: 45532 | H118: =IF(G118="","",YEAR(G118)) | I118: 5000000 | J118: 5000000 | K118: =IF(OR(I118="",J118=""),"",I118-J118) | L118: 3 months | M118: Bought | N118: BLOCK E, PLOT 3 | O118: Deed dispatched to client, Signed out by rep | P118: Ms Taiwo | Q118: BAAY PROJECTS CLIENTS > GREEN CITY PHASE 3, OMU EPE | R118: 17 | S118: 28/08/2024
A119: SB0115 | B119: BP-C0121 | C119: Mr Nweze Valentine Oluebube | D119: Land | E119: Green City Phase 3 (Omu-Epe) | F119: 500SQM | G119: 45544 | H119: =IF(G119="","",YEAR(G119)) | I119: 5000000 | J119: 5000000 | K119: =IF(OR(I119="",J119=""),"",I119-J119) | L119: 3 months | M119: Bought | N119: BLOCK F, PLOT 4 | O119: Deed collected by client | P119: Ms Bolanle | Q119: BAAY PROJECTS CLIENTS > GREEN CITY PHASE 3, OMU EPE | R119: 19 | S119: 2024-09-09
A120: SB0116 | B120: BP-C0122 | C120: Mr Olusegun Dare Micheal | D120: Land | E120: Green City Phase 3 (Omu-Epe) | F120: 500SQM | G120: 45544 | H120: =IF(G120="","",YEAR(G120)) | I120: 4500000 | J120: 4500000 | K120: =IF(OR(I120="",J120=""),"",I120-J120) | L120: 3 months | M120: Bought | N120: BLOCK F, PLOT 6 | O120: Deed collected by client's rep | P120: Ms Bolanle | Q120: BAAY PROJECTS CLIENTS > GREEN CITY PHASE 3, OMU EPE | R120: 18 | S120: 2024-09-09
A121: SB0117 | B121: BP-C0123 | C121: Mr Olaogun Samuel Oriyomi | D121: Land | E121: Green City Phase 3 (Omu-Epe) | F121: 250SQM | G121: 45548 | H121: =IF(G121="","",YEAR(G121)) | I121: 2600000 | J121: 2600000 | K121: =IF(OR(I121="",J121=""),"",I121-J121) | L121: 3 months | M121: Bought | N121: BLOCK D, PLOT 7 | O121: Deed collected by client | P121: Mr Rapheal | Q121: BAAY PROJECTS CLIENTS > GREEN CITY PHASE 3, OMU EPE | R121: 20 | S121: 13/09/2024
A122: SB0118 | B122: BP-C0125 | C122: Mrs Adelaja-Idowu Mosebolatan Tomilayo & Mr Tse Mike Terzungwe | D122: Land | E122: Green City Phase 2 (Ketu-Epe) | F122: 1000Sqm | G122: 45552 | H122: =IF(G122="","",YEAR(G122)) | I122: 12800000 | J122: 12800000 | K122: =IF(OR(I122="",J122=""),"",I122-J122) | L122: 3 months | M122: Bought | N122: BLOCK A, PLOT 15 & 16 | O122: Collected by client | P122: Mr Ogidan Abiodun | Q122: BAAY PROJECTS CLIENTS > GREEN CITY KETU EPE 2 | R122: 48 | S122: 17/09/2024
... A136: SB0132 | B136: BP-C0140 | C136: Mr Balogun Akeem Tokunbo | D136: Land | E136: Green City Phase 3 (Omu-Epe) | F136: 1,200SQM (COMMERCIAL PLOT) | G136: 45588 | H136: =IF(G136="","",YEAR(G136)) | I136: 20000000 | J136: 20000000 | K136: =IF(OR(I136="",J136=""),"",I136-J136) | L136: 6 Months | M136: Bought | N136: BLOCK B, PLOT 1 & 2 | O136: Deed collected by client | P136: Client Relations/Marketing | Q136: BAAY PROJECTS CLIENTS > GREEN CITY PHASE 3, OMU EPE | R136: 27 | S136: 23/10/2024
A137: SB0133 | B137: BP-C0140 | C137: Mr Balogun Akeem Tokunbo | D137: Housing | E137: Pacific Apartment | F137: 2 bedroom with a BQ Fully Finished | units: 1.0 | G137: 45590 | H137: =IF(G137="","",YEAR(G137)) | I137: 65000000 | J137: 65000000 | K137: =IF(OR(I137="",J137=""),"",I137-J137) | L137: 6 months | M137: Bought | P137: Clients Relations/Accounts | Q137: BAAY PROJECTS CLIENTS > PACIFIC APARTMENT | R137: 2 | S137: 25/10/2024
A138: SB0134 | B138: BP-C0141 | C138: Mr Aremu Kayode Sarafa | D138: Land | E138: Green City Phase 2 (Ketu-Epe) | F138: 250sqm | G138: 45595 | H138: =IF(G138="","",YEAR(G138)) | I138: 3200000 | J138: 3200000 | K138: =IF(OR(I138="",J138=""),"",I138-J138) | L138: 3 months | M138: Bought | N138: BLOCK E, PLOT 6 | O138: Contract of sales signed | P138: Mr Ogidan Abiodun | Q138: BAAY PROJECTS CLIENTS > GREEN CITY KETU EPE 2 | R138: 51 | S138: 30/10/2024
A139: SB0135 | B139: BP-C0143 | C139: Mrs Oyindamola Duntoye Adekunle | D139: Housing | E139: Pacific Apartment | F139: 2 bedroom with a BQ Fully Finished | units: 1.0 | G139: 45595 | H139: =IF(G139="","",YEAR(G139)) | I139: 67000000 | J139: 67000000 | K139: =IF(OR(I139="",J139=""),"",I139-J139) | L139: 12 months | M139: Bought | P139: Clients Relation/Accounts | Q139: BAAY PROJECTS CLIENTS > PACIFIC APARTMENT | R139: 3 | S139: 30/10/2024
A140: SB0136 | B140: BP-C0145 | C140: Barr Keshinro Phebe Oluwatunmise | D140: Housing | E140: Pacific Apartment | F140: 2 bedroom with a BQ | units: 1.0 | G140: 45605 | H140: =IF(G140="","",YEAR(G140)) | I140: 65000000 | J140: 10000000 | K140: =IF(OR(I140="",J140=""),"",I140-J140) | L140: Outright | M140: Paying | P140: Mr Charles | Q140: BAAY PROJECTS CLIENTS > PACIFIC APARTMENT | R140: 4 | S140: 2024-09-11
A141: SB0137 | B141: BP-C0009 | C141: Miss Oji Blessing Mary | D141: Land | E141: Green City Phase 3 (Omu-Epe) | F141: 500Sqm | G141: 45607 | H141: =IF(G141="","",YEAR(G141)) | I141: 4000000 | J141: 4000000 | K141: =IF(OR(I141="",J141=""),"",I141-J141) | L141: 3 months | M141: Bought | N141: BLOCK G, PLOT 6 | O141: Contract of Sales signed. | P141: Ms Oji Blessing | Q141: BAAY PROJECTS CLIENTS > GREEN CITY PHASE 3, OMU EPE | R141: 28 | S141: 2024-11-11
A142: SB0138 | B142: BP-C0146 | C142: Mrs Tijani Tawa Motunrayo | D142: Land | E142: Green City Phase 3 (Omu-Epe) | F142: 250SQM | G142: 45610 | H142: =IF(G142="","",YEAR(G142)) | I142: 2600000 | J142: 2600000 | K142: =IF(OR(I142="",J142=""),"",I142-J142) | L142: 3 months | M142: Bought | N142: BLOCK H, PLOT 4 | O142: Deed collected by client | P142: Ms Mayowa Awonorin | Q142: BAAY PROJECTS CLIENTS > GREEN CITY PHASE 3, OMU EPE | R142: 30 | S142: 14/11/2024
A143: SB0139 | B143: BP-C0148 | C143: Mr Akinsete Michael Abayomi | D143: Land | E143: Green City Phase 2 (Ketu-Epe) | F143: 500sqm | G143: 45625 | H143: =IF(G143="","",YEAR(G143)) | I143: 10700000 | J143: 2703400 | K143: =IF(OR(I143="",J143=""),"",I143-J143) | L143: 12 Months | M143: Paying | O143: Not Yet Processed | P143: MD | Q143: BAAY PROJECTS CLIENTS > GREEN CITY KETU EPE 2 | R143: 52 | S143: 29/11/2024
A144: SB0140 | B144: BP-C0149 | C144: Mr Uneze Grant Chetanna | D144: Land | E144: Green City Phase 3 (Omu-Epe) | F144: 500SQM | G144: 45625 | H144: =IF(G144="","",YEAR(G144)) | I144: 5000000 | J144: 5000000 | K144: =IF(OR(I144="",J144=""),"",I144-J144) | L144: 3 months | M144: Bought | N144: BLOCK G, PLOT 8 | O144: Deed collected by client | P144: Ms Samuella | Q144: BAAY PROJECTS CLIENTS > GREEN CITY PHASE 3, OMU EPE | R144: 31 | S144: 29/11/2024
A145: SB0141 | B145: BP-C0150 | C145: Mr Ajiboso Damilare Moses & Mrs Ajiboso Gbemisola Rachael | D145: Land | E145: Green City Phase 3 (Omu-Epe) | F145: 500SQM | G145: 45626 | H145: =IF(G145="","",YEAR(G145)) | I145: 5000000 | J145: 5000000 | K145: =IF(OR(I145="",J145=""),"",I145-J145) | L145: 3 months | M145: Bought | N145: BLOCK G, PLOT 9 | O145: Deed collected by client | P145: Ms Adenike | Q145: BAAY PROJECTS CLIENTS > GREEN CITY PHASE 3, OMU EPE | R145: 32 | S145: 30/11/2024
A146: SB0142 | B146: BP-C0151 | C146: Mrs Shotonwa Olamide Abosede | D146: Land | E146: Green City Phase 3 (Omu-Epe) | F146: 500SQM | G146: 45626 | H146: =IF(G146="","",YEAR(G146)) | I146: 5000000 | J146: 5000000 | K146: =IF(OR(I146="",J146=""),"",I146-J146) | L146: 3 months | M146: Bought | N146: BLOCK G, PLOT 10 | O146: Deed collected by client | P146: Ms Adenike | Q146: BAAY PROJECTS CLIENTS > GREEN CITY PHASE 3, OMU EPE | R146: 33 | S146: 30/11/2024
A147: SB0143 | B147: BP-C0152 | C147: Mr Iyama Godsauthority Chinedu | D147: Land | E147: Green City Phase 3 Extension (Omu-Epe) | F147: 250 SQM | G147: 45630 | H147: =IF(G147="","",YEAR(G147)) | I147: 2000000 | J147: 350000 | K147: =IF(OR(I147="",J147=""),"",I147-J147) | L147: 3 months | M147: REFUND | O147: REFUND | P147: Mr Daniel | Q147: BAAY PROJECTS CLIENTS > GREEN CITY PHASE 3 EXTENSION, O | R147: 2 | S147: 2024-04-12
A148: SB0144 | B148: BP-C0153 | C148: Miss Ademakinwa Abosede Wuraola | D148: Land | E148: Green City Ibadan (Akinyele-Moniya) | F148: 500SQM | G148: 45641 | H148: =IF(G148="","",YEAR(G148)) | I148: 2900000 | J148: 2100000 | K148: =IF(OR(I148="",J148=""),"",I148-J148) | L148: 3 months | M148: Bought | N148: BLOCK E, PLOT 1 | O148: Contract of Sale signed | P148: Miss Abosede (Team Taiwo) | Q148: BAAY PROJECTS CLIENTS > GREEN CITY IBADAN, AKINYELE-MON | R148: 4 | S148: 15/12/2024
A149: SB0145 | B149: BP-C0154 | C149: Mr Adepoju Adewale Emmanuel | D149: Land | E149: Green City Ibadan (Akinyele-Moniya) | F149: 1000SQM | G149: 45641 | H149: =IF(G149="","",YEAR(G149)) | I149: 5800000 | J149: 4200000 | K149: =IF(OR(I149="",J149=""),"",I149-J149) | L149: 3 months | M149: Bought | N149: BLOCK E, PLOT 2 & 3 | O149: Contract of Sale signed | P149: Ms Abosede (Team Taiwo | Q149: BAAY PROJECTS CLIENTS > GREEN CITY IBADAN, AKINYELE-MON | R149: 6 | S149: 15/12/2024
A150: SB0146 | B150: BP-C0155 | C150: Mr Adeyanju Adebayo Samson | D150: Land | E150: Green City Ibadan (Akinyele-Moniya) | F150: 500SQM | G150: 45641 | H150: =IF(G150="","",YEAR(G150)) | I150: 2900000 | J150: 2100000 | K150: =IF(OR(I150="",J150=""),"",I150-J150) | L150: 3 months | M150: Bought | N150: BLOCK E, PLOT 4 | O150: Contract of Sale signed | P150: Miss Abosede (Team Taiwo) | Q150: BAAY PROJECTS CLIENTS > GREEN CITY IBADAN, AKINYELE-MON | R150: 5 | S150: 15/12/2024
A151: SB0147 | B151: BP-C0157 | C151: Mrs Adepoju Adebola Adeniran | D151: Land | E151: Green City Ibadan (Akinyele-Moniya) | F151: 1000SQM | G151: 45641 | H151: =IF(G151="","",YEAR(G151)) | I151: 5800000 | J151: 4200000 | K151: =IF(OR(I151="",J151=""),"",I151-J151) | L151: 3 months | M151: Bought | N151: BLOCK E, PLOT 5 & 6 | O151: Contract of Sale signed | P151: Ms Abosede (Team Taiwo | Q151: BAAY PROJECTS CLIENTS > GREEN CITY IBADAN, AKINYELE-MON | R151: 7 | S151: 15/12/2024
A152: SB0148 | B152: BP-C0017 | C152: Mr John Taiwo Adeleye | D152: Land | E152: Green City Ibadan (Akinyele-Moniya) | F152: 250SQM | G152: 45645 | H152: =IF(G152="","",YEAR(G152)) | I152: 1500000 | J152: 1500000 | K152: =IF(OR(I152="",J152=""),"",I152-J152) | L152: 3 months | M152: Bought | N152: BLOCK F, PLOT 1 | O152: Contract of Sale signed | P152: Ms Jochebed (Team Moffat) | Q152: BAAY PROJECTS CLIENTS > GREEN CITY IBADAN, AKINYELE-MON | R152: 8 | S152: 19/12/2024
A153: SB0149 | B153: BP-C0158 | C153: Mr Shino Precious Vincent | D153: Land | E153: Green City Phase 3 Extension (Omu-Epe) | F153: 250 SQM | G153: 45646 | H153: =IF(G153="","",YEAR(G153)) | I153: 2000000 | J153: 1500000 | K153: =IF(OR(I153="",J153=""),"",I153-J153) | L153: 3 months | M153: Migrated | N153: BLOCK D, PLOT 2 | O153: Not Yet Processed | P153: Mr Daniel (Team Pelumi) | Q153: BAAY PROJECTS CLIENTS > GREEN CITY PHASE 3 EXTENSION, O | R153: 3 | S153: 20/12/2024
A154: SB0150 | B154: BP-C0159 | C154: Miss Etefe Ava Ogheneyorhe | D154: Land | E154: Heritage Garden | F154: 500sqm | G154: 45650 | H154: =IF(G154="","",YEAR(G154)) | I154: 1100000 | J154: 1000000 | K154: =IF(OR(I154="",J154=""),"",I154-J154) | L154: 3 months | M154: Paying | N154: BLOCK D, PLOT 2 | O154: Not yet Prepared | P154: Ms Elizabeth | Q154: BAAY PROJECTS CLIENTS > HERITAGE GARDEN | R154: 7 | S154: 24/12/2024
A155: SB0151 | B155: BP-C0160 | C155: Mr Okenla Olugboyega Gabriel | D155: Housing | E155: Pacific Apartment | F155: 2 bedroom with a BQ | units: 1.0 | G155: 45653 | H155: =IF(G155="","",YEAR(G155)) | I155: 75000000 | J155: 30000000 | K155: =IF(OR(I155="",J155=""),"",I155-J155) | L155: 15 months | M155: Paying | P155: Ms Moffat | Q155: BAAY PROJECTS CLIENTS > PACIFIC APARTMENT | R155: 5 | S155: 27/12/2024
A156: SB0152 | B156: BP-C0162 | C156: Miss Uthman Alimat Modupe | D156: Land | E156: Green City Phase 3 Extension (Omu-Epe) | F156: 250 SQM | G156: 45657 | H156: =IF(G156="","",YEAR(G156)) | I156: 2000000 | J156: 500000 | K156: =IF(OR(I156="",J156=""),"",I156-J156) | L156: 3 months | M156: REFUND | O156: Not Yet Processed | P156: Ms Tobi | Q156: BAAY PROJECTS CLIENTS > GREEN CITY PHASE 3 EXTENSION, O | R156: 4 | S156: 31/12/2024
A157: SB0153 | B157: BP-C0163 | C157: Mr Ajagbe James Olatayo | D157: Land | E157: Heritage Garden | F157: 250sqm | G157: 45657 | H157: =IF(G157="","",YEAR(G157)) | I157: 550000 | J157: 550000 | K157: =IF(OR(I157="",J157=""),"",I157-J157) | L157: 3 months | M157: Bought | N157: BLOCK C, PLOT 12 | O157: Contract of Sales Signed | P157: Mr Baqi | Q157: BAAY PROJECTS CLIENTS > HERITAGE GARDEN | R157: 8 | S157: 31/12/2024
A158: SB0154 | B158: BP-C0164 | C158: Miss Arogundade Motunrayo Azeezat | D158: Land | E158: Heritage Garden | F158: 500sqm | G158: 45659 | H158: =IF(G158="","",YEAR(G158)) | I158: 1000000 | J158: 1000000 | K158: =IF(OR(I158="",J158=""),"",I158-J158) | L158: 3 months | M158: Bought | N158: BLOCK D, PLOT 4 | O158: Contract of Sales Signed | P158: Mr Ibukun (Team Taiwo) | Q158: BAAY PROJECTS CLIENTS > HERITAGE GARDEN | R158: 9 | S158: 2025-02-01
A159: SB0155 | B159: BP-C0165 | C159: Mr Ebosele Sunday Osabhue | D159: Housing | E159: Gorge View Court (GVC Gbagada) | F159: 4Bedroom Terrace Triplex | units: 1 unit | G159: 45677 | H159: =IF(G159="","",YEAR(G159)) | I159: 250000000 | J159: 250000000 | K159: =IF(OR(I159="",J159=""),"",I159-J159) | L159: 3 months | M159: Bought | P159: Ms Adebomi | Q159: BAAY PROJECTS CLIENTS > GORGE VIEW COURT | R159: 2 | S159: 20/01/2025
...

Sheet Customer_Master
A1: Customer master: everyone who subscribed to or paid for land/housing, 2022 to 2025
A2: One row per customer. Receipts pull from Sales_Ledger; contract values pull from Subscriptions. Contact details are for auditor confirmations.
A4: Customer ID | B4: Customer name | C4: Phone | D4: Email | E4: Product line(s) | F4: Project(s) | G4: First subscription date (register) | H4: First receipt in ledger | I4: Contract value per register (₦) | J4: Paid to date per register (₦) | K4: Receipts 2023 (₦) | L4: Receipts 2024 (₦) | M4: Receipts 2025 (₦) | N4: Total receipts 2023-2025 (₦) | O4: Identified from | P4: Register status | Q4: Realtor / contact | R4: Review flag
A5: BP-C0001 | B5: Mr Meshack Osagie | C5: 19179388590 | E5: Housing | F5: Pacific Court | G5: 44593 | H5: =IF(COUNTIF(Sales_Ledger!$H$5:$H$863,A5)=0,"",_xlfn.MINIFS(Sales_Ledger!$B$5:$B$863,Sales_Ledger!$H$5:$H$863,A5)) | I5: =SUMIFS(Subscriptions!$I$5:$I$218,Subscriptions!$B$5:$B$218,A5) | J5: =SUMIFS(Subscriptions!$J$5:$J$218,Subscriptions!$B$5:$B$218,A5) | K5: =SUMIFS(Sales_Ledger!$J$5:$J$863,Sales_Ledger!$H$5:$H$863,$A5,Sales_Ledger!$D$5:$D$863,2023) | L5: =SUMIFS(Sales_Ledger!$J$5:$J$863,Sales_Ledger!$H$5:$H$863,$A5,Sales_Ledger!$D$5:$D$863,2024) | M5: =SUMIFS(Sales_Ledger!$J$5:$J$863,Sales_Ledger!$H$5:$H$863,$A5,Sales_Ledger!$D$5:$D$863,2025) | N5: =SUM(K5:M5) | O5: Client register | P5: PAID | Q5: AKIN PHILIP | R5: =IF(AND(I5>0,N5>I5*1.02),"Receipts exceed register contract value: check for duplicate entries, extra plots or ancillary fees",IF(AND(I5=0,N5>0),"Not in client register: contract value unknown",""))
A6: BP-C0002 | B6: Temidayo Oniosun | C6: 13024078280 | D6: SENT | E6: Housing | F6: Pacific Court | G6: 44652 | H6: =IF(COUNTIF(Sales_Ledger!$H$5:$H$863,A6)=0,"",_xlfn.MINIFS(Sales_Ledger!$B$5:$B$863,Sales_Ledger!$H$5:$H$863,A6)) | I6: =SUMIFS(Subscriptions!$I$5:$I$218,Subscriptions!$B$5:$B$218,A6) | J6: =SUMIFS(Subscriptions!$J$5:$J$218,Subscriptions!$B$5:$B$218,A6) | K6: =SUMIFS(Sales_Ledger!$J$5:$J$863,Sales_Ledger!$H$5:$H$863,$A6,Sales_Ledger!$D$5:$D$863,2023) | L6: =SUMIFS(Sales_Ledger!$J$5:$J$863,Sales_Ledger!$H$5:$H$863,$A6,Sales_Ledger!$D$5:$D$863,2024) | M6: =SUMIFS(Sales_Ledger!$J$5:$J$863,Sales_Ledger!$H$5:$H$863,$A6,Sales_Ledger!$D$5:$D$863,2025) | N6: =SUM(K6:M6) | O6: Client register | P6: PAID | Q6: MD | R6: =IF(AND(I6>0,N6>I6*1.02),"Receipts exceed register contract value: check for duplicate entries, extra plots or ancillary fees",IF(AND(I6=0,N6>0),"Not in client register: contract value unknown",""))
A7: BP-C0003 | B7: Mrs Agbaje | C7: 353(87)9217662 | E7: Housing | F7: Pacific Court | G7: 44713 | H7: =IF(COUNTIF(Sales_Ledger!$H$5:$H$863,A7)=0,"",_xlfn.MINIFS(Sales_Ledger!$B$5:$B$863,Sales_Ledger!$H$5:$H$863,A7)) | I7: =SUMIFS(Subscriptions!$I$5:$I$218,Subscriptions!$B$5:$B$218,A7) | J7: =SUMIFS(Subscriptions!$J$5:$J$218,Subscriptions!$B$5:$B$218,A7) | K7: =SUMIFS(Sales_Ledger!$J$5:$J$863,Sales_Ledger!$H$5:$H$863,$A7,Sales_Ledger!$D$5:$D$863,2023) | L7: =SUMIFS(Sales_Ledger!$J$5:$J$863,Sales_Ledger!$H$5:$H$863,$A7,Sales_Ledger!$D$5:$D$863,2024) | M7: =SUMIFS(Sales_Ledger!$J$5:$J$863,Sales_Ledger!$H$5:$H$863,$A7,Sales_Ledger!$D$5:$D$863,2025) | N7: =SUM(K7:M7) | O7: Client register | P7: PAID | Q7: MR BIOLA AKOSILE | R7: =IF(AND(I7>0,N7>I7*1.02),"Receipts exceed register contract value: check for duplicate entries, extra plots or ancillary fees",IF(AND(I7=0,N7>0),"Not in client register: contract value unknown",""))
A8: BP-C0004 | B8: Mrs Kate | E8: Housing | F8: Pacific Court | G8: 44774 | H8: =IF(COUNTIF(Sales_Ledger!$H$5:$H$863,A8)=0,"",_xlfn.MINIFS(Sales_Ledger!$B$5:$B$863,Sales_Ledger!$H$5:$H$863,A8)) | I8: =SUMIFS(Subscriptions!$I$5:$I$218,Subscriptions!$B$5:$B$218,A8) | J8: =SUMIFS(Subscriptions!$J$5:$J$218,Subscriptions!$B$5:$B$218,A8) | K8: =SUMIFS(Sales_Ledger!$J$5:$J$863,Sales_Ledger!$H$5:$H$863,$A8,Sales_Ledger!$D$5:$D$863,2023) | L8: =SUMIFS(Sales_Ledger!$J$5:$J$863,Sales_Ledger!$H$5:$H$863,$A8,Sales_Ledger!$D$5:$D$863,2024) | M8: =SUMIFS(Sales_Ledger!$J$5:$J$863,Sales_Ledger!$H$5:$H$863,$A8,Sales_Ledger!$D$5:$D$863,2025) | N8: =SUM(K8:M8) | O8: Client register | P8: REFUND | Q8: MD | R8: =IF(AND(I8>0,N8>I8*1.02),"Receipts exceed register contract value: check for duplicate entries, extra plots or ancillary fees",IF(AND(I8=0,N8>0),"Not in client register: contract value unknown",""))
A9: BP-C0005 | B9: Mrs Mo | D9: SENT | E9: Housing | F9: Pacific Court | G9: 44896 | H9: =IF(COUNTIF(Sales_Ledger!$H$5:$H$863,A9)=0,"",_xlfn.MINIFS(Sales_Ledger!$B$5:$B$863,Sales_Ledger!$H$5:$H$863,A9)) | I9: =SUMIFS(Subscriptions!$I$5:$I$218,Subscriptions!$B$5:$B$218,A9) | J9: =SUMIFS(Subscriptions!$J$5:$J$218,Subscriptions!$B$5:$B$218,A9) | K9: =SUMIFS(Sales_Ledger!$J$5:$J$863,Sales_Ledger!$H$5:$H$863,$A9,Sales_Ledger!$D$5:$D$863,2023) | L9: =SUMIFS(Sales_Ledger!$J$5:$J$863,Sales_Ledger!$H$5:$H$863,$A9,Sales_Ledger!$D$5:$D$863,2024) | M9: =SUMIFS(Sales_Ledger!$J$5:$J$863,Sales_Ledger!$H$5:$H$863,$A9,Sales_Ledger!$D$5:$D$863,2025) | N9: =SUM(K9:M9) | O9: Client register | P9: PAID | Q9: MS YETUNDE ABISOYE | R9: =IF(AND(I9>0,N9>I9*1.02),"Receipts exceed register contract value: check for duplicate entries, extra plots or ancillary fees",IF(AND(I9=0,N9>0),"Not in client register: contract value unknown",""))
A10: BP-C0006 | B10: Olasupo Oladimeji | C10: 8086769111 | D10: SENT | E10: Land | F10: Green City Phase 1 (Lantaba, Ketu-Epe); Land (estate not stated in source) | G10: 45288 | H10: =IF(COUNTIF(Sales_Ledger!$H$5:$H$863,A10)=0,"",_xlfn.MINIFS(Sales_Ledger!$B$5:$B$863,Sales_Ledger!$H$5:$H$863,A10)) | I10: =SUMIFS(Subscriptions!$I$5:$I$218,Subscriptions!$B$5:$B$218,A10) | J10: =SUMIFS(Subscriptions!$J$5:$J$218,Subscriptions!$B$5:$B$218,A10) | K10: =SUMIFS(Sales_Ledger!$J$5:$J$863,Sales_Ledger!$H$5:$H$863,$A10,Sales_Ledger!$D$5:$D$863,2023) | L10: =SUMIFS(Sales_Ledger!$J$5:$J$863,Sales_Ledger!$H$5:$H$863,$A10,Sales_Ledger!$D$5:$D$863,2024) | M10: =SUMIFS(Sales_Ledger!$J$5:$J$863,Sales_Ledger!$H$5:$H$863,$A10,Sales_Ledger!$D$5:$D$863,2025) | N10: =SUM(K10:M10) | O10: Client register + Transaction records | P10: Bought | Q10: Ms Abimbola | R10: =IF(AND(I10>0,N10>I10*1.02),"Receipts exceed register contract value: check for duplicate entries, extra plots or ancillary fees",IF(AND(I10=0,N10>0),"Not in client register: contract value unknown",""))
A11: BP-C0007 | B11: Mrs Ero | D11: SENT | E11: Housing | F11: Pacific Court | G11: 44958 | H11: =IF(COUNTIF(Sales_Ledger!$H$5:$H$863,A11)=0,"",_xlfn.MINIFS(Sales_Ledger!$B$5:$B$863,Sales_Ledger!$H$5:$H$863,A11)) | I11: =SUMIFS(Subscriptions!$I$5:$I$218,Subscriptions!$B$5:$B$218,A11) | J11: =SUMIFS(Subscriptions!$J$5:$J$218,Subscriptions!$B$5:$B$218,A11) | K11: =SUMIFS(Sales_Ledger!$J$5:$J$863,Sales_Ledger!$H$5:$H$863,$A11,Sales_Ledger!$D$5:$D$863,2023) | L11: =SUMIFS(Sales_Ledger!$J$5:$J$863,Sales_Ledger!$H$5:$H$863,$A11,Sales_Ledger!$D$5:$D$863,2024) | M11: =SUMIFS(Sales_Ledger!$J$5:$J$863,Sales_Ledger!$H$5:$H$863,$A11,Sales_Ledger!$D$5:$D$863,2025) | N11: =SUM(K11:M11) | O11: Client register | P11: PAID | Q11: PASTOR GABRIEL | R11: =IF(AND(I11>0,N11>I11*1.02),"Receipts exceed register contract value: check for duplicate entries, extra plots or ancillary fees",IF(AND(I11=0,N11>0),"Not in client register: contract value unknown",""))
A12: BP-C0008 | B12: Mr Rasaq Roqeeb | C12: 8102767531 | D12: SENT | E12: Land | F12: Green City Phase 1 (Ketu-Epe); Green City Phase 1 (Lantaba, Ketu-Epe); Green City Phase 2 (Idobi, Ketu-Epe); Green City Phase 2 (Ketu-Epe) | G12: 44967 | H12: =IF(COUNTIF(Sales_Ledger!$H$5:$H$863,A12)=0,"",_xlfn.MINIFS(Sales_Ledger!$B$5:$B$863,Sales_Ledger!$H$5:$H$863,A12)) | I12: =SUMIFS(Subscriptions!$I$5:$I$218,Subscriptions!$B$5:$B$218,A12) | J12: =SUMIFS(Subscriptions!$J$5:$J$218,Subscriptions!$B$5:$B$218,A12) | K12: =SUMIFS(Sales_Ledger!$J$5:$J$863,Sales_Ledger!$H$5:$H$863,$A12,Sales_Ledger!$D$5:$D$863,2023) | L12: =SUMIFS(Sales_Ledger!$J$5:$J$863,Sales_Ledger!$H$5:$H$863,$A12,Sales_Ledger!$D$5:$D$863,2024) | M12: =SUMIFS(Sales_Ledger!$J$5:$J$863,Sales_Ledger!$H$5:$H$863,$A12,Sales_Ledger!$D$5:$D$863,2025) | N12: =SUM(K12:M12) | O12: Client register + Transaction records | P12: Bought | Q12: MD | R12: =IF(AND(I12>0,N12>I12*1.02),"Receipts exceed register contract value: check for duplicate entries, extra plots or ancillary fees",IF(AND(I12=0,N12>0),"Not in client register: contract value unknown",""))
A13: BP-C0009 | B13: Miss Oji Blessing Mary | C13: 971589650958 | D13: ojiblexin@gmail.com | E13: Land | F13: Green City Phase 2 (Ketu-Epe); Green City Phase 3 (Omu-Epe); Land (estate not stated in source); Land: ancillary charges | G13: 45334 | H13: =IF(COUNTIF(Sales_Ledger!$H$5:$H$863,A13)=0,"",_xlfn.MINIFS(Sales_Ledger!$B$5:$B$863,Sales_Ledger!$H$5:$H$863,A13)) | I13: =SUMIFS(Subscriptions!$I$5:$I$218,Subscriptions!$B$5:$B$218,A13) | J13: =SUMIFS(Subscriptions!$J$5:$J$218,Subscriptions!$B$5:$B$218,A13) | K13: =SUMIFS(Sales_Ledger!$J$5:$J$863,Sales_Ledger!$H$5:$H$863,$A13,Sales_Ledger!$D$5:$D$863,2023) | L13: =SUMIFS(Sales_Ledger!$J$5:$J$863,Sales_Ledger!$H$5:$H$863,$A13,Sales_Ledger!$D$5:$D$863,2024) | M13: =SUMIFS(Sales_Ledger!$J$5:$J$863,Sales_Ledger!$H$5:$H$863,$A13,Sales_Ledger!$D$5:$D$863,2025) | N13: =SUM(K13:M13) | O13: Client register + Transaction records | P13: Bought | Q13: Ms Bolanle, Ms Oji Blessing | R13: =IF(AND(I13>0,N13>I13*1.02),"Receipts exceed register contract value: check for duplicate entries, extra plots or ancillary fees",IF(AND(I13=0,N13>0),"Not in client register: contract value unknown",""))
A14: BP-C0010 | B14: Mrs Yohanna Paulina | C14: 9044246658 | D14: SENT | E14: Land | F14: Green City Phase 1 (Ketu-Epe); Green City Phase 1 (Lantaba, Ketu-Epe); Land (estate not stated in source) | G14: 45365 | H14: =IF(COUNTIF(Sales_Ledger!$H$5:$H$863,A14)=0,"",_xlfn.MINIFS(Sales_Ledger!$B$5:$B$863,Sales_Ledger!$H$5:$H$863,A14)) | I14: =SUMIFS(Subscriptions!$I$5:$I$218,Subscriptions!$B$5:$B$218,A14) | J14: =SUMIFS(Subscriptions!$J$5:$J$218,Subscriptions!$B$5:$B$218,A14) | K14: =SUMIFS(Sales_Ledger!$J$5:$J$863,Sales_Ledger!$H$5:$H$863,$A14,Sales_Ledger!$D$5:$D$863,2023) | L14: =SUMIFS(Sales_Ledger!$J$5:$J$863,Sales_Ledger!$H$5:$H$863,$A14,Sales_Ledger!$D$5:$D$863,2024) | M14: =SUMIFS(Sales_Ledger!$J$5:$J$863,Sales_Ledger!$H$5:$H$863,$A14,Sales_Ledger!$D$5:$D$863,2025) | N14: =SUM(K14:M14) | O14: Client register + Transaction records | P14: Bought | Q14: Mr Charles | R14: =IF(AND(I14>0,N14>I14*1.02),"Receipts exceed register contract value: check for duplicate entries, extra plots or ancillary fees",IF(AND(I14=0,N14>0),"Not in client register: contract value unknown",""))
A15: BP-C0011 | B15: OLAIYA SUNDAY TEMITOPE | C15: 7062737144 | D15: SENT | E15: Land | F15: Green City Phase 1 (Lantaba, Ketu-Epe); Land: ancillary charges | G15: 45061 | H15: =IF(COUNTIF(Sales_Ledger!$H$5:$H$863,A15)=0,"",_xlfn.MINIFS(Sales_Ledger!$B$5:$B$863,Sales_Ledger!$H$5:$H$863,A15)) | I15: =SUMIFS(Subscriptions!$I$5:$I$218,Subscriptions!$B$5:$B$218,A15) | J15: =SUMIFS(Subscriptions!$J$5:$J$218,Subscriptions!$B$5:$B$218,A15) | K15: =SUMIFS(Sales_Ledger!$J$5:$J$863,Sales_Ledger!$H$5:$H$863,$A15,Sales_Ledger!$D$5:$D$863,2023) | L15: =SUMIFS(Sales_Ledger!$J$5:$J$863,Sales_Ledger!$H$5:$H$863,$A15,Sales_Ledger!$D$5:$D$863,2024) | M15: =SUMIFS(Sales_Ledger!$J$5:$J$863,Sales_Ledger!$H$5:$H$863,$A15,Sales_Ledger!$D$5:$D$863,2025) | N15: =SUM(K15:M15) | O15: Client register + Transaction records | P15: Bought | Q15: Ms Abimbola | R15: =IF(AND(I15>0,N15>I15*1.02),"Receipts exceed register contract value: check for duplicate entries, extra plots or ancillary fees",IF(AND(I15=0,N15>0),"Not in client register: contract value unknown",""))
A16: BP-C0012 | B16: Mr Apiafi Imiebam | C16: 8166128579 | D16: runcheck07@gmail.com | E16: Land | F16: Green City Phase 2 (Ketu-Epe); Land (estate not stated in source) | G16: 45376 | H16: =IF(COUNTIF(Sales_Ledger!$H$5:$H$863,A16)=0,"",_xlfn.MINIFS(Sales_Ledger!$B$5:$B$863,Sales_Ledger!$H$5:$H$863,A16)) | I16: =SUMIFS(Subscriptions!$I$5:$I$218,Subscriptions!$B$5:$B$218,A16) | J16: =SUMIFS(Subscriptions!$J$5:$J$218,Subscriptions!$B$5:$B$218,A16) | K16: =SUMIFS(Sales_Ledger!$J$5:$J$863,Sales_Ledger!$H$5:$H$863,$A16,Sales_Ledger!$D$5:$D$863,2023) | L16: =SUMIFS(Sales_Ledger!$J$5:$J$863,Sales_Ledger!$H$5:$H$863,$A16,Sales_Ledger!$D$5:$D$863,2024) | M16: =SUMIFS(Sales_Ledger!$J$5:$J$863,Sales_Ledger!$H$5:$H$863,$A16,Sales_Ledger!$D$5:$D$863,2025) | N16: =SUM(K16:M16) | O16: Client register + Transaction records | P16: Bought | Q16: Ms Blessing | R16: =IF(AND(I16>0,N16>I16*1.02),"Receipts exceed register contract value: check for duplicate entries, extra plots or ancillary fees",IF(AND(I16=0,N16>0),"Not in client register: contract value unknown",""))
A17: BP-C0013 | B17: MOSHOOD TIJANI | C17: 7030362595 | D17: SENT | E17: Land | F17: Green City Phase 1 (Ketu-Epe); Green City Phase 1 (Lantaba, Ketu-Epe); Green City Phase 2 (Ketu-Epe) | G17: 45073 | H17: =IF(COUNTIF(Sales_Ledger!$H$5:$H$863,A17)=0,"",_xlfn.MINIFS(Sales_Ledger!$B$5:$B$863,Sales_Ledger!$H$5:$H$863,A17)) | I17: =SUMIFS(Subscriptions!$I$5:$I$218,Subscriptions!$B$5:$B$218,A17) | J17: =SUMIFS(Subscriptions!$J$5:$J$218,Subscriptions!$B$5:$B$218,A17) | K17: =SUMIFS(Sales_Ledger!$J$5:$J$863,Sales_Ledger!$H$5:$H$863,$A17,Sales_Ledger!$D$5:$D$863,2023) | L17: =SUMIFS(Sales_Ledger!$J$5:$J$863,Sales_Ledger!$H$5:$H$863,$A17,Sales_Ledger!$D$5:$D$863,2024) | M17: =SUMIFS(Sales_Ledger!$J$5:$J$863,Sales_Ledger!$H$5:$H$863,$A17,Sales_Ledger!$D$5:$D$863,2025) | N17: =SUM(K17:M17) | O17: Client register + Transaction records | P17: Bought | Q17: MD | R17: =IF(AND(I17>0,N17>I17*1.02),"Receipts exceed register contract value: check for duplicate entries, extra plots or ancillary fees",IF(AND(I17=0,N17>0),"Not in client register: contract value unknown",""))
A18: BP-C0014 | B18: PROF OLUGBENGA AKINADE/MRS ARAWOMO OMOLOLA | C18: 7459465947 | D18: SENT | E18: Land | F18: Green City Phase 1 (Lantaba, Ketu-Epe) | G18: 45083 | H18: =IF(COUNTIF(Sales_Ledger!$H$5:$H$863,A18)=0,"",_xlfn.MINIFS(Sales_Ledger!$B$5:$B$863,Sales_Ledger!$H$5:$H$863,A18)) | I18: =SUMIFS(Subscriptions!$I$5:$I$218,Subscriptions!$B$5:$B$218,A18) | J18: =SUMIFS(Subscriptions!$J$5:$J$218,Subscriptions!$B$5:$B$218,A18) | K18: =SUMIFS(Sales_Ledger!$J$5:$J$863,Sales_Ledger!$H$5:$H$863,$A18,Sales_Ledger!$D$5:$D$863,2023) | L18: =SUMIFS(Sales_Ledger!$J$5:$J$863,Sales_Ledger!$H$5:$H$863,$A18,Sales_Ledger!$D$5:$D$863,2024) | M18: =SUMIFS(Sales_Ledger!$J$5:$J$863,Sales_Ledger!$H$5:$H$863,$A18,Sales_Ledger!$D$5:$D$863,2025) | N18: =SUM(K18:M18) | O18: Client register | P18: Bought | Q18: MD | R18: =IF(AND(I18>0,N18>I18*1.02),"Receipts exceed register contract value: check for duplicate entries, extra plots or ancillary fees",IF(AND(I18=0,N18>0),"Not in client register: contract value unknown",""))
A19: BP-C0015 | B19: MR Damilare Ositade Owolabi | C19: 8061349595 | D19: SENT | E19: Land | F19: Green City Phase 1 (Lantaba, Ketu-Epe); Land (estate not stated in source); Land: ancillary charges | G19: 45092 | H19: =IF(COUNTIF(Sales_Ledger!$H$5:$H$863,A19)=0,"",_xlfn.MINIFS(Sales_Ledger!$B$5:$B$863,Sales_Ledger!$H$5:$H$863,A19)) | I19: =SUMIFS(Subscriptions!$I$5:$I$218,Subscriptions!$B$5:$B$218,A19) | J19: =SUMIFS(Subscriptions!$J$5:$J$218,Subscriptions!$B$5:$B$218,A19) | K19: =SUMIFS(Sales_Ledger!$J$5:$J$863,Sales_Ledger!$H$5:$H$863,$A19,Sales_Ledger!$D$5:$D$863,2023) | L19: =SUMIFS(Sales_Ledger!$J$5:$J$863,Sales_Ledger!$H$5:$H$863,$A19,Sales_Ledger!$D$5:$D$863,2024) | M19: =SUMIFS(Sales_Ledger!$J$5:$J$863,Sales_Ledger!$H$5:$H$863,$A19,Sales_Ledger!$D$5:$D$863,2025) | N19: =SUM(K19:M19) | O19: Client register + Transaction records | P19: Bought | Q19: IDARA | R19: =IF(AND(I19>0,N19>I19*1.02),"Receipts exceed register contract value: check for duplicate entries, extra plots or ancillary fees",IF(AND(I19=0,N19>0),"Not in client register: contract value unknown",""))
A20: BP-C0016 | B20: Mr Tobi Adesina | C20: 8149286156 | E20: Land | F20: Green City Phase 1 (Lantaba, Ketu-Epe) | G20: 45103 | H20: =IF(COUNTIF(Sales_Ledger!$H$5:$H$863,A20)=0,"",_xlfn.MINIFS(Sales_Ledger!$B$5:$B$863,Sales_Ledger!$H$5:$H$863,A20)) | I20: =SUMIFS(Subscriptions!$I$5:$I$218,Subscriptions!$B$5:$B$218,A20) | J20: =SUMIFS(Subscriptions!$J$5:$J$218,Subscriptions!$B$5:$B$218,A20) | K20: =SUMIFS(Sales_Ledger!$J$5:$J$863,Sales_Ledger!$H$5:$H$863,$A20,Sales_Ledger!$D$5:$D$863,2023) | L20: =SUMIFS(Sales_Ledger!$J$5:$J$863,Sales_Ledger!$H$5:$H$863,$A20,Sales_Ledger!$D$5:$D$863,2024) | M20: =SUMIFS(Sales_Ledger!$J$5:$J$863,Sales_Ledger!$H$5:$H$863,$A20,Sales_Ledger!$D$5:$D$863,2025) | N20: =SUM(K20:M20) | O20: Client register | P20: incentives | Q20: TOBY AND TYE | R20: =IF(AND(I20>0,N20>I20*1.02),"Receipts exceed register contract value: check for duplicate entries, extra plots or ancillary fees",IF(AND(I20=0,N20>0),"Not in client register: contract value unknown",""))
A21: BP-C0017 | B21: Mr. Taiwo John Adeleye. | C21: 46766349990 / 8035888286 / 09063911358, 08035888286 | D21: SENT / johnadetaiwo@gmail.com | E21: Land | F21: Green City Ibadan (Akinyele-Moniya); Green City Phase 1 (Lantaba, Ketu-Epe); Green City Phase 2 (Idobi, Ketu-Epe); Green City Phase 2 (Ketu-Epe); Land (estate not stated in source) | G21: 45129 | H21: =IF(COUNTIF(Sales_Ledger!$H$5:$H$863,A21)=0,"",_xlfn.MINIFS(Sales_Ledger!$B$5:$B$863,Sales_Ledger!$H$5:$H$863,A21)) | I21: =SUMIFS(Subscriptions!$I$5:$I$218,Subscriptions!$B$5:$B$218,A21) | J21: =SUMIFS(Subscriptions!$J$5:$J$218,Subscriptions!$B$5:$B$218,A21) | K21: =SUMIFS(Sales_Ledger!$J$5:$J$863,Sales_Ledger!$H$5:$H$863,$A21,Sales_Ledger!$D$5:$D$863,2023) | L21: =SUMIFS(Sales_Ledger!$J$5:$J$863,Sales_Ledger!$H$5:$H$863,$A21,Sales_Ledger!$D$5:$D$863,2024) | M21: =SUMIFS(Sales_Ledger!$J$5:$J$863,Sales_Ledger!$H$5:$H$863,$A21,Sales_Ledger!$D$5:$D$863,2025) | N21: =SUM(K21:M21) | O21: Client register + Transaction records | P21: Bought, bought | Q21: MD, Ms Jochebed (Team Moffat) | R21: =IF(AND(I21>0,N21>I21*1.02),"Receipts exceed register contract value: check for duplicate entries, extra plots or ancillary fees",IF(AND(I21=0,N21>0),"Not in client register: contract value unknown",""))
A22: BP-C0018 | B22: Mr Sunday Gideon | C22: 9051114954 | D22: SENT | E22: Land | F22: Green City Phase 1 (Lantaba, Ketu-Epe); Land (estate not stated in source) | G22: 45137 | H22: =IF(COUNTIF(Sales_Ledger!$H$5:$H$863,A22)=0,"",_xlfn.MINIFS(Sales_Ledger!$B$5:$B$863,Sales_Ledger!$H$5:$H$863,A22)) | I22: =SUMIFS(Subscriptions!$I$5:$I$218,Subscriptions!$B$5:$B$218,A22) | J22: =SUMIFS(Subscriptions!$J$5:$J$218,Subscriptions!$B$5:$B$218,A22) | K22: =SUMIFS(Sales_Ledger!$J$5:$J$863,Sales_Ledger!$H$5:$H$863,$A22,Sales_Ledger!$D$5:$D$863,2023) | L22: =SUMIFS(Sales_Ledger!$J$5:$J$863,Sales_Ledger!$H$5:$H$863,$A22,Sales_Ledger!$D$5:$D$863,2024) | M22: =SUMIFS(Sales_Ledger!$J$5:$J$863,Sales_Ledger!$H$5:$H$863,$A22,Sales_Ledger!$D$5:$D$863,2025) | N22: =SUM(K22:M22) | O22: Client register + Transaction records | P22: bought | Q22: MS BLESSING | R22: =IF(AND(I22>0,N22>I22*1.02),"Receipts exceed register contract value: check for duplicate entries, extra plots or ancillary fees",IF(AND(I22=0,N22>0),"Not in client register: contract value unknown",""))
A23: BP-C0019 | B23: Mr Ogbu Pius Ejaka | C23: 07042269222 09027820971 | D23: ogbu.pius.e@gmail.com | E23: Land | F23: Green City Phase 3 (Omu-Epe); Land (estate not stated in source); Land: ancillary charges | G23: 45516 | H23: =IF(COUNTIF(Sales_Ledger!$H$5:$H$863,A23)=0,"",_xlfn.MINIFS(Sales_Ledger!$B$5:$B$863,Sales_Ledger!$H$5:$H$863,A23)) | I23: =SUMIFS(Subscriptions!$I$5:$I$218,Subscriptions!$B$5:$B$218,A23) | J23: =SUMIFS(Subscriptions!$J$5:$J$218,Subscriptions!$B$5:$B$218,A23) | K23: =SUMIFS(Sales_Ledger!$J$5:$J$863,Sales_Ledger!$H$5:$H$863,$A23,Sales_Ledger!$D$5:$D$863,2023) | L23: =SUMIFS(Sales_Ledger!$J$5:$J$863,Sales_Ledger!$H$5:$H$863,$A23,Sales_Ledger!$D$5:$D$863,2024) | M23: =SUMIFS(Sales_Ledger!$J$5:$J$863,Sales_Ledger!$H$5:$H$863,$A23,Sales_Ledger!$D$5:$D$863,2025) | N23: =SUM(K23:M23) | O23: Client register + Transaction records | P23: Bought | Q23: Ms Anointing | R23: =IF(AND(I23>0,N23>I23*1.02),"Receipts exceed register contract value: check for duplicate entries, extra plots or ancillary fees",IF(AND(I23=0,N23>0),"Not in client register: contract value unknown",""))
A24: BP-C0020 | B24: Mr Adebowale Oluwapelumi Joseph | C24: 1(937) 279-4380 | D24: SENT | E24: Land | F24: Green City Phase 1 (Lantaba, Ketu-Epe) | G24: 45161 | H24: =IF(COUNTIF(Sales_Ledger!$H$5:$H$863,A24)=0,"",_xlfn.MINIFS(Sales_Ledger!$B$5:$B$863,Sales_Ledger!$H$5:$H$863,A24)) | I24: =SUMIFS(Subscriptions!$I$5:$I$218,Subscriptions!$B$5:$B$218,A24) | J24: =SUMIFS(Subscriptions!$J$5:$J$218,Subscriptions!$B$5:$B$218,A24) | K24: =SUMIFS(Sales_Ledger!$J$5:$J$863,Sales_Ledger!$H$5:$H$863,$A24,Sales_Ledger!$D$5:$D$863,2023) | L24: =SUMIFS(Sales_Ledger!$J$5:$J$863,Sales_Ledger!$H$5:$H$863,$A24,Sales_Ledger!$D$5:$D$863,2024) | M24: =SUMIFS(Sales_Ledger!$J$5:$J$863,Sales_Ledger!$H$5:$H$863,$A24,Sales_Ledger!$D$5:$D$863,2025) | N24: =SUM(K24:M24) | O24: Client register | P24: Bought | Q24: MD | R24: =IF(AND(I24>0,N24>I24*1.02),"Receipts exceed register contract value: check for duplicate entries, extra plots or ancillary fees",IF(AND(I24=0,N24>0),"Not in client register: contract value unknown",""))
A25: BP-C0021 | B25: Mr Oyewole Sheriff Oyewusi | C25: 1(310) 728-5174 | D25: SENT | E25: Land | F25: Green City Phase 1 (Lantaba, Ketu-Epe); Land (estate not stated in source) | G25: 45161 | H25: =IF(COUNTIF(Sales_Ledger!$H$5:$H$863,A25)=0,"",_xlfn.MINIFS(Sales_Ledger!$B$5:$B$863,Sales_Ledger!$H$5:$H$863,A25)) | I25: =SUMIFS(Subscriptions!$I$5:$I$218,Subscriptions!$B$5:$B$218,A25) | J25: =SUMIFS(Subscriptions!$J$5:$J$218,Subscriptions!$B$5:$B$218,A25) | K25: =SUMIFS(Sales_Ledger!$J$5:$J$863,Sales_Ledger!$H$5:$H$863,$A25,Sales_Ledger!$D$5:$D$863,2023) | L25: =SUMIFS(Sales_Ledger!$J$5:$J$863,Sales_Ledger!$H$5:$H$863,$A25,Sales_Ledger!$D$5:$D$863,2024) | M25: =SUMIFS(Sales_Ledger!$J$5:$J$863,Sales_Ledger!$H$5:$H$863,$A25,Sales_Ledger!$D$5:$D$863,2025) | N25: =SUM(K25:M25) | O25: Client register + Transaction records | P25: Bought | Q25: Ms Bolanle | R25: =IF(AND(I25>0,N25>I25*1.02),"Receipts exceed register contract value: check for duplicate entries, extra plots or ancillary fees",IF(AND(I25=0,N25>0),"Not in client register: contract value unknown",""))
A26: BP-C0022 | B26: Mr Folaranmi Olatunde | C26: 8064494102 | D26: SENT | E26: Land | F26: Green City Phase 1 (Lantaba, Ketu-Epe) | G26: 45162 | H26: =IF(COUNTIF(Sales_Ledger!$H$5:$H$863,A26)=0,"",_xlfn.MINIFS(Sales_Ledger!$B$5:$B$863,Sales_Ledger!$H$5:$H$863,A26)) | I26: =SUMIFS(Subscriptions!$I$5:$I$218,Subscriptions!$B$5:$B$218,A26) | J26: =SUMIFS(Subscriptions!$J$5:$J$218,Subscriptions!$B$5:$B$218,A26) | K26: =SUMIFS(Sales_Ledger!$J$5:$J$863,Sales_Ledger!$H$5:$H$863,$A26,Sales_Ledger!$D$5:$D$863,2023) | L26: =SUMIFS(Sales_Ledger!$J$5:$J$863,Sales_Ledger!$H$5:$H$863,$A26,Sales_Ledger!$D$5:$D$863,2024) | M26: =SUMIFS(Sales_Ledger!$J$5:$J$863,Sales_Ledger!$H$5:$H$863,$A26,Sales_Ledger!$D$5:$D$863,2025) | N26: =SUM(K26:M26) | O26: Client register | P26: Bought | Q26: MD | R26: =IF(AND(I26>0,N26>I26*1.02),"Receipts exceed register contract value: check for duplicate entries, extra plots or ancillary fees",IF(AND(I26=0,N26>0),"Not in client register: contract value unknown",""))
A27: BP-C0023 | B27: MR KOREDE ADESE | C27: 8136836779 | D27: adeseakorede@gmail.com | E27: Land | F27: Green City Agbowa; Green City Phase 1 (Lantaba, Ketu-Epe) | G27: 45166 | H27: =IF(COUNTIF(Sales_Ledger!$H$5:$H$863,A27)=0,"",_xlfn.MINIFS(Sales_Ledger!$B$5:$B$863,Sales_Ledger!$H$5:$H$863,A27)) | I27: =SUMIFS(Subscriptions!$I$5:$I$218,Subscriptions!$B$5:$B$218,A27) | J27: =SUMIFS(Subscriptions!$J$5:$J$218,Subscriptions!$B$5:$B$218,A27) | K27: =SUMIFS(Sales_Ledger!$J$5:$J$863,Sales_Ledger!$H$5:$H$863,$A27,Sales_Ledger!$D$5:$D$863,2023) | L27: =SUMIFS(Sales_Ledger!$J$5:$J$863,Sales_Ledger!$H$5:$H$863,$A27,Sales_Ledger!$D$5:$D$863,2024) | M27: =SUMIFS(Sales_Ledger!$J$5:$J$863,Sales_Ledger!$H$5:$H$863,$A27,Sales_Ledger!$D$5:$D$863,2025) | N27: =SUM(K27:M27) | O27: Client register | P27: Bought, Paying | Q27: MD | R27: =IF(AND(I27>0,N27>I27*1.02),"Receipts exceed register contract value: check for duplicate entries, extra plots or ancillary fees",IF(AND(I27=0,N27>0),"Not in client register: contract value unknown",""))
A28: BP-C0024 | B28: Ms Peace Ikpotokin | C28: 2347063665467 | E28: Land | F28: Green City Phase 1 (Lantaba, Ketu-Epe) | G28: 45166 | H28: =IF(COUNTIF(Sales_Ledger!$H$5:$H$863,A28)=0,"",_xlfn.MINIFS(Sales_Ledger!$B$5:$B$863,Sales_Ledger!$H$5:$H$863,A28)) | I28: =SUMIFS(Subscriptions!$I$5:$I$218,Subscriptions!$B$5:$B$218,A28) | J28: =SUMIFS(Subscriptions!$J$5:$J$218,Subscriptions!$B$5:$B$218,A28) | K28: =SUMIFS(Sales_Ledger!$J$5:$J$863,Sales_Ledger!$H$5:$H$863,$A28,Sales_Ledger!$D$5:$D$863,2023) | L28: =SUMIFS(Sales_Ledger!$J$5:$J$863,Sales_Ledger!$H$5:$H$863,$A28,Sales_Ledger!$D$5:$D$863,2024) | M28: =SUMIFS(Sales_Ledger!$J$5:$J$863,Sales_Ledger!$H$5:$H$863,$A28,Sales_Ledger!$D$5:$D$863,2025) | N28: =SUM(K28:M28) | O28: Client register | P28: Promise | Q28: MD | R28: =IF(AND(I28>0,N28>I28*1.02),"Receipts exceed register contract value: check for duplicate entries, extra plots or ancillary fees",IF(AND(I28=0,N28>0),"Not in client register: contract value unknown",""))
A29: BP-C0025 | B29: Mrs Obadara Dorcas Adebisi | C29: 12149624394 | D29: SENT | E29: Land | F29: Green City Phase 1 (Lantaba, Ketu-Epe); Land (estate not stated in source); Land: ancillary charges | G29: 45173 | H29: =IF(COUNTIF(Sales_Ledger!$H$5:$H$863,A29)=0,"",_xlfn.MINIFS(Sales_Ledger!$B$5:$B$863,Sales_Ledger!$H$5:$H$863,A29)) | I29: =SUMIFS(Subscriptions!$I$5:$I$218,Subscriptions!$B$5:$B$218,A29) | J29: =SUMIFS(Subscriptions!$J$5:$J$218,Subscriptions!$B$5:$B$218,A29) | K29: =SUMIFS(Sales_Ledger!$J$5:$J$863,Sales_Ledger!$H$5:$H$863,$A29,Sales_Ledger!$D$5:$D$863,2023) | L29: =SUMIFS(Sales_Ledger!$J$5:$J$863,Sales_Ledger!$H$5:$H$863,$A29,Sales_Ledger!$D$5:$D$863,2024) | M29: =SUMIFS(Sales_Ledger!$J$5:$J$863,Sales_Ledger!$H$5:$H$863,$A29,Sales_Ledger!$D$5:$D$863,2025) | N29: =SUM(K29:M29) | O29: Client register + Transaction records | P29: Bought | Q29: Barister Nelson | R29: =IF(AND(I29>0,N29>I29*1.02),"Receipts exceed register contract value: check for duplicate entries, extra plots or ancillary fees",IF(AND(I29=0,N29>0),"Not in client register: contract value unknown",""))
A30: BP-C0026 | B30: Mr & Mrs Adebayo Dada | C30: 8037217444 | D30: SENT / adebayodada55@gmail.com | E30: Land | F30: Green City Phase 1 (Ketu-Epe); Green City Phase 1 (Lantaba, Ketu-Epe); Green City Phase 3 (Omu-Epe); Land (estate not stated in source); Land: ancillary charges | G30: 45205 | H30: =IF(COUNTIF(Sales_Ledger!$H$5:$H$863,A30)=0,"",_xlfn.MINIFS(Sales_Ledger!$B$5:$B$863,Sales_Ledger!$H$5:$H$863,A30)) | I30: =SUMIFS(Subscriptions!$I$5:$I$218,Subscriptions!$B$5:$B$218,A30) | J30: =SUMIFS(Subscriptions!$J$5:$J$218,Subscriptions!$B$5:$B$218,A30) | K30: =SUMIFS(Sales_Ledger!$J$5:$J$863,Sales_Ledger!$H$5:$H$863,$A30,Sales_Ledger!$D$5:$D$863,2023) | L30: =SUMIFS(Sales_Ledger!$J$5:$J$863,Sales_Ledger!$H$5:$H$863,$A30,Sales_Ledger!$D$5:$D$863,2024) | M30: =SUMIFS(Sales_Ledger!$J$5:$J$863,Sales_Ledger!$H$5:$H$863,$A30,Sales_Ledger!$D$5:$D$863,2025) | N30: =SUM(K30:M30) | O30: Client register + Transaction records | P30: Bought | Q30: Mrs Abimbola | R30: =IF(AND(I30>0,N30>I30*1.02),"Receipts exceed register contract value: check for duplicate entries, extra plots or ancillary fees",IF(AND(I30=0,N30>0),"Not in client register: contract value unknown",""))
A31: BP-C0027 | B31: Mr Edun Ayobami Simeon and bro | C31: 13525192389 | D31: SENT | E31: Land | F31: Green City Phase 1 (Ketu-Epe); Green City Phase 1 (Lantaba, Ketu-Epe); Land: ancillary charges | G31: 45190 | H31: =IF(COUNTIF(Sales_Ledger!$H$5:$H$863,A31)=0,"",_xlfn.MINIFS(Sales_Ledger!$B$5:$B$863,Sales_Ledger!$H$5:$H$863,A31)) | I31: =SUMIFS(Subscriptions!$I$5:$I$218,Subscriptions!$B$5:$B$218,A31) | J31: =SUMIFS(Subscriptions!$J$5:$J$218,Subscriptions!$B$5:$B$218,A31) | K31: =SUMIFS(Sales_Ledger!$J$5:$J$863,Sales_Ledger!$H$5:$H$863,$A31,Sales_Ledger!$D$5:$D$863,2023) | L31: =SUMIFS(Sales_Ledger!$J$5:$J$863,Sales_Ledger!$H$5:$H$863,$A31,Sales_Ledger!$D$5:$D$863,2024) | M31: =SUMIFS(Sales_Ledger!$J$5:$J$863,Sales_Ledger!$H$5:$H$863,$A31,Sales_Ledger!$D$5:$D$863,2025) | N31: =SUM(K31:M31) | O31: Client register + Transaction records | P31: Bought | Q31: Mr Olaiya/MD | R31: =IF(AND(I31>0,N31>I31*1.02),"Receipts exceed register contract value: check for duplicate entries, extra plots or ancillary fees",IF(AND(I31=0,N31>0),"Not in client register: contract value unknown",""))
A32: BP-C0028 | B32: Mr Adebanjo Isaac Olamilekan | C32: 9030482388 | D32: adebanjoisaac4@gmail.com | E32: Land | F32: Green City Phase 1 (Ketu-Epe); Green City Phase 2 (Idobi, Ketu-Epe); Green City Phase 2 (Ketu-Epe); Land (estate not stated in source) | G32: 45716 | H32: =IF(COUNTIF(Sales_Ledger!$H$5:$H$863,A32)=0,"",_xlfn.MINIFS(Sales_Ledger!$B$5:$B$863,Sales_Ledger!$H$5:$H$863,A32)) | I32: =SUMIFS(Subscriptions!$I$5:$I$218,Subscriptions!$B$5:$B$218,A32) | J32: =SUMIFS(Subscriptions!$J$5:$J$218,Subscriptions!$B$5:$B$218,A32) | K32: =SUMIFS(Sales_Ledger!$J$5:$J$863,Sales_Ledger!$H$5:$H$863,$A32,Sales_Ledger!$D$5:$D$863,2023) | L32: =SUMIFS(Sales_Ledger!$J$5:$J$863,Sales_Ledger!$H$5:$H$863,$A32,Sales_Ledger!$D$5:$D$863,2024) | M32: =SUMIFS(Sales_Ledger!$J$5:$J$863,Sales_Ledger!$H$5:$H$863,$A32,Sales_Ledger!$D$5:$D$863,2025) | N32: =SUM(K32:M32) | O32: Client register + Transaction records | P32: Bought | Q32: MD | R32: =IF(AND(I32>0,N32>I32*1.02),"Receipts exceed register contract value: check for duplicate entries, extra plots or ancillary fees",IF(AND(I32=0,N32>0),"Not in client register: contract value unknown",""))
A33: BP-C0029 | B33: Mr Ohanehi Anthony Chukwunonso | C33: 8034359513 | D33: SENT / tonyjay202183@gmail.com | E33: Land | F33: Green City Phase 1 (Ketu-Epe); Green City Phase 1 (Lantaba, Ketu-Epe); Green City Phase 2 (Idobi, Ketu-Epe); Green City Phase 2 (Ketu-Epe); Land (estate not stated in source) | G33: 45229 | H33: =IF(COUNTIF(Sales_Ledger!$H$5:$H$863,A33)=0,"",_xlfn.MINIFS(Sales_Ledger!$B$5:$B$863,Sales_Ledger!$H$5:$H$863,A33)) | I33: =SUMIFS(Subscriptions!$I$5:$I$218,Subscriptions!$B$5:$B$218,A33) | J33: =SUMIFS(Subscriptions!$J$5:$J$218,Subscriptions!$B$5:$B$218,A33) | K33: =SUMIFS(Sales_Ledger!$J$5:$J$863,Sales_Ledger!$H$5:$H$863,$A33,Sales_Ledger!$D$5:$D$863,2023) | L33: =SUMIFS(Sales_Ledger!$J$5:$J$863,Sales_Ledger!$H$5:$H$863,$A33,Sales_Ledger!$D$5:$D$863,2024) | M33: =SUMIFS(Sales_Ledger!$J$5:$J$863,Sales_Ledger!$H$5:$H$863,$A33,Sales_Ledger!$D$5:$D$863,2025) | N33: =SUM(K33:M33) | O33: Client register + Transaction records | P33: Bought, Paying | Q33: MD, Ms Immaculate | R33: =IF(AND(I33>0,N33>I33*1.02),"Receipts exceed register contract value: check for duplicate entries, extra plots or ancillary fees",IF(AND(I33=0,N33>0),"Not in client register: contract value unknown",""))
A34: BP-C0030 | B34: Mr. Adese Akorede John | C34: 8136836779 | D34: adeseakorede@gmail.com | E34: Land | F34: Green City Ibadan (Akinyele-Moniya); Green City Phase 1 (Ketu-Epe); Green City Phase 2 (Idobi, Ketu-Epe); Green City Phase 2 (Ketu-Epe); Land (estate not stated in source); Land: ancillary charges | G34: 45376 | H34: =IF(COUNTIF(Sales_Ledger!$H$5:$H$863,A34)=0,"",_xlfn.MINIFS(Sales_Ledger!$B$5:$B$863,Sales_Ledger!$H$5:$H$863,A34)) | I34: =SUMIFS(Subscriptions!$I$5:$I$218,Subscriptions!$B$5:$B$218,A34) | J34: =SUMIFS(Subscriptions!$J$5:$J$218,Subscriptions!$B$5:$B$218,A34) | K34: =SUMIFS(Sales_Ledger!$J$5:$J$863,Sales_Ledger!$H$5:$H$863,$A34,Sales_Ledger!$D$5:$D$863,2023) | L34: =SUMIFS(Sales_Ledger!$J$5:$J$863,Sales_Ledger!$H$5:$H$863,$A34,Sales_Ledger!$D$5:$D$863,2024) | M34: =SUMIFS(Sales_Ledger!$J$5:$J$863,Sales_Ledger!$H$5:$H$863,$A34,Sales_Ledger!$D$5:$D$863,2025) | N34: =SUM(K34:M34) | O34: Client register + Transaction records | P34: Bought | Q34: MD | R34: =IF(AND(I34>0,N34>I34*1.02),"Receipts exceed register contract value: check for duplicate entries, extra plots or ancillary fees",IF(AND(I34=0,N34>0),"Not in client register: contract value unknown",""))
A35: BP-C0031 | B35: Mr Eguavoen Harrison | D35: harrisoneguavoen@yahoo.com | E35: Land | F35: Green City Agbowa | G35: 45209 | H35: =IF(COUNTIF(Sales_Ledger!$H$5:$H$863,A35)=0,"",_xlfn.MINIFS(Sales_Ledger!$B$5:$B$863,Sales_Ledger!$H$5:$H$863,A35)) | I35: =SUMIFS(Subscriptions!$I$5:$I$218,Subscriptions!$B$5:$B$218,A35) | J35: =SUMIFS(Subscriptions!$J$5:$J$218,Subscriptions!$B$5:$B$218,A35) | K35: =SUMIFS(Sales_Ledger!$J$5:$J$863,Sales_Ledger!$H$5:$H$863,$A35,Sales_Ledger!$D$5:$D$863,2023) | L35: =SUMIFS(Sales_Ledger!$J$5:$J$863,Sales_Ledger!$H$5:$H$863,$A35,Sales_Ledger!$D$5:$D$863,2024) | M35: =SUMIFS(Sales_Ledger!$J$5:$J$863,Sales_Ledger!$H$5:$H$863,$A35,Sales_Ledger!$D$5:$D$863,2025) | N35: =SUM(K35:M35) | O35: Client register | P35: Refund | Q35: Ms Blessing | R35: =IF(AND(I35>0,N35>I35*1.02),"Receipts exceed register contract value: check for duplicate entries, extra plots or ancillary fees",IF(AND(I35=0,N35>0),"Not in client register: contract value unknown",""))
A36: BP-C0032 | B36: Mr Tomiwa Ibiks ********* | C36: 7039367538 | E36: Land | F36: Green City Phase 1 (Lantaba, Ketu-Epe) | G36: 45209 | H36: =IF(COUNTIF(Sales_Ledger!$H$5:$H$863,A36)=0,"",_xlfn.MINIFS(Sales_Ledger!$B$5:$B$863,Sales_Ledger!$H$5:$H$863,A36)) | I36: =SUMIFS(Subscriptions!$I$5:$I$218,Subscriptions!$B$5:$B$218,A36) | J36: =SUMIFS(Subscriptions!$J$5:$J$218,Subscriptions!$B$5:$B$218,A36) | K36: =SUMIFS(Sales_Ledger!$J$5:$J$863,Sales_Ledger!$H$5:$H$863,$A36,Sales_Ledger!$D$5:$D$863,2023) | L36: =SUMIFS(Sales_Ledger!$J$5:$J$863,Sales_Ledger!$H$5:$H$863,$A36,Sales_Ledger!$D$5:$D$863,2024) | M36: =SUMIFS(Sales_Ledger!$J$5:$J$863,Sales_Ledger!$H$5:$H$863,$A36,Sales_Ledger!$D$5:$D$863,2025) | N36: =SUM(K36:M36) | O36: Client register | P36: Paying | Q36: MD | R36: =IF(AND(I36>0,N36>I36*1.02),"Receipts exceed register contract value: check for duplicate entries, extra plots or ancillary fees",IF(AND(I36=0,N36>0),"Not in client register: contract value unknown",""))
A37: BP-C0033 | B37: Mr Olumoko Oladapo Oluwaseun | C37: 8033494369 | D37: SENT | E37: Land | F37: Green City Phase 1 (Ketu-Epe); Green City Phase 1 (Lantaba, Ketu-Epe); Land (estate not stated in source) | G37: 45211 | H37: =IF(COUNTIF(Sales_Ledger!$H$5:$H$863,A37)=0,"",_xlfn.MINIFS(Sales_Ledger!$B$5:$B$863,Sales_Ledger!$H$5:$H$863,A37)) | I37: =SUMIFS(Subscriptions!$I$5:$I$218,Subscriptions!$B$5:$B$218,A37) | J37: =SUMIFS(Subscriptions!$J$5:$J$218,Subscriptions!$B$5:$B$218,A37) | K37: =SUMIFS(Sales_Ledger!$J$5:$J$863,Sales_Ledger!$H$5:$H$863,$A37,Sales_Ledger!$D$5:$D$863,2023) | L37: =SUMIFS(Sales_Ledger!$J$5:$J$863,Sales_Ledger!$H$5:$H$863,$A37,Sales_Ledger!$D$5:$D$863,2024) | M37: =SUMIFS(Sales_Ledger!$J$5:$J$863,Sales_Ledger!$H$5:$H$863,$A37,Sales_Ledger!$D$5:$D$863,2025) | N37: =SUM(K37:M37) | O37: Client register + Transaction records | P37: Bought | Q37: Ms Bolanle | R37: =IF(AND(I37>0,N37>I37*1.02),"Receipts exceed register contract value: check for duplicate entries, extra plots or ancillary fees",IF(AND(I37=0,N37>0),"Not in client register: contract value unknown",""))
A38: BP-C0034 | B38: Mrs Ndubuisi Ujunwa | C38: 9060220053 | D38: SENT | E38: Land | F38: Green City Phase 1 (Lantaba, Ketu-Epe); Land (estate not stated in source) | G38: 45211 | H38: =IF(COUNTIF(Sales_Ledger!$H$5:$H$863,A38)=0,"",_xlfn.MINIFS(Sales_Ledger!$B$5:$B$863,Sales_Ledger!$H$5:$H$863,A38)) | I38: =SUMIFS(Subscriptions!$I$5:$I$218,Subscriptions!$B$5:$B$218,A38) | J38: =SUMIFS(Subscriptions!$J$5:$J$218,Subscriptions!$B$5:$B$218,A38) | K38: =SUMIFS(Sales_Ledger!$J$5:$J$863,Sales_Ledger!$H$5:$H$863,$A38,Sales_Ledger!$D$5:$D$863,2023) | L38: =SUMIFS(Sales_Ledger!$J$5:$J$863,Sales_Ledger!$H$5:$H$863,$A38,Sales_Ledger!$D$5:$D$863,2024) | M38: =SUMIFS(Sales_Ledger!$J$5:$J$863,Sales_Ledger!$H$5:$H$863,$A38,Sales_Ledger!$D$5:$D$863,2025) | N38: =SUM(K38:M38) | O38: Client register + Transaction records | P38: Bought | Q38: Ms Immaculate | R38: =IF(AND(I38>0,N38>I38*1.02),"Receipts exceed register contract value: check for duplicate entries, extra plots or ancillary fees",IF(AND(I38=0,N38>0),"Not in client register: contract value unknown",""))
A39: BP-C0035 | B39: Vacant | C39: 8167516120 | E39: Land | F39: Green City Phase 1 (Lantaba, Ketu-Epe) | G39: 45211 | H39: =IF(COUNTIF(Sales_Ledger!$H$5:$H$863,A39)=0,"",_xlfn.MINIFS(Sales_Ledger!$B$5:$B$863,Sales_Ledger!$H$5:$H$863,A39)) | I39: =SUMIFS(Subscriptions!$I$5:$I$218,Subscriptions!$B$5:$B$218,A39) | J39: =SUMIFS(Subscriptions!$J$5:$J$218,Subscriptions!$B$5:$B$218,A39) | K39: =SUMIFS(Sales_Ledger!$J$5:$J$863,Sales_Ledger!$H$5:$H$863,$A39,Sales_Ledger!$D$5:$D$863,2023) | L39: =SUMIFS(Sales_Ledger!$J$5:$J$863,Sales_Ledger!$H$5:$H$863,$A39,Sales_Ledger!$D$5:$D$863,2024) | M39: =SUMIFS(Sales_Ledger!$J$5:$J$863,Sales_Ledger!$H$5:$H$863,$A39,Sales_Ledger!$D$5:$D$863,2025) | N39: =SUM(K39:M39) | O39: Client register | P39: bought | Q39: MD | R39: =IF(AND(I39>0,N39>I39*1.02),"Receipts exceed register contract value: check for duplicate entries, extra plots or ancillary fees",IF(AND(I39=0,N39>0),"Not in client register: contract value unknown",""))
A40: BP-C0036 | B40: Ohumende Paul Osaze | C40: 8165253939 | D40: SENT / mendes.paul28@gmail.com | E40: Land | F40: Green City Phase 1 (Ketu-Epe); Green City Phase 1 (Lantaba, Ketu-Epe); Green City Phase 2 (Ketu-Epe); Land (estate not stated in source); Land: ancillary charges | G40: 45232 | H40: =IF(COUNTIF(Sales_Ledger!$H$5:$H$863,A40)=0,"",_xlfn.MINIFS(Sales_Ledger!$B$5:$B$863,Sales_Ledger!$H$5:$H$863,A40)) | I40: =SUMIFS(Subscriptions!$I$5:$I$218,Subscriptions!$B$5:$B$218,A40) | J40: =SUMIFS(Subscriptions!$J$5:$J$218,Subscriptions!$B$5:$B$218,A40) | K40: =SUMIFS(Sales_Ledger!$J$5:$J$863,Sales_Ledger!$H$5:$H$863,$A40,Sales_Ledger!$D$5:$D$863,2023) | L40: =SUMIFS(Sales_Ledger!$J$5:$J$863,Sales_Ledger!$H$5:$H$863,$A40,Sales_Ledger!$D$5:$D$863,2024) | M40: =SUMIFS(Sales_Ledger!$J$5:$J$863,Sales_Ledger!$H$5:$H$863,$A40,Sales_Ledger!$D$5:$D$863,2025) | N40: =SUM(K40:M40) | O40: Client register + Transaction records | P40: Bought | Q40: MD | R40: =IF(AND(I40>0,N40>I40*1.02),"Receipts exceed register contract value: check for duplicate entries, extra plots or ancillary fees",IF(AND(I40=0,N40>0),"Not in client register: contract value unknown",""))
A41: BP-C0037 | B41: Miss Okezie Mandy Ifeoma | C41: 7032342126 | D41: SENT / okezieifeoma00@gmail.com | E41: Land | F41: Green City Phase 1 (Lantaba, Ketu-Epe); Green City Phase 3 (Omu-Epe) | G41: 45228 | H41: =IF(COUNTIF(Sales_Ledger!$H$5:$H$863,A41)=0,"",_xlfn.MINIFS(Sales_Ledger!$B$5:$B$863,Sales_Ledger!$H$5:$H$863,A41)) | I41: =SUMIFS(Subscriptions!$I$5:$I$218,Subscriptions!$B$5:$B$218,A41) | J41: =SUMIFS(Subscriptions!$J$5:$J$218,Subscriptions!$B$5:$B$218,A41) | K41: =SUMIFS(Sales_Ledger!$J$5:$J$863,Sales_Ledger!$H$5:$H$863,$A41,Sales_Ledger!$D$5:$D$863,2023) | L41: =SUMIFS(Sales_Ledger!$J$5:$J$863,Sales_Ledger!$H$5:$H$863,$A41,Sales_Ledger!$D$5:$D$863,2024) | M41: =SUMIFS(Sales_Ledger!$J$5:$J$863,Sales_Ledger!$H$5:$H$863,$A41,Sales_Ledger!$D$5:$D$863,2025) | N41: =SUM(K41:M41) | O41: Client register + Transaction records | P41: Bought | Q41: Celina, Ms Celina | R41: =IF(AND(I41>0,N41>I41*1.02),"Receipts exceed register contract value: check for duplicate entries, extra plots or ancillary fees",IF(AND(I41=0,N41>0),"Not in client register: contract value unknown",""))
A42: BP-C0038 | B42: Okeizie Ifeoma Mandy | E42: Land | F42: Land (estate not stated in source) | H42: =IF(COUNTIF(Sales_Ledger!$H$5:$H$863,A42)=0,"",_xlfn.MINIFS(Sales_Ledger!$B$5:$B$863,Sales_Ledger!$H$5:$H$863,A42)) | I42: =SUMIFS(Subscriptions!$I$5:$I$218,Subscriptions!$B$5:$B$218,A42) | J42: =SUMIFS(Subscriptions!$J$5:$J$218,Subscriptions!$B$5:$B$218,A42) | K42: =SUMIFS(Sales_Ledger!$J$5:$J$863,Sales_Ledger!$H$5:$H$863,$A42,Sales_Ledger!$D$5:$D$863,2023) | L42: =SUMIFS(Sales_Ledger!$J$5:$J$863,Sales_Ledger!$H$5:$H$863,$A42,Sales_Ledger!$D$5:$D$863,2024) | M42: =SUMIFS(Sales_Ledger!$J$5:$J$863,Sales_Ledger!$H$5:$H$863,$A42,Sales_Ledger!$D$5:$D$863,2025) | N42: =SUM(K42:M42) | O42: Transaction records | R42: =IF(AND(I42>0,N42>I42*1.02),"Receipts exceed register contract value: check for duplicate entries, extra plots or ancillary fees",IF(AND(I42=0,N42>0),"Not in client register: contract value unknown",""))
A43: BP-C0039 | B43: Alabi Abdulazeez Toyosi | C43: 7064191538 | D43: alabitoyosi1616@gmail.com | E43: Land | F43: Green City Phase 2 (Ketu-Epe); Land (estate not stated in source) | G43: 45321 | H43: =IF(COUNTIF(Sales_Ledger!$H$5:$H$863,A43)=0,"",_xlfn.MINIFS(Sales_Ledger!$B$5:$B$863,Sales_Ledger!$H$5:$H$863,A43)) | I43: =SUMIFS(Subscriptions!$I$5:$I$218,Subscriptions!$B$5:$B$218,A43) | J43: =SUMIFS(Subscriptions!$J$5:$J$218,Subscriptions!$B$5:$B$218,A43) | K43: =SUMIFS(Sales_Ledger!$J$5:$J$863,Sales_Ledger!$H$5:$H$863,$A43,Sales_Ledger!$D$5:$D$863,2023) | L43: =SUMIFS(Sales_Ledger!$J$5:$J$863,Sales_Ledger!$H$5:$H$863,$A43,Sales_Ledger!$D$5:$D$863,2024) | M43: =SUMIFS(Sales_Ledger!$J$5:$J$863,Sales_Ledger!$H$5:$H$863,$A43,Sales_Ledger!$D$5:$D$863,2025) | N43: =SUM(K43:M43) | O43: Client register + Transaction records | P43: REFUND | Q43: MD | R43: =IF(AND(I43>0,N43>I43*1.02),"Receipts exceed register contract value: check for duplicate entries, extra plots or ancillary fees",IF(AND(I43=0,N43>0),"Not in client register: contract value unknown",""))
A44: BP-C0040 | B44: Bassey Christopher | C44: 9039054374 | D44: SENT | E44: Land | F44: Green City Phase 1 (Lantaba, Ketu-Epe); Land (estate not stated in source) | G44: 45229 | H44: =IF(COUNTIF(Sales_Ledger!$H$5:$H$863,A44)=0,"",_xlfn.MINIFS(Sales_Ledger!$B$5:$B$863,Sales_Ledger!$H$5:$H$863,A44)) | I44: =SUMIFS(Subscriptions!$I$5:$I$218,Subscriptions!$B$5:$B$218,A44) | J44: =SUMIFS(Subscriptions!$J$5:$J$218,Subscriptions!$B$5:$B$218,A44) | K44: =SUMIFS(Sales_Ledger!$J$5:$J$863,Sales_Ledger!$H$5:$H$863,$A44,Sales_Ledger!$D$5:$D$863,2023) | L44: =SUMIFS(Sales_Ledger!$J$5:$J$863,Sales_Ledger!$H$5:$H$863,$A44,Sales_Ledger!$D$5:$D$863,2024) | M44: =SUMIFS(Sales_Ledger!$J$5:$J$863,Sales_Ledger!$H$5:$H$863,$A44,Sales_Ledger!$D$5:$D$863,2025) | N44: =SUM(K44:M44) | O44: Client register + Transaction records | P44: Bought | Q44: Ms Immaculate | R44: =IF(AND(I44>0,N44>I44*1.02),"Receipts exceed register contract value: check for duplicate entries, extra plots or ancillary fees",IF(AND(I44=0,N44>0),"Not in client register: contract value unknown",""))
A45: BP-C0041 | B45: Alhaji Badamasi Mohammadu | C45: 8033417527 | D45: SENT | E45: Land | F45: Green City Phase 1 (Lantaba, Ketu-Epe) | G45: 45233 | H45: =IF(COUNTIF(Sales_Ledger!$H$5:$H$863,A45)=0,"",_xlfn.MINIFS(Sales_Ledger!$B$5:$B$863,Sales_Ledger!$H$5:$H$863,A45)) | I45: =SUMIFS(Subscriptions!$I$5:$I$218,Subscriptions!$B$5:$B$218,A45) | J45: =SUMIFS(Subscriptions!$J$5:$J$218,Subscriptions!$B$5:$B$218,A45) | K45: =SUMIFS(Sales_Ledger!$J$5:$J$863,Sales_Ledger!$H$5:$H$863,$A45,Sales_Ledger!$D$5:$D$863,2023) | L45: =SUMIFS(Sales_Ledger!$J$5:$J$863,Sales_Ledger!$H$5:$H$863,$A45,Sales_Ledger!$D$5:$D$863,2024) | M45: =SUMIFS(Sales_Ledger!$J$5:$J$863,Sales_Ledger!$H$5:$H$863,$A45,Sales_Ledger!$D$5:$D$863,2025) | N45: =SUM(K45:M45) | O45: Client register | P45: Bought | Q45: Ms Tobi Associate | R45: =IF(AND(I45>0,N45>I45*1.02),"Receipts exceed register contract value: check for duplicate entries, extra plots or ancillary fees",IF(AND(I45=0,N45>0),"Not in client register: contract value unknown",""))
A46: BP-C0042 | B46: Alhaji Gbadamosi Mohammad | E46: Land | F46: Land (estate not stated in source) | H46: =IF(COUNTIF(Sales_Ledger!$H$5:$H$863,A46)=0,"",_xlfn.MINIFS(Sales_Ledger!$B$5:$B$863,Sales_Ledger!$H$5:$H$863,A46)) | I46: =SUMIFS(Subscriptions!$I$5:$I$218,Subscriptions!$B$5:$B$218,A46) | J46: =SUMIFS(Subscriptions!$J$5:$J$218,Subscriptions!$B$5:$B$218,A46) | K46: =SUMIFS(Sales_Ledger!$J$5:$J$863,Sales_Ledger!$H$5:$H$863,$A46,Sales_Ledger!$D$5:$D$863,2023) | L46: =SUMIFS(Sales_Ledger!$J$5:$J$863,Sales_Ledger!$H$5:$H$863,$A46,Sales_Ledger!$D$5:$D$863,2024) | M46: =SUMIFS(Sales_Ledger!$J$5:$J$863,Sales_Ledger!$H$5:$H$863,$A46,Sales_Ledger!$D$5:$D$863,2025) | N46: =SUM(K46:M46) | O46: Transaction records | R46: =IF(AND(I46>0,N46>I46*1.02),"Receipts exceed register contract value: check for duplicate entries, extra plots or ancillary fees",IF(AND(I46=0,N46>0),"Not in client register: contract value unknown",""))
A47: BP-C0043 | B47: Mrs Oladiran Omolola Agnes | C47: Not filled | D47: agnesomolola7@gmail.com | E47: Land | F47: Green City Agbowa; Green City Phase 2 (Ketu-Epe); Land (estate not stated in source) | G47: 45239 | H47: =IF(COUNTIF(Sales_Ledger!$H$5:$H$863,A47)=0,"",_xlfn.MINIFS(Sales_Ledger!$B$5:$B$863,Sales_Ledger!$H$5:$H$863,A47)) | I47: =SUMIFS(Subscriptions!$I$5:$I$218,Subscriptions!$B$5:$B$218,A47) | J47: =SUMIFS(Subscriptions!$J$5:$J$218,Subscriptions!$B$5:$B$218,A47) | K47: =SUMIFS(Sales_Ledger!$J$5:$J$863,Sales_Ledger!$H$5:$H$863,$A47,Sales_Ledger!$D$5:$D$863,2023) | L47: =SUMIFS(Sales_Ledger!$J$5:$J$863,Sales_Ledger!$H$5:$H$863,$A47,Sales_Ledger!$D$5:$D$863,2024) | M47: =SUMIFS(Sales_Ledger!$J$5:$J$863,Sales_Ledger!$H$5:$H$863,$A47,Sales_Ledger!$D$5:$D$863,2025) | N47: =SUM(K47:M47) | O47: Client register + Transaction records | P47: Convert to ketu 2, REFUND | Q47: Mr Pelumi, Pelumi | R47: =IF(AND(I47>0,N47>I47*1.02),"Receipts exceed register contract value: check for duplicate entries, extra plots or ancillary fees",IF(AND(I47=0,N47>0),"Not in client register: contract value unknown",""))
A48: BP-C0044 | B48: Oluwase Babajide Victor | C48: 8136389666 | D48: SENT | E48: Land | F48: Green City Phase 1 (Ketu-Epe); Green City Phase 1 (Lantaba, Ketu-Epe) | G48: 45239 | H48: =IF(COUNTIF(Sales_Ledger!$H$5:$H$863,A48)=0,"",_xlfn.MINIFS(Sales_Ledger!$B$5:$B$863,Sales_Ledger!$H$5:$H$863,A48)) | I48: =SUMIFS(Subscriptions!$I$5:$I$218,Subscriptions!$B$5:$B$218,A48) | J48: =SUMIFS(Subscriptions!$J$5:$J$218,Subscriptions!$B$5:$B$218,A48) | K48: =SUMIFS(Sales_Ledger!$J$5:$J$863,Sales_Ledger!$H$5:$H$863,$A48,Sales_Ledger!$D$5:$D$863,2023) | L48: =SUMIFS(Sales_Ledger!$J$5:$J$863,Sales_Ledger!$H$5:$H$863,$A48,Sales_Ledger!$D$5:$D$863,2024) | M48: =SUMIFS(Sales_Ledger!$J$5:$J$863,Sales_Ledger!$H$5:$H$863,$A48,Sales_Ledger!$D$5:$D$863,2025) | N48: =SUM(K48:M48) | O48: Client register + Transaction records | P48: Bought | Q48: MD | R48: =IF(AND(I48>0,N48>I48*1.02),"Receipts exceed register contract value: check for duplicate entries, extra plots or ancillary fees",IF(AND(I48=0,N48>0),"Not in client register: contract value unknown",""))
A49: BP-C0045 | B49: Mr Bolarinwa Iyanuoluwa Simon & Dr Bolarinwa Abisola Christianah | C49: 7030281365 | D49: SENT / iyanuoluwabolarinwa@gmail.com | E49: Land | F49: Green City Phase 1 (Ketu-Epe); Green City Phase 1 (Lantaba, Ketu-Epe); Green City Phase 2 (Ketu-Epe) | G49: 45245 | H49: =IF(COUNTIF(Sales_Ledger!$H$5:$H$863,A49)=0,"",_xlfn.MINIFS(Sales_Ledger!$B$5:$B$863,Sales_Ledger!$H$5:$H$863,A49)) | I49: =SUMIFS(Subscriptions!$I$5:$I$218,Subscriptions!$B$5:$B$218,A49) | J49: =SUMIFS(Subscriptions!$J$5:$J$218,Subscriptions!$B$5:$B$218,A49) | K49: =SUMIFS(Sales_Ledger!$J$5:$J$863,Sales_Ledger!$H$5:$H$863,$A49,Sales_Ledger!$D$5:$D$863,2023) | L49: =SUMIFS(Sales_Ledger!$J$5:$J$863,Sales_Ledger!$H$5:$H$863,$A49,Sales_Ledger!$D$5:$D$863,2024) | M49: =SUMIFS(Sales_Ledger!$J$5:$J$863,Sales_Ledger!$H$5:$H$863,$A49,Sales_Ledger!$D$5:$D$863,2025) | N49: =SUM(K49:M49) | O49: Client register + Transaction records | P49: Bought | Q49: MD | R49: =IF(AND(I49>0,N49>I49*1.02),"Receipts exceed register contract value: check for duplicate entries, extra plots or ancillary fees",IF(AND(I49=0,N49>0),"Not in client register: contract value unknown",""))
A50: BP-C0046 | B50: Mr Adesida Raphael Abiodun | E50: Land | F50: Green City Phase 1 (Ketu-Epe); Green City Phase 1 (Lantaba, Ketu-Epe); Land (estate not stated in source); Land: ancillary charges | H50: =IF(COUNTIF(Sales_Ledger!$H$5:$H$863,A50)=0,"",_xlfn.MINIFS(Sales_Ledger!$B$5:$B$863,Sales_Ledger!$H$5:$H$863,A50)) | I50: =SUMIFS(Subscriptions!$I$5:$I$218,Subscriptions!$B$5:$B$218,A50) | J50: =SUMIFS(Subscriptions!$J$5:$J$218,Subscriptions!$B$5:$B$218,A50) | K50: =SUMIFS(Sales_Ledger!$J$5:$J$863,Sales_Ledger!$H$5:$H$863,$A50,Sales_Ledger!$D$5:$D$863,2023) | L50: =SUMIFS(Sales_Ledger!$J$5:$J$863,Sales_Ledger!$H$5:$H$863,$A50,Sales_Ledger!$D$5:$D$863,2024) | M50: =SUMIFS(Sales_Ledger!$J$5:$J$863,Sales_Ledger!$H$5:$H$863,$A50,Sales_Ledger!$D$5:$D$863,2025) | N50: =SUM(K50:M50) | O50: Transaction records | R50: =IF(AND(I50>0,N50>I50*1.02),"Receipts exceed register contract value: check for duplicate entries, extra plots or ancillary fees",IF(AND(I50=0,N50>0),"Not in client register: contract value unknown",""))
A51: BP-C0047 | B51: Ms Paulina Kehinde Akhere George | D51: SENT | E51: Housing | F51: Housing unit (project not stated in source); Pacific Court | G51: 45261 | H51: =IF(COUNTIF(Sales_Ledger!$H$5:$H$863,A51)=0,"",_xlfn.MINIFS(Sales_Ledger!$B$5:$B$863,Sales_Ledger!$H$5:$H$863,A51)) | I51: =SUMIFS(Subscriptions!$I$5:$I$218,Subscriptions!$B$5:$B$218,A51) | J51: =SUMIFS(Subscriptions!$J$5:$J$218,Subscriptions!$B$5:$B$218,A51) | K51: =SUMIFS(Sales_Ledger!$J$5:$J$863,Sales_Ledger!$H$5:$H$863,$A51,Sales_Ledger!$D$5:$D$863,2023) | L51: =SUMIFS(Sales_Ledger!$J$5:$J$863,Sales_Ledger!$H$5:$H$863,$A51,Sales_Ledger!$D$5:$D$863,2024) | M51: =SUMIFS(Sales_Ledger!$J$5:$J$863,Sales_Ledger!$H$5:$H$863,$A51,Sales_Ledger!$D$5:$D$863,2025) | N51: =SUM(K51:M51) | O51: Client register + Transaction records | P51: PAID | Q51: Barr. Amokeodo | R51: =IF(AND(I51>0,N51>I51*1.02),"Receipts exceed register contract value: check for duplicate entries, extra plots or ancillary fees",IF(AND(I51=0,N51>0),"Not in client register: contract value unknown",""))
A52: BP-C0048 | B52: Mr Araokonmi Sodiq Ayinla | C52: 08032726622, 07058447433 | D52: SENT | E52: Land | F52: Green City Phase 1 (Lantaba, Ketu-Epe); Land (estate not stated in source) | G52: 45268 | H52: =IF(COUNTIF(Sales_Ledger!$H$5:$H$863,A52)=0,"",_xlfn.MINIFS(Sales_Ledger!$B$5:$B$863,Sales_Ledger!$H$5:$H$863,A52)) | I52: =SUMIFS(Subscriptions!$I$5:$I$218,Subscriptions!$B$5:$B$218,A52) | J52: =SUMIFS(Subscriptions!$J$5:$J$218,Subscriptions!$B$5:$B$218,A52) | K52: =SUMIFS(Sales_Ledger!$J$5:$J$863,Sales_Ledger!$H$5:$H$863,$A52,Sales_Ledger!$D$5:$D$863,2023) | L52: =SUMIFS(Sales_Ledger!$J$5:$J$863,Sales_Ledger!$H$5:$H$863,$A52,Sales_Ledger!$D$5:$D$863,2024) | M52: =SUMIFS(Sales_Ledger!$J$5:$J$863,Sales_Ledger!$H$5:$H$863,$A52,Sales_Ledger!$D$5:$D$863,2025) | N52: =SUM(K52:M52) | O52: Client register + Transaction records | P52: Bought | Q52: Yetunde/MD | R52: =IF(AND(I52>0,N52>I52*1.02),"Receipts exceed register contract value: check for duplicate entries, extra plots or ancillary fees",IF(AND(I52=0,N52>0),"Not in client register: contract value unknown",""))
A53: BP-C0049 | B53: Mr Ali Ifesinachi Innocent | C53: 8090794894 | D53: SENT | E53: Land | F53: Green City Phase 1 (Lantaba, Ketu-Epe); Land (estate not stated in source) | G53: 45271 | H53: =IF(COUNTIF(Sales_Ledger!$H$5:$H$863,A53)=0,"",_xlfn.MINIFS(Sales_Ledger!$B$5:$B$863,Sales_Ledger!$H$5:$H$863,A53)) | I53: =SUMIFS(Subscriptions!$I$5:$I$218,Subscriptions!$B$5:$B$218,A53) | J53: =SUMIFS(Subscriptions!$J$5:$J$218,Subscriptions!$B$5:$B$218,A53) | K53: =SUMIFS(Sales_Ledger!$J$5:$J$863,Sales_Ledger!$H$5:$H$863,$A53,Sales_Ledger!$D$5:$D$863,2023) | L53: =SUMIFS(Sales_Ledger!$J$5:$J$863,Sales_Ledger!$H$5:$H$863,$A53,Sales_Ledger!$D$5:$D$863,2024) | M53: =SUMIFS(Sales_Ledger!$J$5:$J$863,Sales_Ledger!$H$5:$H$863,$A53,Sales_Ledger!$D$5:$D$863,2025) | N53: =SUM(K53:M53) | O53: Client register + Transaction records | P53: Bought | Q53: MD | R53: =IF(AND(I53>0,N53>I53*1.02),"Receipts exceed register contract value: check for duplicate entries, extra plots or ancillary fees",IF(AND(I53=0,N53>0),"Not in client register: contract value unknown",""))
A54: BP-C0050 | B54: Mr Atuanya Patrick Jideovo | C54: 9080257655 | D54: SENT / patuanya@gmail.com | E54: Land | F54: Green City Phase 1 (Ketu-Epe); Green City Phase 1 (Lantaba, Ketu-Epe); Green Hillside; Land (estate not stated in source); Land: ancillary charges | G54: 45274 | H54: =IF(COUNTIF(Sales_Ledger!$H$5:$H$863,A54)=0,"",_xlfn.MINIFS(Sales_Ledger!$B$5:$B$863,Sales_Ledger!$H$5:$H$863,A54)) | I54: =SUMIFS(Subscriptions!$I$5:$I$218,Subscriptions!$B$5:$B$218,A54) | J54: =SUMIFS(Subscriptions!$J$5:$J$218,Subscriptions!$B$5:$B$218,A54) | K54: =SUMIFS(Sales_Ledger!$J$5:$J$863,Sales_Ledger!$H$5:$H$863,$A54,Sales_Ledger!$D$5:$D$863,2023) | L54: =SUMIFS(Sales_Ledger!$J$5:$J$863,Sales_Ledger!$H$5:$H$863,$A54,Sales_Ledger!$D$5:$D$863,2024) | M54: =SUMIFS(Sales_Ledger!$J$5:$J$863,Sales_Ledger!$H$5:$H$863,$A54,Sales_Ledger!$D$5:$D$863,2025) | N54: =SUM(K54:M54) | O54: Client register + Transaction records | P54: Bought | Q54: Ms Yetunde, Yetunde/MD | R54: =IF(AND(I54>0,N54>I54*1.02),"Receipts exceed register contract value: check for duplicate entries, extra plots or ancillary fees",IF(AND(I54=0,N54>0),"Not in client register: contract value unknown",""))
A55: BP-C0051 | B55: Mr Ogunleye Olumide Victor | C55: 8139122188 | D55: SENT / ogunleyeolumide@gmail.com | E55: Land | F55: Green City Agbowa; Green City Phase 1 (Lantaba, Ketu-Epe); Green City Phase 2 (Ketu-Epe); Land (estate not stated in source) | G55: 45280 | H55: =IF(COUNTIF(Sales_Ledger!$H$5:$H$863,A55)=0,"",_xlfn.MINIFS(Sales_Ledger!$B$5:$B$863,Sales_Ledger!$H$5:$H$863,A55)) | I55: =SUMIFS(Subscriptions!$I$5:$I$218,Subscriptions!$B$5:$B$218,A55) | J55: =SUMIFS(Subscriptions!$J$5:$J$218,Subscriptions!$B$5:$B$218,A55) | K55: =SUMIFS(Sales_Ledger!$J$5:$J$863,Sales_Ledger!$H$5:$H$863,$A55,Sales_Ledger!$D$5:$D$863,2023) | L55: =SUMIFS(Sales_Ledger!$J$5:$J$863,Sales_Ledger!$H$5:$H$863,$A55,Sales_Ledger!$D$5:$D$863,2024) | M55: =SUMIFS(Sales_Ledger!$J$5:$J$863,Sales_Ledger!$H$5:$H$863,$A55,Sales_Ledger!$D$5:$D$863,2025) | N55: =SUM(K55:M55) | O55: Client register + Transaction records | P55: Bought, Paying | Q55: MD | R55: =IF(AND(I55>0,N55>I55*1.02),"Receipts exceed register contract value: check for duplicate entries, extra plots or ancillary fees",IF(AND(I55=0,N55>0),"Not in client register: contract value unknown",""))
A56: BP-C0052 | B56: Mathias Ojoma Lilian | C56: 7056666525 | D56: SENT | E56: Land | F56: Green City Phase 1 (Lantaba, Ketu-Epe); Land (estate not stated in source) | G56: 45283 | H56: =IF(COUNTIF(Sales_Ledger!$H$5:$H$863,A56)=0,"",_xlfn.MINIFS(Sales_Ledger!$B$5:$B$863,Sales_Ledger!$H$5:$H$863,A56)) | I56: =SUMIFS(Subscriptions!$I$5:$I$218,Subscriptions!$B$5:$B$218,A56) | J56: =SUMIFS(Subscriptions!$J$5:$J$218,Subscriptions!$B$5:$B$218,A56) | K56: =SUMIFS(Sales_Ledger!$J$5:$J$863,Sales_Ledger!$H$5:$H$863,$A56,Sales_Ledger!$D$5:$D$863,2023) | L56: =SUMIFS(Sales_Ledger!$J$5:$J$863,Sales_Ledger!$H$5:$H$863,$A56,Sales_Ledger!$D$5:$D$863,2024) | M56: =SUMIFS(Sales_Ledger!$J$5:$J$863,Sales_Ledger!$H$5:$H$863,$A56,Sales_Ledger!$D$5:$D$863,2025) | N56: =SUM(K56:M56) | O56: Client register + Transaction records | P56: Bought | Q56: Ms Immaculate | R56: =IF(AND(I56>0,N56>I56*1.02),"Receipts exceed register contract value: check for duplicate entries, extra plots or ancillary fees",IF(AND(I56=0,N56>0),"Not in client register: contract value unknown",""))
A57: BP-C0053 | B57: Mr Adegbembo Stephen Oluwagbemiga | C57: 447915419823 | D57: SENT | E57: Land | F57: Green City Phase 1 (Lantaba, Ketu-Epe); Land (estate not stated in source); Land: ancillary charges | G57: 45286 | H57: =IF(COUNTIF(Sales_Ledger!$H$5:$H$863,A57)=0,"",_xlfn.MINIFS(Sales_Ledger!$B$5:$B$863,Sales_Ledger!$H$5:$H$863,A57)) | I57: =SUMIFS(Subscriptions!$I$5:$I$218,Subscriptions!$B$5:$B$218,A57) | J57: =SUMIFS(Subscriptions!$J$5:$J$218,Subscriptions!$B$5:$B$218,A57) | K57: =SUMIFS(Sales_Ledger!$J$5:$J$863,Sales_Ledger!$H$5:$H$863,$A57,Sales_Ledger!$D$5:$D$863,2023) | L57: =SUMIFS(Sales_Ledger!$J$5:$J$863,Sales_Ledger!$H$5:$H$863,$A57,Sales_Ledger!$D$5:$D$863,2024) | M57: =SUMIFS(Sales_Ledger!$J$5:$J$863,Sales_Ledger!$H$5:$H$863,$A57,Sales_Ledger!$D$5:$D$863,2025) | N57: =SUM(K57:M57) | O57: Client register + Transaction records | P57: Bought | Q57: Ms Elizabeth | R57: =IF(AND(I57>0,N57>I57*1.02),"Receipts exceed register contract value: check for duplicate entries, extra plots or ancillary fees",IF(AND(I57=0,N57>0),"Not in client register: contract value unknown",""))
A58: BP-C0054 | B58: Mr Ademola Adeniyi | C58: 16475612700 | D58: SENT / demossa2000@gmail.com | E58: Land | F58: Green City Phase 1 (Lantaba, Ketu-Epe); Green City Phase 2 (Idobi, Ketu-Epe); Green City Phase 2 (Ketu-Epe); Land (estate not stated in source); Land: ancillary charges | G58: 45288 | H58: =IF(COUNTIF(Sales_Ledger!$H$5:$H$863,A58)=0,"",_xlfn.MINIFS(Sales_Ledger!$B$5:$B$863,Sales_Ledger!$H$5:$H$863,A58)) | I58: =SUMIFS(Subscriptions!$I$5:$I$218,Subscriptions!$B$5:$B$218,A58) | J58: =SUMIFS(Subscriptions!$J$5:$J$218,Subscriptions!$B$5:$B$218,A58) | K58: =SUMIFS(Sales_Ledger!$J$5:$J$863,Sales_Ledger!$H$5:$H$863,$A58,Sales_Ledger!$D$5:$D$863,2023) | L58: =SUMIFS(Sales_Ledger!$J$5:$J$863,Sales_Ledger!$H$5:$H$863,$A58,Sales_Ledger!$D$5:$D$863,2024) | M58: =SUMIFS(Sales_Ledger!$J$5:$J$863,Sales_Ledger!$H$5:$H$863,$A58,Sales_Ledger!$D$5:$D$863,2025) | N58: =SUM(K58:M58) | O58: Client register + Transaction records | P58: Bought | Q58: Ms Abimbola | R58: =IF(AND(I58>0,N58>I58*1.02),"Receipts exceed register contract value: check for duplicate entries, extra plots or ancillary fees",IF(AND(I58=0,N58>0),"Not in client register: contract value unknown",""))
A59: BP-C0055 | B59: Mr. Adeniji Oluwatosin Ademola | C59: 447375656023 | D59: adenijitosin01@yahoo.com | E59: Housing, Land | F59: Baay Foreshore; Green City Phase 1 (Ketu-Epe); Green City Phase 1 (Lantaba, Ketu-Epe); Land (estate not stated in source) | G59: 45875 | H59: =IF(COUNTIF(Sales_Ledger!$H$5:$H$863,A59)=0,"",_xlfn.MINIFS(Sales_Ledger!$B$5:$B$863,Sales_Ledger!$H$5:$H$863,A59)) | I59: =SUMIFS(Subscriptions!$I$5:$I$218,Subscriptions!$B$5:$B$218,A59) | J59: =SUMIFS(Subscriptions!$J$5:$J$218,Subscriptions!$B$5:$B$218,A59) | K59: =SUMIFS(Sales_Ledger!$J$5:$J$863,Sales_Ledger!$H$5:$H$863,$A59,Sales_Ledger!$D$5:$D$863,2023) | L59: =SUMIFS(Sales_Ledger!$J$5:$J$863,Sales_Ledger!$H$5:$H$863,$A59,Sales_Ledger!$D$5:$D$863,2024) | M59: =SUMIFS(Sales_Ledger!$J$5:$J$863,Sales_Ledger!$H$5:$H$863,$A59,Sales_Ledger!$D$5:$D$863,2025) | N59: =SUM(K59:M59) | O59: Client register + Transaction records | P59: Paying | Q59: Ms. Tijani Bolanle | R59: =IF(AND(I59>0,N59>I59*1.02),"Receipts exceed register contract value: check for duplicate entries, extra plots or ancillary fees",IF(AND(I59=0,N59>0),"Not in client register: contract value unknown",""))
A60: BP-C0056 | B60: Mr Adeuti Olanrewaju Babatunde | C60: 61452614036 | D60: SENT | E60: Land | F60: Green City Phase 1 (Lantaba, Ketu-Epe); Land (estate not stated in source); Land: ancillary charges | G60: 45289 | H60: =IF(COUNTIF(Sales_Ledger!$H$5:$H$863,A60)=0,"",_xlfn.MINIFS(Sales_Ledger!$B$5:$B$863,Sales_Ledger!$H$5:$H$863,A60)) | I60: =SUMIFS(Subscriptions!$I$5:$I$218,Subscriptions!$B$5:$B$218,A60) | J60: =SUMIFS(Subscriptions!$J$5:$J$218,Subscriptions!$B$5:$B$218,A60) | K60: =SUMIFS(Sales_Ledger!$J$5:$J$863,Sales_Ledger!$H$5:$H$863,$A60,Sales_Ledger!$D$5:$D$863,2023) | L60: =SUMIFS(Sales_Ledger!$J$5:$J$863,Sales_Ledger!$H$5:$H$863,$A60,Sales_Ledger!$D$5:$D$863,2024) | M60: =SUMIFS(Sales_Ledger!$J$5:$J$863,Sales_Ledger!$H$5:$H$863,$A60,Sales_Ledger!$D$5:$D$863,2025) | N60: =SUM(K60:M60) | O60: Client register + Transaction records | P60: Bought | Q60: Ms Abimbola | R60: =IF(AND(I60>0,N60>I60*1.02),"Receipts exceed register contract value: check for duplicate entries, extra plots or ancillary fees",IF(AND(I60=0,N60>0),"Not in client register: contract value unknown",""))
A61: BP-C0057 | B61: Mr Oniyide Olalouwa Blessing | E61: Land | F61: Green City Phase 1 (Lantaba, Ketu-Epe); Land (estate not stated in source) | H61: =IF(COUNTIF(Sales_Ledger!$H$5:$H$863,A61)=0,"",_xlfn.MINIFS(Sales_Ledger!$B$5:$B$863,Sales_Ledger!$H$5:$H$863,A61)) | I61: =SUMIFS(Subscriptions!$I$5:$I$218,Subscriptions!$B$5:$B$218,A61) | J61: =SUMIFS(Subscriptions!$J$5:$J$218,Subscriptions!$B$5:$B$218,A61) | K61: =SUMIFS(Sales_Ledger!$J$5:$J$863,Sales_Ledger!$H$5:$H$863,$A61,Sales_Ledger!$D$5:$D$863,2023) | L61: =SUMIFS(Sales_Ledger!$J$5:$J$863,Sales_Ledger!$H$5:$H$863,$A61,Sales_Ledger!$D$5:$D$863,2024) | M61: =SUMIFS(Sales_Ledger!$J$5:$J$863,Sales_Ledger!$H$5:$H$863,$A61,Sales_Ledger!$D$5:$D$863,2025) | N61: =SUM(K61:M61) | O61: Transaction records | R61: =IF(AND(I61>0,N61>I61*1.02),"Receipts exceed register contract value: check for duplicate entries, extra plots or ancillary fees",IF(AND(I61=0,N61>0),"Not in client register: contract value unknown",""))
A62: BP-C0058 | B62: Mr Oniyide Olaoluwa | C62: 07057815975 08171666974 | D62: SENT | E62: Land | F62: Green City Phase 1 (Lantaba, Ketu-Epe); Land (estate not stated in source); Land: ancillary charges | G62: 45289 | H62: =IF(COUNTIF(Sales_Ledger!$H$5:$H$863,A62)=0,"",_xlfn.MINIFS(Sales_Ledger!$B$5:$B$863,Sales_Ledger!$H$5:$H$863,A62)) | I62: =SUMIFS(Subscriptions!$I$5:$I$218,Subscriptions!$B$5:$B$218,A62) | J62: =SUMIFS(Subscriptions!$J$5:$J$218,Subscriptions!$B$5:$B$218,A62) | K62: =SUMIFS(Sales_Ledger!$J$5:$J$863,Sales_Ledger!$H$5:$H$863,$A62,Sales_Ledger!$D$5:$D$863,2023) | L62: =SUMIFS(Sales_Ledger!$J$5:$J$863,Sales_Ledger!$H$5:$H$863,$A62,Sales_Ledger!$D$5:$D$863,2024) | M62: =SUMIFS(Sales_Ledger!$J$5:$J$863,Sales_Ledger!$H$5:$H$863,$A62,Sales_Ledger!$D$5:$D$863,2025) | N62: =SUM(K62:M62) | O62: Client register + Transaction records | P62: Bought | Q62: Mr Charles | R62: =IF(AND(I62>0,N62>I62*1.02),"Receipts exceed register contract value: check for duplicate entries, extra plots or ancillary fees",IF(AND(I62=0,N62>0),"Not in client register: contract value unknown",""))
A63: BP-C0059 | B63: Elochukwu George | C63: 8132039018 | D63: SENT | E63: Land | F63: Green City Phase 1 (Lantaba, Ketu-Epe); Land (estate not stated in source) | G63: 45291 | H63: =IF(COUNTIF(Sales_Ledger!$H$5:$H$863,A63)=0,"",_xlfn.MINIFS(Sales_Ledger!$B$5:$B$863,Sales_Ledger!$H$5:$H$863,A63)) | I63: =SUMIFS(Subscriptions!$I$5:$I$218,Subscriptions!$B$5:$B$218,A63) | J63: =SUMIFS(Subscriptions!$J$5:$J$218,Subscriptions!$B$5:$B$218,A63) | K63: =SUMIFS(Sales_Ledger!$J$5:$J$863,Sales_Ledger!$H$5:$H$863,$A63,Sales_Ledger!$D$5:$D$863,2023) | L63: =SUMIFS(Sales_Ledger!$J$5:$J$863,Sales_Ledger!$H$5:$H$863,$A63,Sales_Ledger!$D$5:$D$863,2024) | M63: =SUMIFS(Sales_Ledger!$J$5:$J$863,Sales_Ledger!$H$5:$H$863,$A63,Sales_Ledger!$D$5:$D$863,2025) | N63: =SUM(K63:M63) | O63: Client register + Transaction records | P63: Bought | Q63: Ms Abimbola | R63: =IF(AND(I63>0,N63>I63*1.02),"Receipts exceed register contract value: check for duplicate entries, extra plots or ancillary fees",IF(AND(I63=0,N63>0),"Not in client register: contract value unknown",""))
A64: BP-C0060 | B64: Ms Mitchell Jennifer | C64: 13212970320 | D64: jenn.mitchell48@gmail.com | E64: Land | F64: Green City Phase 2 (Idobi, Ketu-Epe); Green City Phase 2 (Ketu-Epe); Heritage Garden; Land (estate not stated in source) | G64: 45526 | H64: =IF(COUNTIF(Sales_Ledger!$H$5:$H$863,A64)=0,"",_xlfn.MINIFS(Sales_Ledger!$B$5:$B$863,Sales_Ledger!$H$5:$H$863,A64)) | I64: =SUMIFS(Subscriptions!$I$5:$I$218,Subscriptions!$B$5:$B$218,A64) | J64: =SUMIFS(Subscriptions!$J$5:$J$218,Subscriptions!$B$5:$B$218,A64) | K64: =SUMIFS(Sales_Ledger!$J$5:$J$863,Sales_Ledger!$H$5:$H$863,$A64,Sales_Ledger!$D$5:$D$863,2023) | L64: =SUMIFS(Sales_Ledger!$J$5:$J$863,Sales_Ledger!$H$5:$H$863,$A64,Sales_Ledger!$D$5:$D$863,2024) | M64: =SUMIFS(Sales_Ledger!$J$5:$J$863,Sales_Ledger!$H$5:$H$863,$A64,Sales_Ledger!$D$5:$D$863,2025) | N64: =SUM(K64:M64) | O64: Client register + Transaction records | P64: Bought | Q64: Ms Celina | R64: =IF(AND(I64>0,N64>I64*1.02),"Receipts exceed register contract value: check for duplicate entries, extra plots or ancillary fees",IF(AND(I64=0,N64>0),"Not in client register: contract value unknown",""))
A65: BP-C0061 | B65: OGUNKOYA EMMANUEL | C65: 8056191865 | D65: nazareth_emmanuel@yahoo.com | E65: Land | F65: Green City Phase 2 (Idobi, Ketu-Epe); Green City Phase 2 (Ketu-Epe); Land (estate not stated in source); Land: ancillary charges | G65: 45296 | H65: =IF(COUNTIF(Sales_Ledger!$H$5:$H$863,A65)=0,"",_xlfn.MINIFS(Sales_Ledger!$B$5:$B$863,Sales_Ledger!$H$5:$H$863,A65)) | I65: =SUMIFS(Subscriptions!$I$5:$I$218,Subscriptions!$B$5:$B$218,A65) | J65: =SUMIFS(Subscriptions!$J$5:$J$218,Subscriptions!$B$5:$B$218,A65) | K65: =SUMIFS(Sales_Ledger!$J$5:$J$863,Sales_Ledger!$H$5:$H$863,$A65,Sales_Ledger!$D$5:$D$863,2023) | L65: =SUMIFS(Sales_Ledger!$J$5:$J$863,Sales_Ledger!$H$5:$H$863,$A65,Sales_Ledger!$D$5:$D$863,2024) | M65: =SUMIFS(Sales_Ledger!$J$5:$J$863,Sales_Ledger!$H$5:$H$863,$A65,Sales_Ledger!$D$5:$D$863,2025) | N65: =SUM(K65:M65) | O65: Client register + Transaction records | P65: bought | Q65: MD | R65: =IF(AND(I65>0,N65>I65*1.02),"Receipts exceed register contract value: check for duplicate entries, extra plots or ancillary fees",IF(AND(I65=0,N65>0),"Not in client register: contract value unknown",""))
A66: BP-C0062 | B66: Mr Agbaje Christopher Usiola | C66: 353879754960 | D66: SENT | E66: Land | F66: Green City Phase 1 (Ketu-Epe); Green City Phase 1 (Lantaba, Ketu-Epe) | G66: 45323 | H66: =IF(COUNTIF(Sales_Ledger!$H$5:$H$863,A66)=0,"",_xlfn.MINIFS(Sales_Ledger!$B$5:$B$863,Sales_Ledger!$H$5:$H$863,A66)) | I66: =SUMIFS(Subscriptions!$I$5:$I$218,Subscriptions!$B$5:$B$218,A66) | J66: =SUMIFS(Subscriptions!$J$5:$J$218,Subscriptions!$B$5:$B$218,A66) | K66: =SUMIFS(Sales_Ledger!$J$5:$J$863,Sales_Ledger!$H$5:$H$863,$A66,Sales_Ledger!$D$5:$D$863,2023) | L66: =SUMIFS(Sales_Ledger!$J$5:$J$863,Sales_Ledger!$H$5:$H$863,$A66,Sales_Ledger!$D$5:$D$863,2024) | M66: =SUMIFS(Sales_Ledger!$J$5:$J$863,Sales_Ledger!$H$5:$H$863,$A66,Sales_Ledger!$D$5:$D$863,2025) | N66: =SUM(K66:M66) | O66: Client register + Transaction records | P66: Bought | Q66: MD | R66: =IF(AND(I66>0,N66>I66*1.02),"Receipts exceed register contract value: check for duplicate entries, extra plots or ancillary fees",IF(AND(I66=0,N66>0),"Not in client register: contract value unknown",""))
A67: BP-C0063 | B67: Omodara Adewale David | C67: 7039678467 | D67: adewaledavid777@gmail.com | E67: Land | F67: Green City Phase 2 (Ketu-Epe) | G67: 45326 | H67: =IF(COUNTIF(Sales_Ledger!$H$5:$H$863,A67)=0,"",_xlfn.MINIFS(Sales_Ledger!$B$5:$B$863,Sales_Ledger!$H$5:$H$863,A67)) | I67: =SUMIFS(Subscriptions!$I$5:$I$218,Subscriptions!$B$5:$B$218,A67) | J67: =SUMIFS(Subscriptions!$J$5:$J$218,Subscriptions!$B$5:$B$218,A67) | K67: =SUMIFS(Sales_Ledger!$J$5:$J$863,Sales_Ledger!$H$5:$H$863,$A67,Sales_Ledger!$D$5:$D$863,2023) | L67: =SUMIFS(Sales_Ledger!$J$5:$J$863,Sales_Ledger!$H$5:$H$863,$A67,Sales_Ledger!$D$5:$D$863,2024) | M67: =SUMIFS(Sales_Ledger!$J$5:$J$863,Sales_Ledger!$H$5:$H$863,$A67,Sales_Ledger!$D$5:$D$863,2025) | N67: =SUM(K67:M67) | O67: Client register + Transaction records | P67: Bought | Q67: Ms Taiwo Ajibola | R67: =IF(AND(I67>0,N67>I67*1.02),"Receipts exceed register contract value: check for duplicate entries, extra plots or ancillary fees",IF(AND(I67=0,N67>0),"Not in client register: contract value unknown",""))
A68: BP-C0064 | B68: Okosun Damian | C68: 8034367176 | D68: damianokosun@gmail.com | E68: Land | F68: Green City Phase 2 (Ketu-Epe) | G68: 45327 | H68: =IF(COUNTIF(Sales_Ledger!$H$5:$H$863,A68)=0,"",_xlfn.MINIFS(Sales_Ledger!$B$5:$B$863,Sales_Ledger!$H$5:$H$863,A68)) | I68: =SUMIFS(Subscriptions!$I$5:$I$218,Subscriptions!$B$5:$B$218,A68) | J68: =SUMIFS(Subscriptions!$J$5:$J$218,Subscriptions!$B$5:$B$218,A68) | K68: =SUMIFS(Sales_Ledger!$J$5:$J$863,Sales_Ledger!$H$5:$H$863,$A68,Sales_Ledger!$D$5:$D$863,2023) | L68: =SUMIFS(Sales_Ledger!$J$5:$J$863,Sales_Ledger!$H$5:$H$863,$A68,Sales_Ledger!$D$5:$D$863,2024) | M68: =SUMIFS(Sales_Ledger!$J$5:$J$863,Sales_Ledger!$H$5:$H$863,$A68,Sales_Ledger!$D$5:$D$863,2025) | N68: =SUM(K68:M68) | O68: Client register + Transaction records | P68: Bought | Q68: Ms Bolanle | R68: =IF(AND(I68>0,N68>I68*1.02),"Receipts exceed register contract value: check for duplicate entries, extra plots or ancillary fees",IF(AND(I68=0,N68>0),"Not in client register: contract value unknown",""))
A69: BP-C0065 | B69: Mr Yusuf Saheed Taiwo | C69: 8102375562 | D69: yusufsaheedtaiwo@gmail.com | E69: Land | F69: Green City Phase 2 (Ketu-Epe) | G69: 45328 | H69: =IF(COUNTIF(Sales_Ledger!$H$5:$H$863,A69)=0,"",_xlfn.MINIFS(Sales_Ledger!$B$5:$B$863,Sales_Ledger!$H$5:$H$863,A69)) | I69: =SUMIFS(Subscriptions!$I$5:$I$218,Subscriptions!$B$5:$B$218,A69) | J69: =SUMIFS(Subscriptions!$J$5:$J$218,Subscriptions!$B$5:$B$218,A69) | K69: =SUMIFS(Sales_Ledger!$J$5:$J$863,Sales_Ledger!$H$5:$H$863,$A69,Sales_Ledger!$D$5:$D$863,2023) | L69: =SUMIFS(Sales_Ledger!$J$5:$J$863,Sales_Ledger!$H$5:$H$863,$A69,Sales_Ledger!$D$5:$D$863,2024) | M69: =SUMIFS(Sales_Ledger!$J$5:$J$863,Sales_Ledger!$H$5:$H$863,$A69,Sales_Ledger!$D$5:$D$863,2025) | N69: =SUM(K69:M69) | O69: Client register + Transaction records | P69: Bought | Q69: MD | R69: =IF(AND(I69>0,N69>I69*1.02),"Receipts exceed register contract value: check for duplicate entries, extra plots or ancillary fees",IF(AND(I69=0,N69>0),"Not in client register: contract value unknown",""))
A70: BP-C0066 | B70: Miss Omosanya Dotun Akeju | C70: 8052506221 | D70: omosanyaakeju4@gmail.com | E70: Land | F70: Green City Phase 2 (Ketu-Epe); Green City Phase 3 (Omu-Epe); Land (estate not stated in source); Land: ancillary charges | G70: 45343 | H70: =IF(COUNTIF(Sales_Ledger!$H$5:$H$863,A70)=0,"",_xlfn.MINIFS(Sales_Ledger!$B$5:$B$863,Sales_Ledger!$H$5:$H$863,A70)) | I70: =SUMIFS(Subscriptions!$I$5:$I$218,Subscriptions!$B$5:$B$218,A70) | J70: =SUMIFS(Subscriptions!$J$5:$J$218,Subscriptions!$B$5:$B$218,A70) | K70: =SUMIFS(Sales_Ledger!$J$5:$J$863,Sales_Ledger!$H$5:$H$863,$A70,Sales_Ledger!$D$5:$D$863,2023) | L70: =SUMIFS(Sales_Ledger!$J$5:$J$863,Sales_Ledger!$H$5:$H$863,$A70,Sales_Ledger!$D$5:$D$863,2024) | M70: =SUMIFS(Sales_Ledger!$J$5:$J$863,Sales_Ledger!$H$5:$H$863,$A70,Sales_Ledger!$D$5:$D$863,2025) | N70: =SUM(K70:M70) | O70: Client register + Transaction records | P70: Bought | Q70: Ms Bola, Ms Oji Blessing | R70: =IF(AND(I70>0,N70>I70*1.02),"Receipts exceed register contract value: check for duplicate entries, extra plots or ancillary fees",IF(AND(I70=0,N70>0),"Not in client register: contract value unknown",""))
A71: BP-C0067 | B71: Mr Odje Theophilus Bamidele | C71: 8164722166 | D71: theoodje@gmail.com | E71: Land | F71: Green City Phase 2 (Ketu-Epe) | G71: 45348 | H71: =IF(COUNTIF(Sales_Ledger!$H$5:$H$863,A71)=0,"",_xlfn.MINIFS(Sales_Ledger!$B$5:$B$863,Sales_Ledger!$H$5:$H$863,A71)) | I71: =SUMIFS(Subscriptions!$I$5:$I$218,Subscriptions!$B$5:$B$218,A71) | J71: =SUMIFS(Subscriptions!$J$5:$J$218,Subscriptions!$B$5:$B$218,A71) | K71: =SUMIFS(Sales_Ledger!$J$5:$J$863,Sales_Ledger!$H$5:$H$863,$A71,Sales_Ledger!$D$5:$D$863,2023) | L71: =SUMIFS(Sales_Ledger!$J$5:$J$863,Sales_Ledger!$H$5:$H$863,$A71,Sales_Ledger!$D$5:$D$863,2024) | M71: =SUMIFS(Sales_Ledger!$J$5:$J$863,Sales_Ledger!$H$5:$H$863,$A71,Sales_Ledger!$D$5:$D$863,2025) | N71: =SUM(K71:M71) | O71: Client register + Transaction records | P71: Bought | Q71: Mr Praise | R71: =IF(AND(I71>0,N71>I71*1.02),"Receipts exceed register contract value: check for duplicate entries, extra plots or ancillary fees",IF(AND(I71=0,N71>0),"Not in client register: contract value unknown",""))
A72: BP-C0068 | B72: Miss Ebhotah Sharon Aisosa | C72: 447947786248 | D72: cadizsharon28@gmail.com | E72: Land | F72: Green City Phase 2 (Idobi, Ketu-Epe); Green City Phase 2 (Ketu-Epe); Green City Phase 3 (Omu-Epe); Land (estate not stated in source); Land: ancillary charges | G72: 45350 | H72: =IF(COUNTIF(Sales_Ledger!$H$5:$H$863,A72)=0,"",_xlfn.MINIFS(Sales_Ledger!$B$5:$B$863,Sales_Ledger!$H$5:$H$863,A72)) | I72: =SUMIFS(Subscriptions!$I$5:$I$218,Subscriptions!$B$5:$B$218,A72) | J72: =SUMIFS(Subscriptions!$J$5:$J$218,Subscriptions!$B$5:$B$218,A72) | K72: =SUMIFS(Sales_Ledger!$J$5:$J$863,Sales_Ledger!$H$5:$H$863,$A72,Sales_Ledger!$D$5:$D$863,2023) | L72: =SUMIFS(Sales_Ledger!$J$5:$J$863,Sales_Ledger!$H$5:$H$863,$A72,Sales_Ledger!$D$5:$D$863,2024) | M72: =SUMIFS(Sales_Ledger!$J$5:$J$863,Sales_Ledger!$H$5:$H$863,$A72,Sales_Ledger!$D$5:$D$863,2025) | N72: =SUM(K72:M72) | O72: Client register + Transaction records | P72: Bought | Q72: Ms Blessing, Ms blessing | R72: =IF(AND(I72>0,N72>I72*1.02),"Receipts exceed register contract value: check for duplicate entries, extra plots or ancillary fees",IF(AND(I72=0,N72>0),"Not in client register: contract value unknown",""))
A73: BP-C0069 | B73: Mr Agbaje Christopher Usiala | E73: Land | F73: Green City Phase 1 (Lantaba, Ketu-Epe) | H73: =IF(COUNTIF(Sales_Ledger!$H$5:$H$863,A73)=0,"",_xlfn.MINIFS(Sales_Ledger!$B$5:$B$863,Sales_Ledger!$H$5:$H$863,A73)) | I73: =SUMIFS(Subscriptions!$I$5:$I$218,Subscriptions!$B$5:$B$218,A73) | J73: =SUMIFS(Subscriptions!$J$5:$J$218,Subscriptions!$B$5:$B$218,A73) | K73: =SUMIFS(Sales_Ledger!$J$5:$J$863,Sales_Ledger!$H$5:$H$863,$A73,Sales_Ledger!$D$5:$D$863,2023) | L73: =SUMIFS(Sales_Ledger!$J$5:$J$863,Sales_Ledger!$H$5:$H$863,$A73,Sales_Ledger!$D$5:$D$863,2024) | M73: =SUMIFS(Sales_Ledger!$J$5:$J$863,Sales_Ledger!$H$5:$H$863,$A73,Sales_Ledger!$D$5:$D$863,2025) | N73: =SUM(K73:M73) | O73: Transaction records | R73: =IF(AND(I73>0,N73>I73*1.02),"Receipts exceed register contract value: check for duplicate entries, extra plots or ancillary fees",IF(AND(I73=0,N73>0),"Not in client register: contract value unknown",""))
A74: BP-C0070 | B74: Mr Daniel Ayodeji Adeogun | C74: 8143671690 | D74: ayodejimoses96@gmail.com | E74: Land | F74: Green City Phase 2 (Ketu-Epe); Land: ancillary charges | G74: 45357 | H74: =IF(COUNTIF(Sales_Ledger!$H$5:$H$863,A74)=0,"",_xlfn.MINIFS(Sales_Ledger!$B$5:$B$863,Sales_Ledger!$H$5:$H$863,A74)) | I74: =SUMIFS(Subscriptions!$I$5:$I$218,Subscriptions!$B$5:$B$218,A74) | J74: =SUMIFS(Subscriptions!$J$5:$J$218,Subscriptions!$B$5:$B$218,A74) | K74: =SUMIFS(Sales_Ledger!$J$5:$J$863,Sales_Ledger!$H$5:$H$863,$A74,Sales_Ledger!$D$5:$D$863,2023) | L74: =SUMIFS(Sales_Ledger!$J$5:$J$863,Sales_Ledger!$H$5:$H$863,$A74,Sales_Ledger!$D$5:$D$863,2024) | M74: =SUMIFS(Sales_Ledger!$J$5:$J$863,Sales_Ledger!$H$5:$H$863,$A74,Sales_Ledger!$D$5:$D$863,2025) | N74: =SUM(K74:M74) | O74: Client register + Transaction records | P74: Bought | Q74: Ms Taiwo Ajibola | R74: =IF(AND(I74>0,N74>I74*1.02),"Receipts exceed register contract value: check for duplicate entries, extra plots or ancillary fees",IF(AND(I74=0,N74>0),"Not in client register: contract value unknown",""))
A75: BP-C0071 | B75: Miss Oyebola Moyosoreoluwa Boluwatife | C75: 8098338600 | D75: olayinka_oyebola@hotmail.com | E75: Land | F75: Green City Phase 2 (Ketu-Epe) | G75: 45359 | H75: =IF(COUNTIF(Sales_Ledger!$H$5:$H$863,A75)=0,"",_xlfn.MINIFS(Sales_Ledger!$B$5:$B$863,Sales_Ledger!$H$5:$H$863,A75)) | I75: =SUMIFS(Subscriptions!$I$5:$I$218,Subscriptions!$B$5:$B$218,A75) | J75: =SUMIFS(Subscriptions!$J$5:$J$218,Subscriptions!$B$5:$B$218,A75) | K75: =SUMIFS(Sales_Ledger!$J$5:$J$863,Sales_Ledger!$H$5:$H$863,$A75,Sales_Ledger!$D$5:$D$863,2023) | L75: =SUMIFS(Sales_Ledger!$J$5:$J$863,Sales_Ledger!$H$5:$H$863,$A75,Sales_Ledger!$D$5:$D$863,2024) | M75: =SUMIFS(Sales_Ledger!$J$5:$J$863,Sales_Ledger!$H$5:$H$863,$A75,Sales_Ledger!$D$5:$D$863,2025) | N75: =SUM(K75:M75) | O75: Client register + Transaction records | P75: Bought | Q75: Mr Ayo | R75: =IF(AND(I75>0,N75>I75*1.02),"Receipts exceed register contract value: check for duplicate entries, extra plots or ancillary fees",IF(AND(I75=0,N75>0),"Not in client register: contract value unknown",""))
A76: BP-C0072 | B76: Mr Oyebola Ajibola Ayobami | C76: 8098338600 | D76: olayinka_oyebola@hotmail.com | E76: Land | F76: Green City Phase 2 (Ketu-Epe); Land: ancillary charges | G76: 45359 | H76: =IF(COUNTIF(Sales_Ledger!$H$5:$H$863,A76)=0,"",_xlfn.MINIFS(Sales_Ledger!$B$5:$B$863,Sales_Ledger!$H$5:$H$863,A76)) | I76: =SUMIFS(Subscriptions!$I$5:$I$218,Subscriptions!$B$5:$B$218,A76) | J76: =SUMIFS(Subscriptions!$J$5:$J$218,Subscriptions!$B$5:$B$218,A76) | K76: =SUMIFS(Sales_Ledger!$J$5:$J$863,Sales_Ledger!$H$5:$H$863,$A76,Sales_Ledger!$D$5:$D$863,2023) | L76: =SUMIFS(Sales_Ledger!$J$5:$J$863,Sales_Ledger!$H$5:$H$863,$A76,Sales_Ledger!$D$5:$D$863,2024) | M76: =SUMIFS(Sales_Ledger!$J$5:$J$863,Sales_Ledger!$H$5:$H$863,$A76,Sales_Ledger!$D$5:$D$863,2025) | N76: =SUM(K76:M76) | O76: Client register + Transaction records | P76: Bought | Q76: Mr Ayo | R76: =IF(AND(I76>0,N76>I76*1.02),"Receipts exceed register contract value: check for duplicate entries, extra plots or ancillary fees",IF(AND(I76=0,N76>0),"Not in client register: contract value unknown",""))
A77: BP-C0073 | B77: Mr Oyebola Temiloluwa Olayinka | C77: 8098338600 | D77: olayinka_oyebola@hotmail.com | E77: Land | F77: Green City Phase 2 (Ketu-Epe) | G77: 45359 | H77: =IF(COUNTIF(Sales_Ledger!$H$5:$H$863,A77)=0,"",_xlfn.MINIFS(Sales_Ledger!$B$5:$B$863,Sales_Ledger!$H$5:$H$863,A77)) | I77: =SUMIFS(Subscriptions!$I$5:$I$218,Subscriptions!$B$5:$B$218,A77) | J77: =SUMIFS(Subscriptions!$J$5:$J$218,Subscriptions!$B$5:$B$218,A77) | K77: =SUMIFS(Sales_Ledger!$J$5:$J$863,Sales_Ledger!$H$5:$H$863,$A77,Sales_Ledger!$D$5:$D$863,2023) | L77: =SUMIFS(Sales_Ledger!$J$5:$J$863,Sales_Ledger!$H$5:$H$863,$A77,Sales_Ledger!$D$5:$D$863,2024) | M77: =SUMIFS(Sales_Ledger!$J$5:$J$863,Sales_Ledger!$H$5:$H$863,$A77,Sales_Ledger!$D$5:$D$863,2025) | N77: =SUM(K77:M77) | O77: Client register + Transaction records | P77: Bought | Q77: Mr Ayo | R77: =IF(AND(I77>0,N77>I77*1.02),"Receipts exceed register contract value: check for duplicate entries, extra plots or ancillary fees",IF(AND(I77=0,N77>0),"Not in client register: contract value unknown",""))
A78: BP-C0074 | B78: Mrs Oloniluyi Victoria Adetutu Iyabode | C78: 447828073149 | D78: SENT | E78: Land | F78: Green City Phase 1 (Lantaba, Ketu-Epe); Land: ancillary charges | G78: 45359 | H78: =IF(COUNTIF(Sales_Ledger!$H$5:$H$863,A78)=0,"",_xlfn.MINIFS(Sales_Ledger!$B$5:$B$863,Sales_Ledger!$H$5:$H$863,A78)) | I78: =SUMIFS(Subscriptions!$I$5:$I$218,Subscriptions!$B$5:$B$218,A78) | J78: =SUMIFS(Subscriptions!$J$5:$J$218,Subscriptions!$B$5:$B$218,A78) | K78: =SUMIFS(Sales_Ledger!$J$5:$J$863,Sales_Ledger!$H$5:$H$863,$A78,Sales_Ledger!$D$5:$D$863,2023) | L78: =SUMIFS(Sales_Ledger!$J$5:$J$863,Sales_Ledger!$H$5:$H$863,$A78,Sales_Ledger!$D$5:$D$863,2024) | M78: =SUMIFS(Sales_Ledger!$J$5:$J$863,Sales_Ledger!$H$5:$H$863,$A78,Sales_Ledger!$D$5:$D$863,2025) | N78: =SUM(K78:M78) | O78: Client register + Transaction records | P78: Bought | Q78: MD | R78: =IF(AND(I78>0,N78>I78*1.02),"Receipts exceed register contract value: check for duplicate entries, extra plots or ancillary fees",IF(AND(I78=0,N78>0),"Not in client register: contract value unknown",""))
A79: BP-C0075 | B79: Miss Ogidan funmilayo Jumoke | C79: 971543457569 | D79: funmilayojumaika26@gmail.com | E79: Land | F79: Green City Phase 2 (Ketu-Epe); Land: ancillary charges | G79: 45360 | H79: =IF(COUNTIF(Sales_Ledger!$H$5:$H$863,A79)=0,"",_xlfn.MINIFS(Sales_Ledger!$B$5:$B$863,Sales_Ledger!$H$5:$H$863,A79)) | I79: =SUMIFS(Subscriptions!$I$5:$I$218,Subscriptions!$B$5:$B$218,A79) | J79: =SUMIFS(Subscriptions!$J$5:$J$218,Subscriptions!$B$5:$B$218,A79) | K79: =SUMIFS(Sales_Ledger!$J$5:$J$863,Sales_Ledger!$H$5:$H$863,$A79,Sales_Ledger!$D$5:$D$863,2023) | L79: =SUMIFS(Sales_Ledger!$J$5:$J$863,Sales_Ledger!$H$5:$H$863,$A79,Sales_Ledger!$D$5:$D$863,2024) | M79: =SUMIFS(Sales_Ledger!$J$5:$J$863,Sales_Ledger!$H$5:$H$863,$A79,Sales_Ledger!$D$5:$D$863,2025) | N79: =SUM(K79:M79) | O79: Client register + Transaction records | P79: Bought | Q79: Mr Ogidan Abiodun | R79: =IF(AND(I79>0,N79>I79*1.02),"Receipts exceed register contract value: check for duplicate entries, extra plots or ancillary fees",IF(AND(I79=0,N79>0),"Not in client register: contract value unknown",""))
A80: BP-C0076 | B80: Ojo Ayomide Babatunde | C80: 8168964986 | D80: ojobabatunde12@gmail.com | E80: Land | F80: Green City Phase 2 (Ketu-Epe); Land: ancillary charges | G80: 45360 | H80: =IF(COUNTIF(Sales_Ledger!$H$5:$H$863,A80)=0,"",_xlfn.MINIFS(Sales_Ledger!$B$5:$B$863,Sales_Ledger!$H$5:$H$863,A80)) | I80: =SUMIFS(Subscriptions!$I$5:$I$218,Subscriptions!$B$5:$B$218,A80) | J80: =SUMIFS(Subscriptions!$J$5:$J$218,Subscriptions!$B$5:$B$218,A80) | K80: =SUMIFS(Sales_Ledger!$J$5:$J$863,Sales_Ledger!$H$5:$H$863,$A80,Sales_Ledger!$D$5:$D$863,2023) | L80: =SUMIFS(Sales_Ledger!$J$5:$J$863,Sales_Ledger!$H$5:$H$863,$A80,Sales_Ledger!$D$5:$D$863,2024) | M80: =SUMIFS(Sales_Ledger!$J$5:$J$863,Sales_Ledger!$H$5:$H$863,$A80,Sales_Ledger!$D$5:$D$863,2025) | N80: =SUM(K80:M80) | O80: Client register + Transaction records | P80: Bought | Q80: Ms Olayinka Fasuyi | R80: =IF(AND(I80>0,N80>I80*1.02),"Receipts exceed register contract value: check for duplicate entries, extra plots or ancillary fees",IF(AND(I80=0,N80>0),"Not in client register: contract value unknown",""))
A81: BP-C0077 | B81: Mr Uebari Sorbari Godwin | C81: 8103010747 | D81: sorbarigodwin@gmail.com | E81: Land | F81: Green City Phase 2 (Ketu-Epe); Green City Phase 3 Extension (Omu-Epe); Land (estate not stated in source) | G81: 45706 | H81: =IF(COUNTIF(Sales_Ledger!$H$5:$H$863,A81)=0,"",_xlfn.MINIFS(Sales_Ledger!$B$5:$B$863,Sales_Ledger!$H$5:$H$863,A81)) | I81: =SUMIFS(Subscriptions!$I$5:$I$218,Subscriptions!$B$5:$B$218,A81) | J81: =SUMIFS(Subscriptions!$J$5:$J$218,Subscriptions!$B$5:$B$218,A81) | K81: =SUMIFS(Sales_Ledger!$J$5:$J$863,Sales_Ledger!$H$5:$H$863,$A81,Sales_Ledger!$D$5:$D$863,2023) | L81: =SUMIFS(Sales_Ledger!$J$5:$J$863,Sales_Ledger!$H$5:$H$863,$A81,Sales_Ledger!$D$5:$D$863,2024) | M81: =SUMIFS(Sales_Ledger!$J$5:$J$863,Sales_Ledger!$H$5:$H$863,$A81,Sales_Ledger!$D$5:$D$863,2025) | N81: =SUM(K81:M81) | O81: Client register + Transaction records | P81: Bought | Q81: Ms Elizabeth | R81: =IF(AND(I81>0,N81>I81*1.02),"Receipts exceed register contract value: check for duplicate entries, extra plots or ancillary fees",IF(AND(I81=0,N81>0),"Not in client register: contract value unknown",""))
A82: BP-C0078 | B82: Miss Bingham Kendra | C82: 16014151259 | D82: kendrabingham@yhaoo.com | E82: Land | F82: Green City Phase 1 (Lantaba, Ketu-Epe); Green City Phase 2 (Ketu-Epe); Land: ancillary charges | G82: 45362 | H82: =IF(COUNTIF(Sales_Ledger!$H$5:$H$863,A82)=0,"",_xlfn.MINIFS(Sales_Ledger!$B$5:$B$863,Sales_Ledger!$H$5:$H$863,A82)) | I82: =SUMIFS(Subscriptions!$I$5:$I$218,Subscriptions!$B$5:$B$218,A82) | J82: =SUMIFS(Subscriptions!$J$5:$J$218,Subscriptions!$B$5:$B$218,A82) | K82: =SUMIFS(Sales_Ledger!$J$5:$J$863,Sales_Ledger!$H$5:$H$863,$A82,Sales_Ledger!$D$5:$D$863,2023) | L82: =SUMIFS(Sales_Ledger!$J$5:$J$863,Sales_Ledger!$H$5:$H$863,$A82,Sales_Ledger!$D$5:$D$863,2024) | M82: =SUMIFS(Sales_Ledger!$J$5:$J$863,Sales_Ledger!$H$5:$H$863,$A82,Sales_Ledger!$D$5:$D$863,2025) | N82: =SUM(K82:M82) | O82: Client register + Transaction records | P82: Bought | Q82: Ms Abimbola | R82: =IF(AND(I82>0,N82>I82*1.02),"Receipts exceed register contract value: check for duplicate entries, extra plots or ancillary fees",IF(AND(I82=0,N82>0),"Not in client register: contract value unknown",""))
